Workbook
Name CapMonth: 'Absorption Schedule'!#REF!
Name CapPct: 'Absorption Schedule'!#REF!

Sheet INPUTS

Sheet T-12 Inputs
B2: Property: | D2: Date of Financials | E2: 46113
D4: 1 | E4: =+D4+1 -> 2 | F4: =+E4+1 -> 3 | G4: =+F4+1 -> 4 | H4: =+G4+1 -> 5 | I4: =+H4+1 -> 6 | J4: =+I4+1 -> 7 | K4: =+J4+1 -> 8 | L4: =+K4+1 -> 9 | ... O4: =+N4+1 -> 12 | S4: T-1 Trends | T4: T-3 Trends | U4: T-6 Trends | V4: T-9 Trends | W4: T-12 Trends
B5: REVENUE
A6: Line Item | B6: Notes | C6: Sub Notes | D6: =EOMONTH(E6,-1) -> 45808 | E6: =EOMONTH(F6,-1) -> 45838 | F6: =EOMONTH(G6,-1) -> 45869 | G6: =EOMONTH(H6,-1) -> 45900 | H6: =EOMONTH(I6,-1) -> 45930 | I6: =EOMONTH(J6,-1) -> 45961 | J6: =EOMONTH(K6,-1) -> 45991 | K6: =EOMONTH(L6,-1) -> 46022 | ... N6: =EOMONTH(O6,-1) -> 46112 | O6: =+E2 -> 46113 | Q6: Total
Q7: =IFERROR(SUM(D7:O7),"") -> 0 | S7: =+SUM(O7)*12 -> 0 | T7: =+SUM(M7:O7)*4 -> 0 | U7: =+SUM(J7:O7)*2 -> 0 | V7: =+SUM(G7:O7)/9*12 -> 0 | W7: =+SUM(D7:O7) -> 0
Q8: =IFERROR(SUM(D8:O8),"") -> 0 | S8: =+SUM(O8)*12 -> 0 | T8: =+SUM(M8:O8)*4 -> 0 | U8: =+SUM(J8:O8)*2 -> 0 | V8: =+SUM(G8:O8)/9*12 -> 0 | W8: =+SUM(D8:O8) -> 0 | Y8: {=+SUMPRODUCT(D7:O100*(A7:A100="GPR"))} -> 0
Q9: =IFERROR(SUM(D9:O9),"") -> 0 | S9: =+SUM(O9)*12 -> 0 | T9: =+SUM(M9:O9)*4 -> 0 | U9: =+SUM(J9:O9)*2 -> 0 | V9: =+SUM(G9:O9)/9*12 -> 0 | W9: =+SUM(D9:O9) -> 0
Q10: =IFERROR(SUM(D10:O10),"") -> 0 | S10: =+SUM(O10)*12 -> 0 | T10: =+SUM(M10:O10)*4 -> 0 | U10: =+SUM(J10:O10)*2 -> 0 | V10: =+SUM(G10:O10)/9*12 -> 0 | W10: =+SUM(D10:O10) -> 0
Q11: =IFERROR(SUM(D11:O11),"") -> 0 | S11: =+SUM(O11)*12 -> 0 | T11: =+SUM(M11:O11)*4 -> 0 | U11: =+SUM(J11:O11)*2 -> 0 | V11: =+SUM(G11:O11)/9*12 -> 0 | W11: =+SUM(D11:O11) -> 0
Q12: =IFERROR(SUM(D12:O12),"") -> 0 | S12: =+SUM(O12)*12 -> 0 | T12: =+SUM(M12:O12)*4 -> 0 | U12: =+SUM(J12:O12)*2 -> 0 | V12: =+SUM(G12:O12)/9*12 -> 0 | W12: =+SUM(D12:O12) -> 0
Q13: =IFERROR(SUM(D13:O13),"") -> 0 | S13: =+SUM(O13)*12 -> 0 | T13: =+SUM(M13:O13)*4 -> 0 | U13: =+SUM(J13:O13)*2 -> 0 | V13: =+SUM(G13:O13)/9*12 -> 0 | W13: =+SUM(D13:O13) -> 0
Q14: =IFERROR(SUM(D14:O14),"") -> 0 | S14: =+SUM(O14)*12 -> 0 | T14: =+SUM(M14:O14)*4 -> 0 | U14: =+SUM(J14:O14)*2 -> 0 | V14: =+SUM(G14:O14)/9*12 -> 0 | W14: =+SUM(D14:O14) -> 0
Q15: =IFERROR(SUM(D15:O15),"") -> 0 | S15: =+SUM(O15)*12 -> 0 | T15: =+SUM(M15:O15)*4 -> 0 | U15: =+SUM(J15:O15)*2 -> 0 | V15: =+SUM(G15:O15)/9*12 -> 0 | W15: =+SUM(D15:O15) -> 0
Q16: =IFERROR(SUM(D16:O16),"") -> 0 | S16: =+SUM(O16)*12 -> 0 | T16: =+SUM(M16:O16)*4 -> 0 | U16: =+SUM(J16:O16)*2 -> 0 | V16: =+SUM(G16:O16)/9*12 -> 0 | W16: =+SUM(D16:O16) -> 0
Q17: =IFERROR(SUM(D17:O17),"") -> 0 | S17: =+SUM(O17)*12 -> 0 | T17: =+SUM(M17:O17)*4 -> 0 | U17: =+SUM(J17:O17)*2 -> 0 | V17: =+SUM(G17:O17)/9*12 -> 0 | W17: =+SUM(D17:O17) -> 0
Q18: =IFERROR(SUM(D18:O18),"") -> 0 | S18: =+SUM(O18)*12 -> 0 | T18: =+SUM(M18:O18)*4 -> 0 | U18: =+SUM(J18:O18)*2 -> 0 | V18: =+SUM(G18:O18)/9*12 -> 0 | W18: =+SUM(D18:O18) -> 0
Q19: =IFERROR(SUM(D19:O19),"") -> 0 | S19: =+SUM(O19)*12 -> 0 | T19: =+SUM(M19:O19)*4 -> 0 | U19: =+SUM(J19:O19)*2 -> 0 | V19: =+SUM(G19:O19)/9*12 -> 0 | W19: =+SUM(D19:O19) -> 0
Q20: =IFERROR(SUM(D20:O20),"") -> 0 | S20: =+SUM(O20)*12 -> 0 | T20: =+SUM(M20:O20)*4 -> 0 | U20: =+SUM(J20:O20)*2 -> 0 | V20: =+SUM(G20:O20)/9*12 -> 0 | W20: =+SUM(D20:O20) -> 0
... Q58: =IFERROR(SUM(D58:O58),"") -> 0 | S58: =+SUM(O58)*12 -> 0 | T58: =+SUM(M58:O58)*4 -> 0 | U58: =+SUM(J58:O58)*2 -> 0 | V58: =+SUM(G58:O58)/9*12 -> 0 | W58: =+SUM(D58:O58) -> 0
Q59: =IFERROR(SUM(O59:O59),"") -> 0 | S59: =+SUM(O59)*12 -> 0 | T59: =+SUM(M59:O59)*4 -> 0 | U59: =+SUM(J59:O59)*2 -> 0 | V59: =+SUM(G59:O59)/9*12 -> 0 | W59: =+SUM(D59:O59) -> 0
Q60: =IFERROR(SUM(D60:O60),"") -> 0 | S60: =+SUM(O60)*12 -> 0 | T60: =+SUM(M60:O60)*4 -> 0 | U60: =+SUM(J60:O60)*2 -> 0 | V60: =+SUM(G60:O60)/9*12 -> 0 | W60: =+SUM(D60:O60) -> 0
Q61: =IFERROR(SUM(D61:O61),"") -> 0 | S61: =+SUM(O61)*12 -> 0 | T61: =+SUM(M61:O61)*4 -> 0 | U61: =+SUM(J61:O61)*2 -> 0 | V61: =+SUM(G61:O61)/9*12 -> 0 | W61: =+SUM(D61:O61) -> 0
Q62: =IFERROR(SUM(D62:O62),"") -> 0 | S62: =+SUM(O62)*12 -> 0 | T62: =+SUM(M62:O62)*4 -> 0 | U62: =+SUM(J62:O62)*2 -> 0 | V62: =+SUM(G62:O62)/9*12 -> 0 | W62: =+SUM(D62:O62) -> 0
Q63: =IFERROR(SUM(D63:O63),"") -> 0 | S63: =+SUM(O63)*12 -> 0 | T63: =+SUM(M63:O63)*4 -> 0 | U63: =+SUM(J63:O63)*2 -> 0 | V63: =+SUM(G63:O63)/9*12 -> 0 | W63: =+SUM(D63:O63) -> 0
Q64: =IFERROR(SUM(D64:O64),"") -> 0 | S64: =+SUM(O64)*12 -> 0 | T64: =+SUM(M64:O64)*4 -> 0 | U64: =+SUM(J64:O64)*2 -> 0 | V64: =+SUM(G64:O64)/9*12 -> 0 | W64: =+SUM(D64:O64) -> 0
Q65: =IFERROR(SUM(D65:O65),"") -> 0 | S65: =+SUM(O65)*12 -> 0 | T65: =+SUM(M65:O65)*4 -> 0 | U65: =+SUM(J65:O65)*2 -> 0 | V65: =+SUM(G65:O65)/9*12 -> 0 | W65: =+SUM(D65:O65) -> 0
Q66: =IFERROR(SUM(D66:O66),"") -> 0 | S66: =+SUM(O66)*12 -> 0 | T66: =+SUM(M66:O66)*4 -> 0 | U66: =+SUM(J66:O66)*2 -> 0 | V66: =+SUM(G66:O66)/9*12 -> 0 | W66: =+SUM(D66:O66) -> 0
Q67: =IFERROR(SUM(D67:O67),"") -> 0 | S67: =+SUM(O67)*12 -> 0 | T67: =+SUM(M67:O67)*4 -> 0 | U67: =+SUM(J67:O67)*2 -> 0 | V67: =+SUM(G67:O67)/9*12 -> 0 | W67: =+SUM(D67:O67) -> 0
Q68: =IFERROR(SUM(D68:O68),"") -> 0 | S68: =+SUM(O68)*12 -> 0 | T68: =+SUM(M68:O68)*4 -> 0 | U68: =+SUM(J68:O68)*2 -> 0 | V68: =+SUM(G68:O68)/9*12 -> 0 | W68: =+SUM(D68:O68) -> 0
Q69: =IFERROR(SUM(D69:O69),"") -> 0 | S69: =+SUM(O69)*12 -> 0 | T69: =+SUM(M69:O69)*4 -> 0 | U69: =+SUM(J69:O69)*2 -> 0 | V69: =+SUM(G69:O69)/9*12 -> 0 | W69: =+SUM(D69:O69) -> 0
Q70: =IFERROR(SUM(D70:O70),"") -> 0 | S70: =+SUM(O70)*12 -> 0 | T70: =+SUM(M70:O70)*4 -> 0 | U70: =+SUM(J70:O70)*2 -> 0 | V70: =+SUM(G70:O70)/9*12 -> 0 | W70: =+SUM(D70:O70) -> 0
Q71: =IFERROR(SUM(D71:O71),"") -> 0 | S71: =+SUM(O71)*12 -> 0 | T71: =+SUM(M71:O71)*4 -> 0 | U71: =+SUM(J71:O71)*2 -> 0 | V71: =+SUM(G71:O71)/9*12 -> 0 | W71: =+SUM(D71:O71) -> 0
... Q100: =IFERROR(SUM(D100:O100),"") -> 0 | S100: =+SUM(O100)*12 -> 0 | T100: =+SUM(M100:O100)*4 -> 0 | U100: =+SUM(J100:O100)*2 -> 0 | V100: =+SUM(G100:O100)/9*12 -> 0 | W100: =+SUM(D100:O100) -> 0
B101: Total | D101: =+SUM(D7:D100) -> 0 | E101: =+SUM(E7:E100) -> 0 | F101: =+SUM(F7:F100) -> 0 | G101: =+SUM(G7:G100) -> 0 | H101: =+SUM(H7:H100) -> 0 | I101: =+SUM(I7:I100) -> 0 | J101: =+SUM(J7:J100) -> 0 | K101: =+SUM(K7:K100) -> 0 | ... O101: =+SUM(O7:O100) -> 0 | Q101: =SUM(Q7:Q100) -> 0 | S101: =SUM(S7:S100) -> 0 | T101: =SUM(T7:T100) -> 0 | U101: =SUM(U7:U100) -> 0 | V101: =SUM(V7:V100) -> 0 | W101: =SUM(W7:W100) -> 0
P102: Check | Q102: =+Q101-SUM(D101:O101) -> 0
B104: EXPENSES | D104: =+D6 -> 45808 | E104: =+E6 -> 45838 | F104: =+F6 -> 45869 | G104: =+G6 -> 45900 | H104: =+H6 -> 45930 | I104: =+I6 -> 45961 | J104: =+J6 -> 45991 | K104: =+K6 -> 46022 | ... O104: =+O6 -> 46113 | S104: T-1 Trends | T104: T-3 Trends | U104: T-6 Trends | V104: T-9 Trends | W104: T-12 Trends
Q105: =IFERROR(SUM(D105:O105),"") -> 0 | S105: =+SUM(O105)*12 -> 0 | T105: =+SUM(M105:O105)*4 -> 0 | U105: =+SUM(J105:O105)*2 -> 0 | V105: =+SUM(G105:O105)/9*12 -> 0 | W105: =+SUM(D105:O105) -> 0
Q106: =IFERROR(SUM(D106:O106),"") -> 0 | S106: =+SUM(O106)*12 -> 0 | T106: =+SUM(M106:O106)*4 -> 0 | U106: =+SUM(J106:O106)*2 -> 0 | V106: =+SUM(G106:O106)/9*12 -> 0 | W106: =+SUM(D106:O106) -> 0
Q107: =IFERROR(SUM(D107:O107),"") -> 0 | S107: =+SUM(O107)*12 -> 0 | T107: =+SUM(M107:O107)*4 -> 0 | U107: =+SUM(J107:O107)*2 -> 0 | V107: =+SUM(G107:O107)/9*12 -> 0 | W107: =+SUM(D107:O107) -> 0
Q108: =IFERROR(SUM(D108:O108),"") -> 0 | S108: =+SUM(O108)*12 -> 0 | T108: =+SUM(M108:O108)*4 -> 0 | U108: =+SUM(J108:O108)*2 -> 0 | V108: =+SUM(G108:O108)/9*12 -> 0 | W108: =+SUM(D108:O108) -> 0
Q109: =IFERROR(SUM(D109:O109),"") -> 0 | S109: =+SUM(O109)*12 -> 0 | T109: =+SUM(M109:O109)*4 -> 0 | U109: =+SUM(J109:O109)*2 -> 0 | V109: =+SUM(G109:O109)/9*12 -> 0 | W109: =+SUM(D109:O109) -> 0
Q110: =IFERROR(SUM(D110:O110),"") -> 0 | S110: =+SUM(O110)*12 -> 0 | T110: =+SUM(M110:O110)*4 -> 0 | U110: =+SUM(J110:O110)*2 -> 0 | V110: =+SUM(G110:O110)/9*12 -> 0 | W110: =+SUM(D110:O110) -> 0
Q111: =IFERROR(SUM(D111:O111),"") -> 0 | S111: =+SUM(O111)*12 -> 0 | T111: =+SUM(M111:O111)*4 -> 0 | U111: =+SUM(J111:O111)*2 -> 0 | V111: =+SUM(G111:O111)/9*12 -> 0 | W111: =+SUM(D111:O111) -> 0
Q112: =IFERROR(SUM(D112:O112),"") -> 0 | S112: =+SUM(O112)*12 -> 0 | T112: =+SUM(M112:O112)*4 -> 0 | U112: =+SUM(J112:O112)*2 -> 0 | V112: =+SUM(G112:O112)/9*12 -> 0 | W112: =+SUM(D112:O112) -> 0
Q113: =IFERROR(SUM(D113:O113),"") -> 0 | S113: =+SUM(O113)*12 -> 0 | T113: =+SUM(M113:O113)*4 -> 0 | U113: =+SUM(J113:O113)*2 -> 0 | V113: =+SUM(G113:O113)/9*12 -> 0 | W113: =+SUM(D113:O113) -> 0
Q114: =IFERROR(SUM(D114:O114),"") -> 0 | S114: =+SUM(O114)*12 -> 0 | T114: =+SUM(M114:O114)*4 -> 0 | U114: =+SUM(J114:O114)*2 -> 0 | V114: =+SUM(G114:O114)/9*12 -> 0 | W114: =+SUM(D114:O114) -> 0
Q115: =IFERROR(SUM(D115:O115),"") -> 0 | S115: =+SUM(O115)*12 -> 0 | T115: =+SUM(M115:O115)*4 -> 0 | U115: =+SUM(J115:O115)*2 -> 0 | V115: =+SUM(G115:O115)/9*12 -> 0 | W115: =+SUM(D115:O115) -> 0
Q116: =IFERROR(SUM(D116:O116),"") -> 0 | S116: =+SUM(O116)*12 -> 0 | T116: =+SUM(M116:O116)*4 -> 0 | U116: =+SUM(J116:O116)*2 -> 0 | V116: =+SUM(G116:O116)/9*12 -> 0 | W116: =+SUM(D116:O116) -> 0
... Q430: =IFERROR(SUM(D430:O430),"") -> 0 | S430: =+SUM(O430)*12 -> 0 | T430: =+SUM(M430:O430)*4 -> 0 | U430: =+SUM(J430:O430)*2 -> 0 | V430: =+SUM(G430:O430)/9*12 -> 0 | W430: =+SUM(D430:O430) -> 0
A431: x | B431: x
D432: =+SUM(D105:D430) -> 0 | E432: =+SUM(E105:E430) -> 0 | F432: =+SUM(F105:F430) -> 0 | G432: =+SUM(G105:G430) -> 0 | H432: =+SUM(H105:H430) -> 0 | I432: =+SUM(I105:I430) -> 0 | J432: =+SUM(J105:J430) -> 0 | K432: =+SUM(K105:K430) -> 0 | ... O432: =+SUM(O105:O430) -> 0 | Q432: =SUM(Q105:Q430) -> 0 | S432: =SUM(S105:S430) -> 0 | T432: =SUM(T105:T430) -> 0 | U432: =SUM(U105:U430) -> 0 | V432: =SUM(V105:V430) -> 0 | W432: =SUM(W105:W430) -> 0
P433: Check | Q433: =+Q432-SUM(D432:O432) -> 0
Q434: =+Q101-Q432 -> 0 | R434: =+R101-R432 -> 0 | S434: =+S101-S432 -> 0 | T434: =+T101-T432 -> 0 | U434: =+U101-U432 -> 0 | V434: =+V101-V432 -> 0 | W434: =+W101-W432 -> 0
Q439: =Q432-'Proforma (Annual)'!E112 -> 0

Sheet Other Income Assumptions
B2: Total Number of Units
B3: ='Rent Schedule'!$E$21 -> 0
B5: Code | C5: Line Item | D5: Fees | E5: =+'Absorption Schedule'!I25 -> 46204 | F5: =EOMONTH(E5,1) -> 46265 | G5: =EOMONTH(F5,1) -> 46295 | H5: =EOMONTH(G5,1) -> 46326 | I5: =EOMONTH(H5,1) -> 46356 | J5: =EOMONTH(I5,1) -> 46387 | K5: =EOMONTH(J5,1) -> 46418 | L5: =EOMONTH(K5,1) -> 46446 | M5: =EOMONTH(L5,1) -> 46477 | ... P5: =EOMONTH(O5,1) -> 46568 | Q5: Total | R5: Comments
C6: Utilities (RUBS) Water&Sewer | Q6: =SUM(E6:P6) -> 0
C7: Retail Income - CAM | Q7: =SUM(E7:P7) -> 0
C8: Garage Rent | Q8: =SUM(E8:P8) -> 0
C9: Storage Rent | Q9: =SUM(E9:P9) -> 0
C10: Pet Rent | Q10: =SUM(E10:P10) -> 0
C11: Other Rent | Q11: =SUM(E11:P11) -> 0
C12: Month-to-Month Premium | Q12: =SUM(E12:P12) -> 0
C13: Application Fees | Q13: =SUM(E13:P13) -> 0
C14: Administrative Fees | Q14: =SUM(E14:P14) -> 0
C15: Transfer Fees | Q15: =SUM(E15:P15) -> 0
C16: Pet Fees | Q16: =SUM(E16:P16) -> 0
C17: Utilities Reimbursement - Water | Q17: =SUM(E17:P17) -> 0
... C33: Other Fees | Q33: =SUM(E33:P33) -> 0
Q34: =SUM(E34:P34) -> 0
Q35: =SUM(E35:P35) -> 0
Q36: =SUM(E36:P36) -> 0
Q37: =SUM(E37:P37) -> 0
Q38: =SUM(E38:P38) -> 0
Q39: =SUM(E39:P39) -> 0
Q40: =SUM(E40:P40) -> 0
Q41: =SUM(E41:P41) -> 0
Q42: =SUM(E42:P42) -> 0
Q43: =SUM(E43:P43) -> 0
Q44: =SUM(E44:P44) -> 0
Q45: =SUM(E45:P45) -> 0
... Q101: =SUM(E101:P101) -> 0
B103: xx | C103: Total | E103: =SUM(E6:E101) -> 0 | F103: =SUM(F6:F101) -> 0 | G103: =SUM(G6:G101) -> 0 | H103: =SUM(H6:H101) -> 0 | I103: =SUM(I6:I101) -> 0 | J103: =SUM(J6:J101) -> 0 | K103: =SUM(K6:K101) -> 0 | L103: =SUM(L6:L101) -> 0 | ... P103: =SUM(P6:P101) -> 0 | Q103: =SUM(E103:P103) -> 0
Q105: =+Q103/B3 -> #DIV/0!
Q106: Per Unit

Sheet Payroll Schedule - Lease-Up
B5: Proposed Payroll Schedule | C5: =IF('Proforma (Annual)'!C2="",'Lease-Up Proforma'!C2,'Proforma (Annual)'!C2) -> 0
B6: Units | C6: ='Rent Schedule'!E31 -> 0
B9: TOTAL PAYROLL | C9: =SUM(J21,J34,F40,F51) -> 588812.8
B10: Per Unit | C10: =C9/C6 -> #DIV/0!
B13: Property Management Team | H13: 0.28
B14: Position | C14: FT/PT (Hrs) | D14: Salary | F14: Hourly Rate | G14: Payroll Prior to Burden | H14: Burden
B15: Community Manager | C15: 2080 | D15: 95000 | G15: =IF(D15>0, D15, C15*F15) -> 95000 | H15: =G15*$H$13 -> 26600
B16: Assistant Manager | C16: 2080 | F16: 25 | G16: =IF(D16>0, D16, C16*F16) -> 52000 | H16: =G16*$H$13 -> 14560
B17: Leasing Professional | C17: 2080 | F17: 20 | G17: =IF(D17>0, D17, C17*F17) -> 41600 | H17: =G17*$H$13 -> 11648
B18: Leasing Professional | C18: 2080 | F18: 19 | G18: =IF(D18>0, D18, C18*F18) -> 39520 | H18: =G18*$H$13 -> 11065.6
G19: =IF(D19>0, D19, C19*F19) -> 0 | H19: =G19*$H$13 -> 0
G20: =IF(D20>0, D20, C20*F20) -> 0 | H20: =G20*$H$13 -> 0
D21: Total Property Management Cost | G21: =SUM(G15:G20) -> 228120 | H21: =SUM(H15:H20) -> 63873.6 | J21: =SUM(G21:H21) -> 291993.6 | K21: Total
B24: Maintenance Team | H24: =H13 -> 0.28
B25: Position | C25: FT/PT (Hrs) | D25: Salary | F25: Hourly Rate | G25: Payroll Prior to Burden | H25: Burden
B26: Service Supervisor | C26: 2080 | F26: 34 | G26: =IF(D26>0, D26, C26*F26) -> 70720 | H26: =G26*$H$13 -> 19801.6
B27: Service Technician | C27: 2080 | F27: 22.5 | G27: =IF(D27>0, D27, C27*F27) -> 46800 | H27: =G27*$H$13 -> 13104
B28: Make-Ready | C28: 2080 | F28: 20 | G28: =IF(D28>0, D28, C28*F28) -> 41600 | H28: =G28*$H$13 -> 11648
B29: Porter | C29: 2080 | F29: 19 | G29: =IF(D29>0, D29, C29*F29) -> 39520 | H29: =G29*$H$13 -> 11065.6
G30: =IF(D30>0, D30, C30*F30) -> 0 | H30: =G30*$H$13 -> 0
G31: =IF(D31>0, D31, C31*F31) -> 0 | H31: =G31*$H$13 -> 0
G32: =IF(D32>0, D32, C32*F32) -> 0 | H32: =G32*$H$13 -> 0
G33: =IF(D33>0, D33, C33*F33) -> 0 | H33: =G33*$H$13 -> 0
D34: Total Maintenance Team Cost | G34: =SUM(G26:G33) -> 198640 | H34: =SUM(H26:H33) -> 55619.2 | J34: =SUM(G34:H34) -> 254259.2 | K34: Total
B37: Leasing Bonuses
B38: Average New Lease/Renewal Bonus: | D38: 185
B39: New Lease/Renewal Percentage Pay-Out: | D39: 0.8
B40: Total Leasing Bonus Cost | D40: =(C6*D38*D39)*(1+H13) -> 0 | F40: =D40 -> 0 | G40: Total
B42: Team Bonuses | C42: Bonus Potential | D42: Burden
B43: =+B15 -> Community Manager | C43: =D15*0.15 -> 14250 | D43: =+C43*$H$24 -> 3990
B44: =+B16 -> Assistant Manager | C44: 4000 | D44: =+C44*$H$24 -> 1120
B46: =+B26 -> Service Supervisor | C46: 6000 | D46: =+C46*$H$24 -> 1680
B47: =+B27 -> Service Technician | C47: 4000 | D47: =+C47*$H$24 -> 1120
B48: =+B28 -> Make-Ready | C48: 3000 | D48: =+C48*$H$24 -> 840
B49: =+B29 -> Porter | C49: 2000 | D49: =+C49*$H$24 -> 560
D50: =+C50*$H$24 -> 0
B51: Total | C51: =SUM(C43:C50) -> 33250 | D51: =SUM(D43:D50) -> 9310 | F51: =SUM(C51:D51) -> 42560 | G51: Total

Sheet Payroll Schedule
B5: Proposed Payroll Schedule | C5: =IF('Proforma (Annual)'!C2="",'Lease-Up Proforma'!C2,'Proforma (Annual)'!C2) -> 0
B6: Units | C6: ='Rent Schedule'!E31 -> 0
B9: TOTAL PAYROLL | C9: =SUM(J21,J34,F40,F51) -> 572412.5
B10: Per Unit | C10: =C9/C6 -> #DIV/0!
B13: Property Management Team | H13: 0.25
B14: Position | C14: FT/PT (Hrs) | D14: Salary | F14: Hourly Rate | G14: Payroll Prior to Burden | H14: Burden
B15: Community Manager | C15: 2080 | D15: 95000 | G15: =IF(D15>0, D15, C15*F15) -> 95000 | H15: =G15*$H$13 -> 23750
B16: Assistant Manager | C16: 2080 | F16: 24 | G16: =IF(D16>0, D16, C16*F16) -> 49920 | H16: =G16*$H$13 -> 12480
B17: Leasing Professional | C17: 2080 | F17: 20 | G17: =IF(D17>0, D17, C17*F17) -> 41600 | H17: =G17*$H$13 -> 10400
B18: Leasing Professional | C18: 2080 | F18: 19 | G18: =IF(D18>0, D18, C18*F18) -> 39520 | H18: =G18*$H$13 -> 9880
G19: =IF(D19>0, D19, C19*F19) -> 0 | H19: =G19*$H$13 -> 0
G20: =IF(D20>0, D20, C20*F20) -> 0 | H20: =G20*$H$13 -> 0
D21: Total Property Management Cost | G21: =SUM(G15:G20) -> 226040 | H21: =SUM(H15:H20) -> 56510 | J21: =SUM(G21:H21) -> 282550 | K21: Total
B24: Maintenance Team | H24: =H13 -> 0.25
B25: Position | C25: FT/PT (Hrs) | D25: Salary | F25: Hourly Rate | G25: Payroll Prior to Burden | H25: Burden
B26: Service Supervisor | C26: 2080 | F26: 34 | G26: =IF(D26>0, D26, C26*F26) -> 70720 | H26: =G26*$H$13 -> 17680
B27: Service Technician | C27: 2080 | F27: 22.5 | G27: =IF(D27>0, D27, C27*F27) -> 46800 | H27: =G27*$H$13 -> 11700
B28: Make-Ready | C28: 2080 | F28: 20 | G28: =IF(D28>0, D28, C28*F28) -> 41600 | H28: =G28*$H$13 -> 10400
B29: Porter | C29: 2080 | F29: 19 | G29: =IF(D29>0, D29, C29*F29) -> 39520 | H29: =G29*$H$13 -> 9880
G30: =IF(D30>0, D30, C30*F30) -> 0 | H30: =G30*$H$13 -> 0
G31: =IF(D31>0, D31, C31*F31) -> 0 | H31: =G31*$H$13 -> 0
G32: =IF(D32>0, D32, C32*F32) -> 0 | H32: =G32*$H$13 -> 0
G33: =IF(D33>0, D33, C33*F33) -> 0 | H33: =G33*$H$13 -> 0
D34: Total Maintenance Team Cost | G34: =SUM(G26:G33) -> 198640 | H34: =SUM(H26:H33) -> 49660 | J34: =SUM(G34:H34) -> 248300 | K34: Total
B37: Leasing Bonuses
B38: Average New Lease/Renewal Bonus: | D38: 150
B39: New Lease/Renewal Percentage Pay-Out: | D39: 0.9
B40: Total Leasing Bonus Cost | D40: =(C6*D38*D39)*(1+H13) -> 0 | F40: =D40 -> 0 | G40: Total
B42: Team Bonuses | C42: Bonus Potential | D42: Burden
B43: =+B15 -> Community Manager | C43: =D15*0.15 -> 14250 | D43: =+C43*$H$24 -> 3562.5
B44: =+B16 -> Assistant Manager | C44: 4000 | D44: =+C44*$H$24 -> 1000
B46: =+B26 -> Service Supervisor | C46: 6000 | D46: =+C46*$H$24 -> 1500
B47: =+B27 -> Service Technician | C47: 4000 | D47: =+C47*$H$24 -> 1000
B48: =+B28 -> Make-Ready | C48: =IF(B48>0,3000,"") -> 3000 | D48: =IF(C48>0,C48*$H$24,"") -> 750
B49: =+B29 -> Porter | C49: =IF(B49>0,2000,"") -> 2000 | D49: =IF(C49>0,C49*$H$24,"") -> 500
C50: =IF(B50>0,2000,"") | D50: =IF(C50="<>0",C50*$H$24,"")
B51: Total | C51: =SUM(C43:C50) -> 33250 | D51: =SUM(D43:D50) -> 8312.5 | F51: =SUM(C51:D51) -> 41562.5 | G51: Total

Sheet G&A Assumptions
B2: Total Number of Units
B3: ='Rent Schedule'!$E$21 -> 0
B5: Code | C5: Line Item | D5: Fixed Costs | E5: =+'Absorption Schedule'!I25 -> 46204 | F5: =EOMONTH(E5,1 ) -> 46265 | G5: =EOMONTH(F5,1 ) -> 46295 | H5: =EOMONTH(G5,1 ) -> 46326 | I5: =EOMONTH(H5,1 ) -> 46356 | J5: =EOMONTH(I5,1 ) -> 46387 | K5: =EOMONTH(J5,1 ) -> 46418 | L5: =EOMONTH(K5,1 ) -> 46446 | M5: =EOMONTH(L5,1 ) -> 46477 | ... P5: =EOMONTH(O5,1 ) -> 46568 | Q5: Total | R5: Comments
C6: Bank Charges | Q6: =SUM(E6:P6) -> 0
C7: Credit Processing | Q7: =SUM(E7:P7) -> 0
C8: Eviction Costs | Q8: =SUM(E8:P8) -> 0
C9: Legal Services | Q9: =SUM(E9:P9) -> 0
C10: Delivery Services | Q10: =SUM(E10:P10) -> 0
C11: Apartment Association Fees | Q11: =SUM(E11:P11) -> 0
C12: Licenses and Permits | Q12: =SUM(E12:P12) -> 0
C13: Forms | Q13: =SUM(E13:P13) -> 0
C14: Postage | Q14: =SUM(E14:P14) -> 0
C15: General Office Supplies | Q15: =SUM(E15:P15) -> 0
C16: Office Equipment | Q16: =SUM(E16:P16) -> 0
C17: Leasing/Management Software | Q17: =SUM(E17:P17) -> 0
... C25: Misc. Fees/Expenses | Q25: =SUM(E25:P25) -> 0
Q26: =SUM(E26:P26) -> 0
Q27: =SUM(E27:P27) -> 0
Q28: =SUM(E28:P28) -> 0
Q29: =SUM(E29:P29) -> 0
Q30: =SUM(E30:P30) -> 0
Q31: =SUM(E31:P31) -> 0
Q32: =SUM(E32:P32) -> 0
Q33: =SUM(E33:P33) -> 0
Q34: =SUM(E34:P34) -> 0
Q35: =SUM(E35:P35) -> 0
Q36: =SUM(E36:P36) -> 0
Q37: =SUM(E37:P37) -> 0
... Q101: =SUM(E101:P101) -> 0
B103: xx | C103: Total | E103: =SUM(E6:$E$101) -> 0 | F103: =SUM(F6:$F$101) -> 0 | G103: =SUM(G6:$G$101) -> 0 | H103: =SUM(H6:$H$101) -> 0 | I103: =SUM(I6:$I$101) -> 0 | J103: =SUM(J6:$J$101) -> 0 | K103: =SUM(K6:$K$101) -> 0 | L103: =SUM(L6:$L$101) -> 0 | M103: =SUM(M6:$M$101) -> 0 | N103: =SUM(N6:$N$101) -> 0 | O103: =SUM(O6:$O$101) -> 0 | P103: =SUM(P6:$P$101) -> 0 | Q103: =SUM($E$103:$P$103) -> 0
Q105: =Q103/B3 -> #DIV/0!
Q106: Per Unit

Sheet Marketing Stack - Lease-Up
B2: Total Number of Units
B3: ='Rent Schedule'!E31 -> 0
B5: Code | C5: Service | D5: Level | E5: =+'Absorption Schedule'!I25 -> 46204 | F5: =EOMONTH(E5,1 ) -> 46265 | G5: =EOMONTH(F5,1 ) -> 46295 | H5: =EOMONTH(G5,1 ) -> 46326 | I5: =EOMONTH(H5,1 ) -> 46356 | J5: =EOMONTH(I5,1 ) -> 46387 | K5: =EOMONTH(J5,1 ) -> 46418 | L5: =EOMONTH(K5,1 ) -> 46446 | M5: =EOMONTH(L5,1 ) -> 46477 | ... P5: =EOMONTH(O5,1 ) -> 46568 | Q5: Total | R5: Comments
B6: Marketing | C6: Apts.com | D6: Platinum+ | E6: =+INDEX('Marketing List - Dropdowns'!G5:I12,MATCH('Marketing Stack - Lease-Up'!D6,'Marketing List - Dropdowns'!F5:F12,0),MATCH('Marketing List - Dropdowns'!E4,'Marketing List - Dropdowns'!G4:I4,0)) -> 1625 | F6: =+E6 -> 1625 | G6: =+F6 -> 1625 | H6: =+G6 -> 1625 | I6: =+H6 -> 1625 | J6: =+I6 -> 1625 | K6: =+J6 -> 1625 | L6: =+K6 -> 1625 | M6: =+L6 -> 1625 | ... P6: =+O6 -> 1625 | Q6: =SUM(E6:P6) -> 19500
B7: Marketing | C7: Pay Per Click | D7: 2000 | E7: =+D7 -> 2000 | F7: =+E7 -> 2000 | G7: =+F7 -> 2000 | H7: =+G7 -> 2000 | I7: =+H7 -> 2000 | J7: =+I7 -> 2000 | K7: =+J7 -> 2000 | L7: =+K7 -> 2000 | ... P7: =+O7 -> 2000 | Q7: =+SUM(E7:P7) -> 24000
B8: Marketing | C8: Geofence Campaign | D8: Yes | E8: =+IF(D8="Yes",'Marketing List - Dropdowns'!$P$4,0) -> 350 | F8: =+E8 -> 350 | G8: =+F8 -> 350 | H8: =+G8 -> 350 | I8: =+H8 -> 350 | J8: =+I8 -> 350 | K8: =+J8 -> 350 | L8: =+K8 -> 350 | M8: =+L8 -> 350 | ... P8: =+O8 -> 350 | Q8: =+SUM(E8:P8) -> 4200
B9: Marketing | C9: Digital Direct Mail | D9: Yes | E9: 0 | F9: 0 | G9: 350 | H9: =E9 -> 0 | I9: =F9 -> 0 | J9: =G9 -> 350 | K9: =H9 -> 0 | L9: =I9 -> 0 | M9: =G9 -> 350 | N9: =H9 -> 0 | O9: =I9 -> 0 | P9: =J9 -> 350 | Q9: =+SUM(E9:P9) -> 1400
B10: Marketing | C10: Retargeting | D10: Yes | E10: =+IF(D10="Yes",'Marketing List - Dropdowns'!$S$4,0) -> 300 | F10: =+E10 -> 300 | G10: =+F10 -> 300 | H10: =+G10 -> 300 | I10: =+H10 -> 300 | J10: =+I10 -> 300 | K10: =+J10 -> 300 | L10: =+K10 -> 300 | M10: =+L10 -> 300 | ... P10: =+O10 -> 300 | Q10: =+SUM(E10:P10) -> 3600
B11: Marketing | C11: Apartment List
B12: Referral Fees | C12: Apartment List (Monthly Cost) | D12: Yes | E12: =IF(D12="Yes",'Marketing List - Dropdowns'!G25,0) -> 63 | F12: =E12 -> 63 | G12: =F12 -> 63 | H12: =G12 -> 63 | I12: =H12 -> 63 | J12: =I12 -> 63 | K12: =J12 -> 63 | L12: =K12 -> 63 | M12: =L12 -> 63 | ... P12: =O12 -> 63 | Q12: =+SUM(E12:P12) -> 756
B13: Referral Fees | C13: Apartment List (estimated leases per month) | D13: 2 | E13: =+INDEX('Marketing List - Dropdowns'!G19:G24,MATCH('Marketing Stack - Lease-Up'!D13,'Marketing List - Dropdowns'!F19:F31,0)) -> 818 | F13: =+E13 -> 818 | G13: =+F13 -> 818 | H13: =+G13 -> 818 | I13: =+H13 -> 818 | J13: =+I13 -> 818 | K13: =+J13 -> 818 | L13: =+K13 -> 818 | M13: =+L13 -> 818 | ... P13: =+O13 -> 818 | Q13: =+SUM(E13:P13) -> 9816 | R13: Referral fee is $409/lease plus monthly cost of $63.
B14: Referral Fees | C14: RentGrata
B15: Referral Fees | C15: RentGrata (Monthly Cost) | D15: Yes | E15: =IF(D15="Yes",'Marketing List - Dropdowns'!$G$37,0) -> 380 | F15: =E15 -> 380 | G15: =F15 -> 380 | H15: =G15 -> 380 | I15: =H15 -> 380 | J15: =I15 -> 380 | K15: =J15 -> 380 | L15: =K15 -> 380 | M15: =L15 -> 380 | ... P15: =O15 -> 380 | Q15: =+SUM(E15:P15) -> 4560
B16: Referral Fees | C16: RentGrata Referral Cost (estimated leases per month) | D16: 2 | E16: =+INDEX('Marketing List - Dropdowns'!G31:G36,MATCH('Marketing Stack - Lease-Up'!D16,'Marketing List - Dropdowns'!F31:F36,0)) -> 500 | F16: =E16 -> 500 | G16: =F16 -> 500 | H16: =G16 -> 500 | I16: =H16 -> 500 | J16: =I16 -> 500 | K16: =J16 -> 500 | L16: =K16 -> 500 | M16: =L16 -> 500 | ... P16: =O16 -> 500 | Q16: =+SUM(E16:P16) -> 6000
B17: Marketing | C17: Apartment Ratings (annual rate) $100 set up + $350/mo | Q17: =+SUM(E17:P17) -> 0
B18: Marketing | C18: Better Bot ($200 set up fee) | D18: Yes | E18: 229 | F18: 229 | G18: 229 | H18: 229 | I18: 229 | J18: 229 | K18: 229 | L18: 229 | M18: 229 | N18: 229 | O18: 229 | P18: 229 | Q18: =+SUM(E18:P18) -> 2748
B19: Marketing | C19: Virtual Tours Monthly Hosting Fee | Q19: =+SUM(E19:P19) -> 0
B20: Marketing | C20: Kingsley Reputation | D20: Yes | E20: =+IF(D20="Yes",'Marketing List - Dropdowns'!$N$18,0) -> 55 | F20: =+E20 -> 55 | G20: =+F20 -> 55 | H20: =+G20 -> 55 | I20: =+H20 -> 55 | J20: =+I20 -> 55 | K20: =+J20 -> 55 | L20: =+K20 -> 55 | M20: =+L20 -> 55 | ... P20: =+O20 -> 55 | Q20: =+SUM(E20:P20) -> 660
B21: Marketing | C21: Kingsley Surveys | D21: Yes | E21: =+IF(D21="Yes",'Marketing List - Dropdowns'!Q18*'Marketing Stack - Lease-Up'!$B$3,0) -> 0 | F21: =+E21 -> 0 | G21: =+F21 -> 0 | H21: =+G21 -> 0 | I21: =+H21 -> 0 | J21: =+I21 -> 0 | K21: =+J21 -> 0 | L21: =+K21 -> 0 | M21: =+L21 -> 0 | ... P21: =+O21 -> 0 | Q21: =+SUM(E21:P21) -> 0
B22: Marketing | C22: Canva | D22: Yes | E22: 400 | Q22: =+SUM(E22:P22) -> 400
B23: Marketing | Q23: =+SUM(E23:P23) -> 0
B24: Marketing | C24: Engrain Suite
B25: Marketing | C25: Engrain (Site Map) | D25: Yes | E25: =+IF(D25="Yes",'Marketing List - Dropdowns'!$T$19,0) -> 81 | F25: =+E25 -> 81 | G25: =+F25 -> 81 | H25: =+G25 -> 81 | I25: =+H25 -> 81 | J25: =+I25 -> 81 | K25: =+J25 -> 81 | L25: =+K25 -> 81 | M25: =+L25 -> 81 | ... P25: =+O25 -> 81 | Q25: =+SUM(E25:P25) -> 972
B26: Marketing | C26: Engrain (Site Map) - One Time Set Up Cost | D26: Yes | E26: =+IF(D26="Yes",'Marketing List - Dropdowns'!T18,0) -> 375 | F26: 0 | G26: 0 | H26: 0 | I26: 0 | J26: 0 | K26: 0 | L26: 0 | M26: 0 | N26: 0 | O26: 0 | P26: 0 | Q26: =+SUM(E26:P26) -> 375
B27: Marketing | C27: Engrain (Asset Intelligence) | D27: Yes | E27: =+IF(D27="Yes",'Marketing List - Dropdowns'!$W$19,0) -> 199 | F27: =+E27 -> 199 | G27: =+F27 -> 199 | H27: =+G27 -> 199 | I27: =+H27 -> 199 | J27: =+I27 -> 199 | K27: =+J27 -> 199 | L27: =+K27 -> 199 | M27: =+L27 -> 199 | ... P27: =+O27 -> 199 | Q27: =+SUM(E27:P27) -> 2388
B28: Marketing | C28: Engrain (Asset Intelligence) - One Time Set Up Cost | D28: Yes | E28: =+IF(D28="Yes",'Marketing List - Dropdowns'!$W$18,0) -> 600 | F28: 0 | G28: 0 | H28: 0 | I28: 0 | J28: 0 | K28: 0 | L28: 0 | M28: 0 | N28: 0 | O28: 0 | P28: 0 | Q28: =+SUM(E28:P28) -> 600
B29: Resident Retention | C29: Resident Retention/Prospect Experience | E29: 2000 | F29: =E29 -> 2000 | G29: =F29 -> 2000 | H29: =G29 -> 2000 | I29: =H29 -> 2000 | J29: =I29 -> 2000 | K29: =J29 -> 2000 | L29: =K29 -> 2000 | M29: =L29 -> 2000 | ... P29: =O29 -> 2000 | Q29: =+SUM(E29:P29) -> 24000
B30: Locator Fees | C30: Locators | E30: 2750 | F30: =E30 -> 2750 | G30: =F30 -> 2750 | H30: =G30 -> 2750 | I30: =H30 -> 2750 | J30: =I30 -> 2750 | K30: =J30 -> 2750 | L30: =K30 -> 2750 | M30: =L30 -> 2750 | ... P30: =O30 -> 2750 | Q30: =+SUM(E30:P30) -> 33000
B31: Marketing | Q31: =+SUM(E31:P31) -> 0
B32: Marketing
B33: Marketing
B34: Marketing
B35: Marketing
B36: Marketing
B37: Marketing
C38: Marketing Support Services | D38: 325 | E38: =$D$38 -> 325 | F38: =$D$38 -> 325 | G38: =$D$38 -> 325 | H38: =$D$38 -> 325 | I38: =$D$38 -> 325 | J38: =$D$38 -> 325 | K38: =$D$38 -> 325 | L38: =$D$38 -> 325 | ... P38: =$D$38 -> 325 | Q38: =+SUM(E38:P38) -> 3900
E39: =SUM(E6:E38) -> 13050 | F39: =SUM(F6:F38) -> 11675 | G39: =SUM(G6:G38) -> 12025 | H39: =SUM(H6:H38) -> 11675 | I39: =SUM(I6:I38) -> 11675 | J39: =SUM(J6:J38) -> 12025 | K39: =SUM(K6:K38) -> 11675 | L39: =SUM(L6:L38) -> 11675 | ... Q39: =SUM(Q6:Q38) -> 142875
Q41: =+Q39/B3 -> #DIV/0!
Q42: Per Unit

Sheet Marketing Stack
B2: Total Number of Units
B3: ='Rent Schedule'!E31 -> 0
B5: Code | C5: Service | D5: Level | E5: =+'Absorption Schedule'!I25 -> 46204 | F5: =EOMONTH(E5,1 ) -> 46265 | G5: =EOMONTH(F5,1 ) -> 46295 | H5: =EOMONTH(G5,1 ) -> 46326 | I5: =EOMONTH(H5,1 ) -> 46356 | J5: =EOMONTH(I5,1 ) -> 46387 | K5: =EOMONTH(J5,1 ) -> 46418 | L5: =EOMONTH(K5,1 ) -> 46446 | M5: =EOMONTH(L5,1 ) -> 46477 | ... P5: =EOMONTH(O5,1 ) -> 46568 | Q5: Total | R5: Comments
B6: Marketing | C6: Apts.com | D6: Platinum+ | E6: =+INDEX('Marketing List - Dropdowns'!G5:I12,MATCH('Marketing Stack'!D6,'Marketing List - Dropdowns'!F5:F12,0),MATCH('Marketing List - Dropdowns'!E4,'Marketing List - Dropdowns'!G4:I4,0)) -> 1625 | F6: =+E6 -> 1625 | G6: =+F6 -> 1625 | H6: =+G6 -> 1625 | I6: =+H6 -> 1625 | J6: =+I6 -> 1625 | K6: =+J6 -> 1625 | L6: =+K6 -> 1625 | M6: =+L6 -> 1625 | ... P6: =+O6 -> 1625 | Q6: =SUM(E6:P6) -> 19500
B7: Marketing | C7: Pay Per Click | D7: 3000 | E7: =+D7 -> 3000 | F7: =+E7 -> 3000 | G7: =+F7 -> 3000 | H7: =+G7 -> 3000 | I7: =+H7 -> 3000 | J7: =+I7 -> 3000 | K7: =+J7 -> 3000 | L7: =+K7 -> 3000 | ... P7: =+O7 -> 3000 | Q7: =+SUM(E7:P7) -> 36000
B8: Marketing | C8: Geofence Campaign | D8: Yes | E8: =+IF(D8="Yes",'Marketing List - Dropdowns'!$P$4,0) -> 350 | F8: =+E8 -> 350 | G8: =+F8 -> 350 | H8: =+G8 -> 350 | I8: =+H8 -> 350 | J8: =+I8 -> 350 | K8: =+J8 -> 350 | L8: =+K8 -> 350 | M8: =+L8 -> 350 | ... P8: =+O8 -> 350 | Q8: =+SUM(E8:P8) -> 4200
B9: Marketing | C9: Digital Direct Mail | D9: Yes | E9: 0 | F9: 0 | G9: 350 | H9: =E9 -> 0 | I9: =F9 -> 0 | J9: =G9 -> 350 | K9: =H9 -> 0 | L9: =I9 -> 0 | M9: =G9 -> 350 | N9: =H9 -> 0 | O9: =I9 -> 0 | P9: =J9 -> 350 | Q9: =+SUM(E9:P9) -> 1400
B10: Marketing | C10: Retargeting | D10: Yes | E10: =+IF(D10="Yes",'Marketing List - Dropdowns'!$S$4,0) -> 300 | F10: =+E10 -> 300 | G10: =+F10 -> 300 | H10: =+G10 -> 300 | I10: =+H10 -> 300 | J10: =+I10 -> 300 | K10: =+J10 -> 300 | L10: =+K10 -> 300 | M10: =+L10 -> 300 | ... P10: =+O10 -> 300 | Q10: =+SUM(E10:P10) -> 3600
B11: Marketing | C11: Apartment List
B12: Referral Fees | C12: Apartment List (Monthly Cost) | D12: No | E12: =IF(D12="Yes",'Marketing List - Dropdowns'!G25,0) -> 0 | F12: =E12 -> 0 | G12: =F12 -> 0 | H12: =G12 -> 0 | I12: =H12 -> 0 | J12: =I12 -> 0 | K12: =J12 -> 0 | L12: =K12 -> 0 | M12: =L12 -> 0 | ... P12: =O12 -> 0 | Q12: =+SUM(E12:P12) -> 0
B13: Referral Fees | C13: Apartment List (estimated leases per month) | D13: 0 | E13: =+INDEX('Marketing List - Dropdowns'!G19:G24,MATCH('Marketing Stack'!D13,'Marketing List - Dropdowns'!F19:F31,0)) -> 0 | F13: =+E13 -> 0 | G13: =+F13 -> 0 | H13: =+G13 -> 0 | I13: =+H13 -> 0 | J13: =+I13 -> 0 | K13: =+J13 -> 0 | L13: =+K13 -> 0 | M13: =+L13 -> 0 | ... P13: =+O13 -> 0 | Q13: =+SUM(E13:P13) -> 0 | R13: =IF(D12="yes", "Referral fee is $409/lease plus monthly cost of $63.","")
B14: Referral Fees | C14: RentGrata
B15: Referral Fees | C15: RentGrata (Monthly Cost) | D15: No | E15: =IF(D15="Yes",'Marketing List - Dropdowns'!$G$37,0) -> 0 | F15: =E15 -> 0 | G15: =F15 -> 0 | H15: =G15 -> 0 | I15: =H15 -> 0 | J15: =I15 -> 0 | K15: =J15 -> 0 | L15: =K15 -> 0 | M15: =L15 -> 0 | ... P15: =O15 -> 0 | Q15: =+SUM(E15:P15) -> 0
B16: Referral Fees | C16: RentGrata Referral Cost (estimated leases per month) | D16: 0 | E16: =+INDEX('Marketing List - Dropdowns'!G31:G36,MATCH('Marketing Stack'!D16,'Marketing List - Dropdowns'!F31:F36,0)) -> 0 | F16: =E16 -> 0 | G16: =F16 -> 0 | H16: =G16 -> 0 | I16: =H16 -> 0 | J16: =I16 -> 0 | K16: =J16 -> 0 | L16: =K16 -> 0 | M16: =L16 -> 0 | ... P16: =O16 -> 0 | Q16: =+SUM(E16:P16) -> 0
B17: Marketing | C17: Apartment Ratings (annual rate) $100 set up + $350/mo | Q17: =+SUM(E17:P17) -> 0
B18: Marketing | C18: Better Bot ($200 set up fee) | D18: No | Q18: =+SUM(E18:P18) -> 0
B19: Marketing | C19: Virtual Tours Monthly Hosting Fee | Q19: =+SUM(E19:P19) -> 0
B20: Marketing | C20: Kingsley Reputation | D20: Yes | E20: =+IF(D20="Yes",'Marketing List - Dropdowns'!$N$18,0) -> 55 | F20: =+E20 -> 55 | G20: =+F20 -> 55 | H20: =+G20 -> 55 | I20: =+H20 -> 55 | J20: =+I20 -> 55 | K20: =+J20 -> 55 | L20: =+K20 -> 55 | M20: =+L20 -> 55 | ... P20: =+O20 -> 55 | Q20: =+SUM(E20:P20) -> 660
B21: Marketing | C21: Kingsley Surveys | D21: Yes | E21: =+IF(D21="Yes",'Marketing List - Dropdowns'!Q18*'Marketing Stack'!$B$3,0) -> 0 | F21: =+E21 -> 0 | G21: =+F21 -> 0 | H21: =+G21 -> 0 | I21: =+H21 -> 0 | J21: =+I21 -> 0 | K21: =+J21 -> 0 | L21: =+K21 -> 0 | M21: =+L21 -> 0 | ... P21: =+O21 -> 0 | Q21: =+SUM(E21:P21) -> 0
B22: Marketing | C22: Canva | D22: Yes | E22: 400 | Q22: =+SUM(E22:P22) -> 400
B23: Marketing | Q23: =+SUM(E23:P23) -> 0
B24: Marketing | C24: Engrain Suite
B25: Marketing | C25: Engrain (Site Map) | D25: Yes | E25: =+IF(D25="Yes",'Marketing List - Dropdowns'!$T$19,0) -> 81 | F25: =+E25 -> 81 | G25: =+F25 -> 81 | H25: =+G25 -> 81 | I25: =+H25 -> 81 | J25: =+I25 -> 81 | K25: =+J25 -> 81 | L25: =+K25 -> 81 | M25: =+L25 -> 81 | ... P25: =+O25 -> 81 | Q25: =+SUM(E25:P25) -> 972
B26: Marketing | C26: Engrain (Site Map) - One Time Set Up Cost | D26: No | E26: =+IF(D26="Yes",'Marketing List - Dropdowns'!T18,0) -> 0 | F26: 0 | G26: 0 | H26: 0 | I26: 0 | J26: 0 | K26: 0 | L26: 0 | M26: 0 | N26: 0 | O26: 0 | P26: 0 | Q26: =+SUM(E26:P26) -> 0
B27: Marketing | C27: Engrain (Asset Intelligence) | D27: No | E27: =+IF(D27="Yes",'Marketing List - Dropdowns'!$W$19,0) -> 0 | F27: =+E27 -> 0 | G27: =+F27 -> 0 | H27: =+G27 -> 0 | I27: =+H27 -> 0 | J27: =+I27 -> 0 | K27: =+J27 -> 0 | L27: =+K27 -> 0 | M27: =+L27 -> 0 | ... P27: =+O27 -> 0 | Q27: =+SUM(E27:P27) -> 0
B28: Marketing | C28: Engrain (Asset Intelligence) - One Time Set Up Cost | D28: No | E28: =+IF(D28="Yes",'Marketing List - Dropdowns'!$W$18,0) -> 0 | F28: 0 | G28: 0 | H28: 0 | I28: 0 | J28: 0 | K28: 0 | L28: 0 | M28: 0 | N28: 0 | O28: 0 | P28: 0 | Q28: =+SUM(E28:P28) -> 0
B29: Resident Retention | C29: Resident Retention/Prospect Experience | E29: 1250 | F29: =E29 -> 1250 | G29: =F29 -> 1250 | H29: =G29 -> 1250 | I29: =H29 -> 1250 | J29: =I29 -> 1250 | K29: =J29 -> 1250 | L29: =K29 -> 1250 | M29: =L29 -> 1250 | ... P29: =O29 -> 1250 | Q29: =+SUM(E29:P29) -> 15000
B30: Locator Fees | C30: Locators | E30: 500 | F30: =E30 -> 500 | G30: =F30 -> 500 | H30: =G30 -> 500 | I30: =H30 -> 500 | J30: =I30 -> 500 | K30: =J30 -> 500 | L30: =K30 -> 500 | M30: =L30 -> 500 | ... P30: =O30 -> 500 | Q30: =+SUM(E30:P30) -> 6000
B31: Marketing | Q31: =+SUM(E31:P31) -> 0
B32: Marketing | Q32: =+SUM(E32:P32) -> 0
B33: Marketing | Q33: =+SUM(E33:P33) -> 0
B34: Marketing | Q34: =+SUM(E34:P34) -> 0
B35: Marketing | Q35: =+SUM(E35:P35) -> 0
B36: Marketing | Q36: =+SUM(E36:P36) -> 0
B37: Marketing | Q37: =+SUM(E37:P37) -> 0
B38: Marketing | C38: Marketing Support Services | D38: 325 | E38: =$D$38 -> 325 | F38: =$D$38 -> 325 | G38: =$D$38 -> 325 | H38: =$D$38 -> 325 | I38: =$D$38 -> 325 | J38: =$D$38 -> 325 | K38: =$D$38 -> 325 | L38: =$D$38 -> 325 | ... P38: =$D$38 -> 325 | Q38: =+SUM(E38:P38) -> 3900
E39: =SUM(E6:E38) -> 7886 | F39: =SUM(F6:F38) -> 7486 | G39: =SUM(G6:G38) -> 7836 | H39: =SUM(H6:H38) -> 7486 | I39: =SUM(I6:I38) -> 7486 | J39: =SUM(J6:J38) -> 7836 | K39: =SUM(K6:K38) -> 7486 | L39: =SUM(L6:L38) -> 7486 | ... Q39: =SUM(Q6:Q38) -> 91632
Q41: =+Q39/B3 -> #DIV/0!
Q42: Per Unit

Sheet R&M Assumptions
B2: Total Number of Units
B3: ='Rent Schedule'!E31 -> 0
B5: Code | C5: Line Item | D5: Fixed Costs | E5: =+'Absorption Schedule'!I25 -> 46204 | F5: =EOMONTH(E5,1 ) -> 46265 | G5: =EOMONTH(F5,1 ) -> 46295 | H5: =EOMONTH(G5,1 ) -> 46326 | I5: =EOMONTH(H5,1 ) -> 46356 | J5: =EOMONTH(I5,1 ) -> 46387 | K5: =EOMONTH(J5,1 ) -> 46418 | L5: =EOMONTH(K5,1 ) -> 46446 | M5: =EOMONTH(L5,1 ) -> 46477 | ... P5: =EOMONTH(O5,1 ) -> 46568 | Q5: Total | R5: Comments
B6: R&M | C6: Appliances | Q6: =SUM(E6:P6) -> 0
B7: R&M | C7: Building | Q7: =SUM(E7:P7) -> 0
B8: R&M | C8: Electrical | Q8: =SUM(E8:P8) -> 0
B9: R&M | C9: Heating/AC | Q9: =SUM(E9:P9) -> 0
B10: R&M | C10: Plumbing | Q10: =SUM(E10:P10) -> 0
B11: R&M | C11: Maintenance - Equipment | Q11: =SUM(E11:P11) -> 0
B12: R&M | C12: Other Equipment | Q12: =SUM(E12:P12) -> 0
B13: R&M | C13: Security Access Gates | Q13: =SUM(E13:P13) -> 0
B14: R&M | C14: Fire Alarm Sprinkler | Q14: =SUM(E14:P14) -> 0
B15: R&M | C15: Pool | Q15: =SUM(E15:P15) -> 0
B16: Landscaping | C16: Landscaping (Seasonals) | Q16: =SUM(E16:P16) -> 0
B17: Landscaping | C17: Landscape (Mulch) | Q17: =SUM(E17:P17) -> 0
... B41: Make-Ready/Redec | C41: Window Coverings | Q41: =SUM(E41:P41) -> 0
Q42: =SUM(E42:P42) -> 0
Q43: =SUM(E43:P43) -> 0
Q44: =SUM(E44:P44) -> 0
Q45: =SUM(E45:P45) -> 0
Q46: =SUM(E46:P46) -> 0
Q47: =SUM(E47:P47) -> 0
Q48: =SUM(E48:P48) -> 0
Q49: =SUM(E49:P49) -> 0
Q50: =SUM(E50:P50) -> 0
Q51: =SUM(E51:P51) -> 0
Q52: =SUM(E52:P52) -> 0
Q53: =SUM(E53:P53) -> 0
... Q101: =SUM(E101:P101) -> 0
B103: xx | C103: Total | E103: =SUM(E6:E101) -> 0 | F103: =SUM(F6:F101) -> 0 | G103: =SUM(G6:G101) -> 0 | H103: =SUM(H6:H101) -> 0 | I103: =SUM(I6:I101) -> 0 | J103: =SUM(J6:J101) -> 0 | K103: =SUM(K6:K101) -> 0 | L103: =SUM(L6:L101) -> 0 | ... P103: =SUM(P6:P101) -> 0 | Q103: =SUM(E103:P103) -> 0
Q105: =+Q103/B3 -> #DIV/0!
Q106: Per Unit

Sheet Utilities Assumptions
B2: Total Number of Units
B3: ='Rent Schedule'!$E$21 -> 0
B5: Code | C5: Line Item | D5: =+'Absorption Schedule'!I25 -> 46204 | E5: =EOMONTH(D5,1 ) -> 46265 | F5: =EOMONTH(E5,1 ) -> 46295 | G5: =EOMONTH(F5,1 ) -> 46326 | H5: =EOMONTH(G5,1 ) -> 46356 | I5: =EOMONTH(H5,1 ) -> 46387 | J5: =EOMONTH(I5,1 ) -> 46418 | K5: =EOMONTH(J5,1 ) -> 46446 | L5: =EOMONTH(K5,1 ) -> 46477 | ... O5: =EOMONTH(N5,1 ) -> 46568 | P5: Total | Q5: Comments
B6: Utility Fees | C6: Utility Billing/UPM Fees | P6: =SUM(D6:O6) -> 0
B7: Electricity | C7: Electric | P7: =SUM(D7:O7) -> 0
B8: Electricity | C8: Electric - Vacant | P8: =SUM(D8:O8) -> 0
B9: Gas | C9: Gas | P9: =SUM(D9:O9) -> 0
B10: Water | C10: Water | P10: =SUM(D10:O10) -> 0
B11: Water | C11: Sewer | P11: =SUM(D11:O11) -> 0
B12: Water | C12: Water-Irrigation | P12: =SUM(D12:O12) -> 0
P13: =SUM(D13:O13) -> 0
P14: =SUM(D14:O14) -> 0
P15: =SUM(D15:O15) -> 0
P16: =SUM(D16:O16) -> 0
P17: =SUM(D17:O17) -> 0
P18: =SUM(D18:O18) -> 0
P19: =SUM(D19:O19) -> 0
P20: =SUM(D20:O20) -> 0
P21: =SUM(D21:O21) -> 0
P22: =SUM(D22:O22) -> 0
B24: xx | C24: Total | D24: =SUM(D6:D22) -> 0 | E24: =SUM(E6:E22) -> 0 | F24: =SUM(F6:F22) -> 0 | G24: =SUM(G6:G22) -> 0 | H24: =SUM(H6:H22) -> 0 | I24: =SUM(I6:I22) -> 0 | J24: =SUM(J6:J22) -> 0 | K24: =SUM(K6:K22) -> 0 | ... O24: =SUM(O6:O22) -> 0 | P24: =SUM(D24:O24) -> 0
P26: =+P24/B3 -> #DIV/0!
P27: Per Unit

Sheet Rent Schedule
C2: Morgan Rental Rate Review
C3: Unit Type | D3: Bedrooms | E3: Unit Count | F3: Net SF | G3: PPSF | H3: Occupied Units | I3: Exposure | J3: Market Rent | K3: Weeks | L3: Concessions | M3: Effective Rent | N3: Effective Rent/SF | P3: Annual Rent (Market) | R3: Current Market Rate | S3: Current Market Rate/SF | T3: Variance | U3: Current Effective Rate | V3: Current Effective Rate/SF | X3: Current Annual Rent (Market) | Z3: Increase/(Decrease) in Market Rent | AA3: Increase/(Decrease) in Effective Rent | AB3: Increase (Effective) | AD3: % of Units | AE3: Net SF | AF3: Projected Rent/SF | AG3: Market Rent | AH3: Concessions | AI3: Effective Rent | AJ3: Effective Rent/SF
I4: =IFERROR(1-(H4/E4),"") | J4: =F4*G4 -> 0 | L4: =-J4/52*K4 -> 0 | M4: =J4+L4 -> 0 | N4: =IFERROR(M4/F4,"") | P4: =+J4*E4*12 -> 0 | S4: =IFERROR(R4/F4,"") | T4: =IFERROR((R4-U4)/R4,"") | V4: =IFERROR(U4/F4,"") | X4: =IFERROR(S4*F4*E4*12,"") | Z4: =IFERROR((P4-X4)/X4,"") | AA4: =IFERROR((M4-U4)/U4,"") | AB4: =M4-U4 -> 0 | AD4: =IFERROR(E4/$E$31,"") | AE4: =IFERROR(AD4*F4,"") | AF4: =IFERROR(AD4*G4,"") | AG4: =IFERROR(AD4*J4,"") | AH4: =IFERROR(AD4*L4,"") | AI4: =IFERROR(AD4*M4,"") | AJ4: =IFERROR(AD4*N4,"")
I5: =IFERROR(1-(H5/E5),"") | J5: =F5*G5 -> 0 | L5: =-J5/52*K5 -> 0 | M5: =J5+L5 -> 0 | N5: =IFERROR(M5/F5,"") | P5: =+J5*E5*12 -> 0 | S5: =IFERROR(R5/F5,"") | T5: =IFERROR((R5-U5)/R5,"") | V5: =IFERROR(U5/F5,"") | X5: =IFERROR(S5*F5*E5*12,"") | Z5: =IFERROR((P5-X5)/X5,"") | AA5: =IFERROR((M5-U5)/U5,"") | AB5: =M5-U5 -> 0 | AD5: =IFERROR(E5/$E$31,"") | AE5: =IFERROR(AD5*F5,"") | AF5: =IFERROR(AD5*G5,"") | AG5: =IFERROR(AD5*J5,"") | AH5: =IFERROR(AD5*L5,"") | AI5: =IFERROR(AD5*M5,"") | AJ5: =IFERROR(AD5*N5,"")
I6: =IFERROR(1-(H6/E6),"") | J6: =F6*G6 -> 0 | L6: =-J6/52*K6 -> 0 | M6: =J6+L6 -> 0 | N6: =IFERROR(M6/F6,"") | P6: =+J6*E6*12 -> 0 | S6: =IFERROR(R6/F6,"") | T6: =IFERROR((R6-U6)/R6,"") | V6: =IFERROR(U6/F6,"") | X6: =IFERROR(S6*F6*E6*12,"") | Z6: =IFERROR((P6-X6)/X6,"") | AA6: =IFERROR((M6-U6)/U6,"") | AB6: =M6-U6 -> 0 | AD6: =IFERROR(E6/$E$31,"") | AE6: =IFERROR(AD6*F6,"") | AF6: =IFERROR(AD6*G6,"") | AG6: =IFERROR(AD6*J6,"") | AH6: =IFERROR(AD6*L6,"") | AI6: =IFERROR(AD6*M6,"") | AJ6: =IFERROR(AD6*N6,"")
I7: =IFERROR(1-(H7/E7),"") | J7: =F7*G7 -> 0 | L7: =-J7/52*K7 -> 0 | M7: =J7+L7 -> 0 | N7: =IFERROR(M7/F7,"") | P7: =+J7*E7*12 -> 0 | S7: =IFERROR(R7/F7,"") | T7: =IFERROR((R7-U7)/R7,"") | V7: =IFERROR(U7/F7,"") | X7: =IFERROR(S7*F7*E7*12,"") | Z7: =IFERROR((P7-X7)/X7,"") | AA7: =IFERROR((M7-U7)/U7,"") | AB7: =M7-U7 -> 0 | AD7: =IFERROR(E7/$E$31,"") | AE7: =IFERROR(AD7*F7,"") | AF7: =IFERROR(AD7*G7,"") | AG7: =IFERROR(AD7*J7,"") | AH7: =IFERROR(AD7*L7,"") | AI7: =IFERROR(AD7*M7,"") | AJ7: =IFERROR(AD7*N7,"")
I8: =IFERROR(1-(H8/E8),"") | J8: =F8*G8 -> 0 | L8: =-J8/52*K8 -> 0 | M8: =J8+L8 -> 0 | N8: =IFERROR(M8/F8,"") | P8: =+J8*E8*12 -> 0 | S8: =IFERROR(R8/F8,"") | T8: =IFERROR((R8-U8)/R8,"") | V8: =IFERROR(U8/F8,"") | X8: =IFERROR(S8*F8*E8*12,"") | Z8: =IFERROR((P8-X8)/X8,"") | AA8: =IFERROR((M8-U8)/U8,"") | AB8: =M8-U8 -> 0 | AD8: =IFERROR(E8/$E$31,"") | AE8: =IFERROR(AD8*F8,"") | AF8: =IFERROR(AD8*G8,"") | AG8: =IFERROR(AD8*J8,"") | AH8: =IFERROR(AD8*L8,"") | AI8: =IFERROR(AD8*M8,"") | AJ8: =IFERROR(AD8*N8,"")
I9: =IFERROR(1-(H9/E9),"") | J9: =F9*G9 -> 0 | L9: =-J9/52*K9 -> 0 | M9: =J9+L9 -> 0 | N9: =IFERROR(M9/F9,"") | P9: =+J9*E9*12 -> 0 | S9: =IFERROR(R9/F9,"") | T9: =IFERROR((R9-U9)/R9,"") | V9: =IFERROR(U9/F9,"") | X9: =IFERROR(S9*F9*E9*12,"") | Z9: =IFERROR((P9-X9)/X9,"") | AA9: =IFERROR((M9-U9)/U9,"") | AB9: =M9-U9 -> 0 | AD9: =IFERROR(E9/$E$31,"") | AE9: =IFERROR(AD9*F9,"") | AF9: =IFERROR(AD9*G9,"") | AG9: =IFERROR(AD9*J9,"") | AH9: =IFERROR(AD9*L9,"") | AI9: =IFERROR(AD9*M9,"") | AJ9: =IFERROR(AD9*N9,"")
I10: =IFERROR(1-(H10/E10),"") | J10: =F10*G10 -> 0 | L10: =-J10/52*K10 -> 0 | M10: =J10+L10 -> 0 | N10: =IFERROR(M10/F10,"") | P10: =+J10*E10*12 -> 0 | S10: =IFERROR(R10/F10,"") | T10: =IFERROR((R10-U10)/R10,"") | V10: =IFERROR(U10/F10,"") | X10: =IFERROR(S10*F10*E10*12,"") | Z10: =IFERROR((P10-X10)/X10,"") | AA10: =IFERROR((M10-U10)/U10,"") | AB10: =M10-U10 -> 0 | AD10: =IFERROR(E10/$E$31,"") | AE10: =IFERROR(AD10*F10,"") | AF10: =IFERROR(AD10*G10,"") | AG10: =IFERROR(AD10*J10,"") | AH10: =IFERROR(AD10*L10,"") | AI10: =IFERROR(AD10*M10,"") | AJ10: =IFERROR(AD10*N10,"")
I11: =IFERROR(1-(H11/E11),"") | J11: =F11*G11 -> 0 | L11: =-J11/52*K11 -> 0 | M11: =J11+L11 -> 0 | N11: =IFERROR(M11/F11,"") | P11: =+J11*E11*12 -> 0 | S11: =IFERROR(R11/F11,"") | T11: =IFERROR((R11-U11)/R11,"") | V11: =IFERROR(U11/F11,"") | X11: =IFERROR(S11*F11*E11*12,"") | Z11: =IFERROR((P11-X11)/X11,"") | AA11: =IFERROR((M11-U11)/U11,"") | AB11: =M11-U11 -> 0 | AD11: =IFERROR(E11/$E$31,"") | AE11: =IFERROR(AD11*F11,"") | AF11: =IFERROR(AD11*G11,"") | AG11: =IFERROR(AD11*J11,"") | AH11: =IFERROR(AD11*L11,"") | AI11: =IFERROR(AD11*M11,"") | AJ11: =IFERROR(AD11*N11,"")
I12: =IFERROR(1-(H12/E12),"") | J12: =F12*G12 -> 0 | L12: =-J12/52*K12 -> 0 | M12: =J12+L12 -> 0 | N12: =IFERROR(M12/F12,"") | P12: =+J12*E12*12 -> 0 | S12: =IFERROR(R12/F12,"") | T12: =IFERROR((R12-U12)/R12,"") | V12: =IFERROR(U12/F12,"") | X12: =IFERROR(S12*F12*E12*12,"") | Z12: =IFERROR((P12-X12)/X12,"") | AA12: =IFERROR((M12-U12)/U12,"") | AB12: =M12-U12 -> 0 | AD12: =IFERROR(E12/$E$31,"") | AE12: =IFERROR(AD12*F12,"") | AF12: =IFERROR(AD12*G12,"") | AG12: =IFERROR(AD12*J12,"") | AH12: =IFERROR(AD12*L12,"") | AI12: =IFERROR(AD12*M12,"") | AJ12: =IFERROR(AD12*N12,"")
I13: =IFERROR(1-(H13/E13),"") | J13: =F13*G13 -> 0 | L13: =-J13/52*K13 -> 0 | M13: =J13+L13 -> 0 | N13: =IFERROR(M13/F13,"") | P13: =+J13*E13*12 -> 0 | S13: =IFERROR(R13/F13,"") | T13: =IFERROR((R13-U13)/R13,"") | V13: =IFERROR(U13/F13,"") | X13: =IFERROR(S13*F13*E13*12,"") | Z13: =IFERROR((P13-X13)/X13,"") | AA13: =IFERROR((M13-U13)/U13,"") | AB13: =M13-U13 -> 0 | AD13: =IFERROR(E13/$E$31,"") | AE13: =IFERROR(AD13*F13,"") | AF13: =IFERROR(AD13*G13,"") | AG13: =IFERROR(AD13*J13,"") | AH13: =IFERROR(AD13*L13,"") | AI13: =IFERROR(AD13*M13,"") | AJ13: =IFERROR(AD13*N13,"")
I14: =IFERROR(1-(H14/E14),"") | J14: =F14*G14 -> 0 | L14: =-J14/52*K14 -> 0 | M14: =J14+L14 -> 0 | N14: =IFERROR(M14/F14,"") | P14: =+J14*E14*12 -> 0 | S14: =IFERROR(R14/F14,"") | T14: =IFERROR((R14-U14)/R14,"") | V14: =IFERROR(U14/F14,"") | X14: =IFERROR(S14*F14*E14*12,"") | Z14: =IFERROR((P14-X14)/X14,"") | AA14: =IFERROR((M14-U14)/U14,"") | AB14: =M14-U14 -> 0 | AD14: =IFERROR(E14/$E$31,"") | AE14: =IFERROR(AD14*F14,"") | AF14: =IFERROR(AD14*G14,"") | AG14: =IFERROR(AD14*J14,"") | AH14: =IFERROR(AD14*L14,"") | AI14: =IFERROR(AD14*M14,"") | AJ14: =IFERROR(AD14*N14,"")
I15: =IFERROR(1-(H15/E15),"") | J15: =F15*G15 -> 0 | L15: =-J15/52*K15 -> 0 | M15: =J15+L15 -> 0 | N15: =IFERROR(M15/F15,"") | P15: =+J15*E15*12 -> 0 | S15: =IFERROR(R15/F15,"") | T15: =IFERROR((R15-U15)/R15,"") | V15: =IFERROR(U15/F15,"") | X15: =IFERROR(S15*F15*E15*12,"") | Z15: =IFERROR((P15-X15)/X15,"") | AA15: =IFERROR((M15-U15)/U15,"") | AB15: =M15-U15 -> 0 | AD15: =IFERROR(E15/$E$31,"") | AE15: =IFERROR(AD15*F15,"") | AF15: =IFERROR(AD15*G15,"") | AG15: =IFERROR(AD15*J15,"") | AH15: =IFERROR(AD15*L15,"") | AI15: =IFERROR(AD15*M15,"") | AJ15: =IFERROR(AD15*N15,"")
... I30: =IFERROR(1-(H30/E30),"") | J30: =F30*G30 -> 0 | L30: =-J30/52*K30 -> 0 | M30: =J30+L30 -> 0 | N30: =IFERROR(M30/F30,"") | P30: =+J30*E30*12 -> 0 | S30: =IFERROR(R30/F30,"") | T30: =IFERROR((R30-U30)/R30,"") | V30: =IFERROR(U30/F30,"") | X30: =IFERROR(S30*F30*E30*12,"") | Z30: =IFERROR((P30-X30)/X30,"") | AA30: =IFERROR((M30-U30)/U30,"") | AB30: =M30-U30 -> 0 | AD30: =IFERROR(E30/$E$31,"") | AE30: =IFERROR(AD30*F30,"") | AF30: =IFERROR(AD30*G30,"") | AG30: =IFERROR(AD30*J30,"") | AH30: =IFERROR(AD30*L30,"") | AI30: =IFERROR(AD30*M30,"") | AJ30: =IFERROR(AD30*N30,"")
C31: Total | E31: =SUM(E4:E30) -> 0 | F31: =SUMPRODUCT(F4:F30,E4:E30)/E31 -> #DIV/0! | G31: =IFERROR(J31/F31,"") | H31: =SUM(H4:H30) -> 0 | I31: =IFERROR(SUMPRODUCT(I4:I30,E4:E30)/E31,0) -> 0 | J31: =+SUMPRODUCT(E4:E30,J4:J30)/E31 -> #DIV/0! | K31: =IFERROR(SUMPRODUCT(E4:E30,K4:K30)/E31,0) -> 0 | L31: =+SUMPRODUCT(E4:E30,L4:L30)/E31 -> #DIV/0! | M31: =+SUMPRODUCT(E4:E30,M4:M30)/E31 -> #DIV/0! | N31: =IFERROR(M31/F31,0) -> 0 | P31: =+SUM(P4:P30) -> 0 | R31: =IFERROR(SUMPRODUCT(R4:R30,E4:E30)/SUM(E4:E30),0) -> 0 | S31: =IFERROR(SUMPRODUCT(R4:R30,E4:E30)/SUMPRODUCT(E4:E30,F4:F30),0) -> 0 | T31: =IFERROR(SUMPRODUCT(H4:H30,T4:T30)/H31,0) -> 0 | U31: =IFERROR(SUMPRODUCT(U4:U30,H4:H30)/SUM(H4:H30),0) -> 0 | V31: =IFERROR(SUMPRODUCT(U4:U30,H4:H30)/SUMPRODUCT(H4:H30,F4:F30),0) -> 0 | X31: =SUM(X4:X30) -> 0 | Z31: =IFERROR((P31-X31)/X31,0) -> 0 | AA31: =IFERROR((M31-U31)/U31,0) -> 0 | AB31: =IFERROR(SUMPRODUCT(E4:E30,AB4:AB30)/E31,0) -> 0 | AD31: =SUM(AD4:AD30) -> 0 | AE31: =SUM(AE4:AE30) -> 0 | AF31: =SUM(AF4:AF30) -> 0 | AG31: =SUM(AG4:AG30) -> 0 | AH31: =SUM(AH4:AH30) -> 0 | AI31: =SUM(AI4:AI30) -> 0 | AJ31: =SUM(AJ4:AJ30) -> 0

Sheet Absorption Schedule
B3: Target Occupancy | C3: Min. Units
B4: 0.93 | C4: =B4*'Rent Schedule'!$E$31 -> 0
B5: Start Date | C5: Monthly Absorption
B6: 46204 | C6: =IFERROR(AVERAGE(I35:AF35),"") -> 15.958333
B7: Beginning Occupancy | C7: Closing Ratio
B8: 0 | C8: 0.25
B9: Concessions | C9: Retention
B10: 0 | C10: 0.5
E12: Max Lease Expirations | I12: =ROUND('[1]Rent Schedule'!$E$22* _xlfn.XLOOKUP( TEXT(IFERROR(DATEVALUE("1 "&I$25), I$25), "mmmm"), CapMonth, CapPct ), 0 ) -> #REF! | J12: =ROUND('[1]Rent Schedule'!$E$22* _xlfn.XLOOKUP( TEXT(IFERROR(DATEVALUE("1 "&J$25), J$25), "mmmm"), CapMonth, CapPct ), 0 ) -> #REF! | K12: =ROUND('[1]Rent Schedule'!$E$22* _xlfn.XLOOKUP( TEXT(IFERROR(DATEVALUE("1 "&K$25), K$25), "mmmm"), CapMonth, CapPct ), 0 ) -> #REF! | L12: =ROUND('[1]Rent Schedule'!$E$22* _xlfn.XLOOKUP( TEXT(IFERROR(DATEVALUE("1 "&L$25), L$25), "mmmm"), CapMonth, CapPct ), 0 ) -> #REF! | M12: =ROUND('[1]Rent Schedule'!$E$22* _xlfn.XLOOKUP( TEXT(IFERROR(DATEVALUE("1 "&M$25), M$25), "mmmm"), CapMonth, CapPct ), 0 ) -> #REF! | N12: =ROUND('[1]Rent Schedule'!$E$22* _xlfn.XLOOKUP( TEXT(IFERROR(DATEVALUE("1 "&N$25), N$25), "mmmm"), CapMonth, CapPct ), 0 ) -> #REF! | O12: =ROUND('[1]Rent Schedule'!$E$22* _xlfn.XLOOKUP( TEXT(IFERROR(DATEVALUE("1 "&O$25), O$25), "mmmm"), CapMonth, CapPct ), 0 ) -> #REF! | P12: =ROUND('[1]Rent Schedule'!$E$22* _xlfn.XLOOKUP( TEXT(IFERROR(DATEVALUE("1 "&P$25), P$25), "mmmm"), CapMonth, CapPct ), 0 ) -> #REF! | ... AZ12: =ROUND('[1]Rent Schedule'!$E$22* _xlfn.XLOOKUP( TEXT(IFERROR(DATEVALUE("1 "&AZ$25), AZ$25), "mmmm"), CapMonth, CapPct ), 0 ) -> #REF!
E13: Existing Lease Expirations | I13: 0 | J13: 0 | K13: 0 | L13: 0 | M13: 0 | N13: 0 | O13: 0 | P13: 0 | Q13: 0 | R13: 0 | S13: 0 | T13: 0 | U13: 0 | V13: 0 | W13: 0 | X13: 0 | Y13: 0 | Z13: 0 | AA13: 0 | AB13: 0 | AC13: 0 | AD13: 0 | AE13: 0 | AF13: 0 | AG13: 0 | AH13: 0 | AI13: 0 | AJ13: 0 | AK13: 0 | AL13: 0 | AM13: 0 | AN13: 0 | AO13: 0 | AP13: 0 | AQ13: 0 | AR13: 0 | AS13: 0 | AT13: 0 | AU13: 0 | AV13: 0 | AW13: 0 | AX13: 0 | AY13: 0 | AZ13: 0
E14: Remaining Lease Expirations | I14: =MAX(0, I12 - I13) -> #REF! | J14: =MAX(0, J12 - J13) -> #REF! | K14: =MAX(0, K12 - K13) -> #REF! | L14: =MAX(0, L12 - L13) -> #REF! | M14: =MAX(0, M12 - M13) -> #REF! | N14: =MAX(0, N12 - N13) -> #REF! | O14: =MAX(0, O12 - O13) -> #REF! | P14: =MAX(0, P12 - P13) -> #REF! | ... AZ14: =MAX(0, AZ12 - AZ13) -> #REF!
E16: {=_xlfn.SEQUENCE($BB$5-$BB$3+1,1,$BB$3,1)} -> 0 | I16: =IFERROR(OFFSET(I$14,0,$E$16),0) -> 0 | J16: =IFERROR(OFFSET(J$14,0,$E$16),0) -> 0 | K16: =IFERROR(OFFSET(K$14,0,$E$16),0) -> 0 | L16: =IFERROR(OFFSET(L$14,0,$E$16),0) -> 0 | M16: =IFERROR(OFFSET(M$14,0,$E$16),0) -> 0 | N16: =IFERROR(OFFSET(N$14,0,$E$16),0) -> 0 | O16: =IFERROR(OFFSET(O$14,0,$E$16),0) -> 0 | P16: =IFERROR(OFFSET(P$14,0,$E$16),0) -> 0 | ... AF16: =IFERROR(OFFSET(AF$14,0,$E$16),0) -> 0
I17: =IFERROR(OFFSET(I$14,0,$E$17),0) -> 0 | J17: =IFERROR(OFFSET(J$14,0,$E$17),0) -> 0 | K17: =IFERROR(OFFSET(K$14,0,$E$17),0) -> 0 | L17: =IFERROR(OFFSET(L$14,0,$E$17),0) -> 0 | M17: =IFERROR(OFFSET(M$14,0,$E$17),0) -> 0 | N17: =IFERROR(OFFSET(N$14,0,$E$17),0) -> 0 | O17: =IFERROR(OFFSET(O$14,0,$E$17),0) -> 0 | P17: =IFERROR(OFFSET(P$14,0,$E$17),0) -> 0 | ... AF17: =IFERROR(OFFSET(AF$14,0,$E$17),0) -> 0
I18: =IFERROR(OFFSET(I$14,0,$E$18),0) -> 0 | J18: =IFERROR(OFFSET(J$14,0,$E$18),0) -> 0 | K18: =IFERROR(OFFSET(K$14,0,$E$18),0) -> 0 | L18: =IFERROR(OFFSET(L$14,0,$E$18),0) -> 0 | M18: =IFERROR(OFFSET(M$14,0,$E$18),0) -> 0 | N18: =IFERROR(OFFSET(N$14,0,$E$18),0) -> 0 | O18: =IFERROR(OFFSET(O$14,0,$E$18),0) -> 0 | P18: =IFERROR(OFFSET(P$14,0,$E$18),0) -> 0 | ... AF18: =IFERROR(OFFSET(AF$14,0,$E$18),0) -> 0
I19: =IFERROR(OFFSET(I$14,0,$E$19),0) -> 0 | J19: =IFERROR(OFFSET(J$14,0,$E$19),0) -> 0 | K19: =IFERROR(OFFSET(K$14,0,$E$19),0) -> 0 | L19: =IFERROR(OFFSET(L$14,0,$E$19),0) -> 0 | M19: =IFERROR(OFFSET(M$14,0,$E$19),0) -> 0 | N19: =IFERROR(OFFSET(N$14,0,$E$19),0) -> 0 | O19: =IFERROR(OFFSET(O$14,0,$E$19),0) -> 0 | P19: =IFERROR(OFFSET(P$14,0,$E$19),0) -> 0 | ... AF19: =IFERROR(OFFSET(AF$14,0,$E$19),0) -> 0
I20: =IFERROR(OFFSET(I$14,0,$E$20),0) -> 0 | J20: =IFERROR(OFFSET(J$14,0,$E$20),0) -> 0 | K20: =IFERROR(OFFSET(K$14,0,$E$20),0) -> 0 | L20: =IFERROR(OFFSET(L$14,0,$E$20),0) -> 0 | M20: =IFERROR(OFFSET(M$14,0,$E$20),0) -> 0 | N20: =IFERROR(OFFSET(N$14,0,$E$20),0) -> 0 | O20: =IFERROR(OFFSET(O$14,0,$E$20),0) -> 0 | P20: =IFERROR(OFFSET(P$14,0,$E$20),0) -> 0 | ... AF20: =IFERROR(OFFSET(AF$14,0,$E$20),0) -> 0
I21: =IFERROR(OFFSET(I$14,0,$E$21),0) -> 0 | J21: =IFERROR(OFFSET(J$14,0,$E$21),0) -> 0 | K21: =IFERROR(OFFSET(K$14,0,$E$21),0) -> 0 | L21: =IFERROR(OFFSET(L$14,0,$E$21),0) -> 0 | M21: =IFERROR(OFFSET(M$14,0,$E$21),0) -> 0 | N21: =IFERROR(OFFSET(N$14,0,$E$21),0) -> 0 | O21: =IFERROR(OFFSET(O$14,0,$E$21),0) -> 0 | P21: =IFERROR(OFFSET(P$14,0,$E$21),0) -> 0 | ... AF21: =IFERROR(OFFSET(AF$14,0,$E$21),0) -> 0
I23: 0 | J23: 0 | K23: =MAX(0, MIN(J16, I$32 - MIN(I$32, SUM($J16:J$21)))) -> 0 | L23: =SUMIFS($J$16:$J$21,$I$16:$I$21,L$14) -> 0 | M23: =SUMIFS($J$16:$J$21,$I$16:$I$21,M$14) -> 0 | N23: =SUMIFS($J$16:$J$21,$I$16:$I$21,N$14) -> 0 | O23: =SUMIFS($J$16:$J$21,$I$16:$I$21,O$14) -> 0 | P23: =SUMIFS($J$16:$J$21,$I$16:$I$21,P$14) -> 0 | Q23: =SUMIFS($J$16:$J$21,$I$16:$I$21,Q$14) -> 0 | R23: =SUMIFS($J$16:$J$21,$I$16:$I$21,R$14) -> 0 | S23: =SUMIFS($J$16:$J$21,$I$16:$I$21,S$14) -> 0 | ... AF23: =SUMIFS($J$16:$J$21,$I$16:$I$21,AF$14) -> 0
F24: Pre-Leasing
E25: Month | F25: =EOMONTH(G25,-1) -> 46142 | G25: =EOMONTH(H25,-1) -> 46173 | H25: =EOMONTH(I25,-1) -> 46203 | I25: =+B6 -> 46204 | J25: =EOMONTH(I25,1) -> 46265 | K25: =EOMONTH(J25,1) -> 46295 | L25: =EOMONTH(K25,1) -> 46326 | M25: =EOMONTH(L25,1) -> 46356 | N25: =EOMONTH(M25,1) -> 46387 | O25: =EOMONTH(N25,1) -> 46418 | P25: =EOMONTH(O25,1) -> 46446 | Q25: =EOMONTH(P25,1) -> 46477 | ... AZ25: =EOMONTH(AY25,1) -> 47542
E27: Lease Expirations
E28: Move-Outs | I28: =ROUNDUP((1-I29)*I27,0) -> 0 | J28: =ROUNDUP((1-J29)*J27,0) -> 0 | K28: =ROUNDUP((1-K29)*K27,0) -> 0 | L28: =ROUNDUP(L27*$C$10,0) -> 0 | M28: =ROUNDUP(M27*$C$10,0) -> 0 | N28: =ROUNDUP(N27*$C$10,0) -> 0 | O28: =ROUNDUP(O27*$C$10,0) -> 0 | P28: =ROUNDUP(P27*$C$10,0) -> 0 | Q28: =ROUNDUP(Q27*$C$10,0) -> 0 | R28: =ROUNDUP(R27*$C$10,0) -> 0 | S28: =ROUNDUP(S27*$C$10,0) -> 0 | ... AF28: =ROUNDUP(AF27*$C$10,0) -> 0
E29: Retention Ratio (Transition) | I29: 0.4 | J29: 0.4 | K29: 0.4
E31: Assumed Traffic | I31: 80 | J31: 90 | K31: 90 | L31: 85 | M31: 70 | N31: 70 | O31: 75 | P31: 75 | Q31: 75 | R31: 75 | S31: 75 | T31: 75 | U31: 75 | V31: 85 | W31: 50 | X31: 55 | Y31: 55 | Z31: 60 | AA31: 60 | AB31: 55 | AC31: 50 | AD31: 40 | AE31: 30 | AF31: 30
E32: New Leases | I32: =ROUNDDOWN($C$8*I31,0) -> 20 | J32: =ROUNDDOWN($C$8*J31,0) -> 22 | K32: =ROUNDDOWN($C$8*K31,0) -> 22 | L32: =ROUNDDOWN($C$8*L31,0) -> 21 | M32: =ROUNDDOWN($C$8*M31,0) -> 17 | N32: =ROUNDDOWN($C$8*N31,0) -> 17 | O32: =ROUNDDOWN($C$8*O31,0) -> 18 | P32: =ROUNDDOWN($C$8*P31,0) -> 18 | ... AF32: =ROUNDDOWN($C$8*AF31,0) -> 7
E35: Net Leases | I35: =I32-I28 -> 20 | J35: =J32-J28 -> 22 | K35: =K32-K28 -> 22 | L35: =L32-L28 -> 21 | M35: =M32-M28 -> 17 | N35: =N32-N28 -> 17 | O35: =O32-O28 -> 18 | P35: =P32-P28 -> 18 | ... AF35: =AF32-AF28 -> 7
E37: Occupied Units | H37: =ROUNDUP((1+'Proforma (Annual)'!N15)*'Proforma (Annual)'!C4,0) -> #DIV/0! | I37: =+H37 -> #DIV/0! | J37: =+I37+I35 -> #DIV/0! | K37: =+J37+J35 -> #DIV/0! | L37: =+K37+K35 -> #DIV/0! | M37: =+L37+L35 -> #DIV/0! | N37: =+M37+M35 -> #DIV/0! | O37: =+N37+N35 -> #DIV/0! | P37: =+O37+O35 -> #DIV/0! | Q37: =+P37+P35 -> #DIV/0! | ... T37: =+S37+S35 -> #DIV/0! | U37: =+T37+U35 -> #DIV/0! | V37: =+U37+V35 -> #DIV/0! | W37: =+V37+W35 -> #DIV/0! | X37: =+W37+X35 -> #DIV/0! | Y37: =+X37+Y35 -> #DIV/0! | Z37: =+Y37+Z35 -> #DIV/0! | AA37: =+Z37+AA35 -> #DIV/0! | AB37: =+AA37+AB35 -> #DIV/0! | ... AF37: =+AE37+AF35 -> #DIV/0!
E38: Total Units | I38: =+C4/B4 -> 0 | J38: =+I38 -> 0 | K38: =+J38 -> 0 | L38: =+K38 -> 0 | M38: =+L38 -> 0 | N38: =+M38 -> 0 | O38: =+N38 -> 0 | P38: =+O38 -> 0 | Q38: =+P38 -> 0 | ... AF38: =+AE38 -> 0
E39: Anticipated Occupancy | I39: =+I37/I38 -> #DIV/0! | J39: =+J37/J38 -> #DIV/0! | K39: =+K37/K38 -> #DIV/0! | L39: =+L37/L38 -> #DIV/0! | M39: =+M37/M38 -> #DIV/0! | N39: =+N37/N38 -> #DIV/0! | O39: =+O37/O38 -> #DIV/0! | P39: =+P37/P38 -> #DIV/0! | ... AF39: =+AF37/AF38 -> #DIV/0!
E41: Concessions | I41: =IFERROR(I37*$B$10,0) -> 0 | J41: =IFERROR(J37*$B$10,0) -> 0 | K41: =IFERROR(K37*$B$10,0) -> 0 | L41: =IFERROR(L37*$B$10,0) -> 0 | M41: =IFERROR(M37*$B$10,0) -> 0 | N41: =IFERROR(N37*$B$10,0) -> 0 | O41: =IFERROR(O37*$B$10,0) -> 0 | P41: =IFERROR(P37*$B$10,0) -> 0 | ... AF41: =IFERROR(AF37*$B$10,0) -> 0
I43: Retention Ratio during transition is projected at 40%. Renewals go out roughly 60 days prior to lease expiration, thus assuming a July transition, August and September renewals will have been distributed at a minimum. We are assuming a lower than average renewal ratio for this period.
I45: Closing ratio of 22% is projected based on our portfolio.
I46: Lease Expirations are based on current rent roll. This analysis does not project early terminations.

Sheet OUTPUTS

Sheet Proforma (Annual)
C1: Property Name
C2: ='T-12 Inputs'!C2 -> 0
C3: Units
C4: ='Rent Schedule'!E31 -> 0
E6: =CONCATENATE(C2,"- Annualized Financials") -> 0- Annualized Financials | R6: Owner Budget | U6: Morgan Underwriting | X6: Underwriting Notes
E7: Trailing - 12 | H7: Ann. Trailing - 6 | K7: Ann. Trailing - 3 | N7: Ann. Trailing - 1
E8: $ | F8: $/Unit | H8: $ | I8: $/Unit | K8: $ | L8: $/Unit | N8: $ | O8: $/Unit | R8: $ | S8: $/Unit | V8: $ | W8: $/Unit
C10: Market Rent | E10: {=+SUMPRODUCT('T-12 Inputs'!$D$7:$O$100*('T-12 Inputs'!$A$7:$A$100='OpStatement List - Dropdowns'!$I$5))} -> 0 | F10: =+E10/$C$4 -> #DIV/0! | H10: {=+SUMPRODUCT('T-12 Inputs'!$J$7:$O$100*('T-12 Inputs'!$A$7:$A$100='OpStatement List - Dropdowns'!$I$5))*2} -> 0 | I10: =+H10/$C$4 -> #DIV/0! | K10: {=+SUMPRODUCT('T-12 Inputs'!$M$7:$O$100*('T-12 Inputs'!$A$7:$A$100='OpStatement List - Dropdowns'!$I$5))*4} -> 0 | L10: =+K10/$C$4 -> #DIV/0! | N10: {=+SUMPRODUCT('T-12 Inputs'!$O$7:$O$100*('T-12 Inputs'!$A$7:$A$100='OpStatement List - Dropdowns'!$I$5))*12} -> 0 | O10: =+N10/$C$4 -> #DIV/0! | V10: =+E10 -> 0 | W10: =+V10/$C$4 -> #DIV/0!
C11: Loss to Lease | E11: {=+SUMPRODUCT('T-12 Inputs'!$D$7:$O$100*('T-12 Inputs'!$A$7:$A$100='OpStatement List - Dropdowns'!$I$6))} -> 0 | F11: =+E11/$C$4 -> #DIV/0! | H11: {=+SUMPRODUCT('T-12 Inputs'!$J$7:$O$100*('T-12 Inputs'!$A$7:$A$100='OpStatement List - Dropdowns'!$I$6))*2} -> 0 | I11: =+H11/$C$4 -> #DIV/0! | K11: {=+SUMPRODUCT('T-12 Inputs'!$M$7:$O$100*('T-12 Inputs'!$A$7:$A$100='OpStatement List - Dropdowns'!$I$6))*4} -> 0 | L11: =+K11/$C$4 -> #DIV/0! | N11: {=+SUMPRODUCT('T-12 Inputs'!$O$7:$O$100*('T-12 Inputs'!$A$7:$A$100='OpStatement List - Dropdowns'!$I$6))*12} -> 0 | O11: =+N11/$C$4 -> #DIV/0! | V11: =+V10*-U11 -> 0 | W11: =+V11/$C$4 -> #DIV/0!
C12: Gross Potential Rent | E12: =+SUM(E10:E11) -> 0 | F12: =+E12/$C$4 -> #DIV/0! | H12: =+SUM(H10:H11) -> 0 | I12: =+H12/$C$4 -> #DIV/0! | K12: =+SUM(K10:K11) -> 0 | L12: =+K12/$C$4 -> #DIV/0! | N12: =+SUM(N10:N11) -> 0 | O12: =+N12/$C$4 -> #DIV/0! | R12: =+SUM(R10:R11) -> 0 | S12: =+R12/C4 -> #DIV/0! | V12: =+SUM(V10:V11) -> 0 | W12: =+V12/$C$4 -> #DIV/0!
C14: Vacancy | E14: {=+SUMPRODUCT('T-12 Inputs'!$D$7:$O$100*('T-12 Inputs'!$A$7:$A$100='OpStatement List - Dropdowns'!$I$7))} -> 0 | F14: =+E14/$C$4 -> #DIV/0! | H14: {=+SUMPRODUCT('T-12 Inputs'!$J$7:$O$100*('T-12 Inputs'!$A$7:$A$100='OpStatement List - Dropdowns'!$I$7))*2} -> 0 | I14: =+H14/$C$4 -> #DIV/0! | K14: {=+SUMPRODUCT('T-12 Inputs'!$M$7:$O$100*('T-12 Inputs'!$A$7:$A$100='OpStatement List - Dropdowns'!I7))*4} -> 0 | L14: =+K14/$C$4 -> #DIV/0! | N14: {=+SUMPRODUCT('T-12 Inputs'!$O$7:$O$100*('T-12 Inputs'!$A$7:$A$100='OpStatement List - Dropdowns'!I7))*12} -> 0 | O14: =+N14/$C$4 -> #DIV/0! | S14: =+R14/$C$4 -> #DIV/0! | V14: =+U14*-$V$12 -> 0 | W14: =+V14/$C$4 -> #DIV/0!
C15: Vacancy (%) | E15: =+E14/E12 -> #DIV/0! | H15: =+H14/H12 -> #DIV/0! | K15: =+K14/K12 -> #DIV/0! | N15: =+N14/N12 -> #DIV/0!
C16: Concessions | E16: {=+SUMPRODUCT('T-12 Inputs'!$D$7:$O$100*('T-12 Inputs'!$A$7:$A$100='OpStatement List - Dropdowns'!$I$8))} -> 0 | F16: =+E16/$C$4 -> #DIV/0! | H16: {=+SUMPRODUCT('T-12 Inputs'!$J$7:$O$100*('T-12 Inputs'!$A$7:$A$100='OpStatement List - Dropdowns'!$I$8))*2} -> 0 | I16: =+H16/$C$4 -> #DIV/0! | K16: {=+SUMPRODUCT('T-12 Inputs'!$M$7:$O$100*('T-12 Inputs'!$A$7:$A$100='OpStatement List - Dropdowns'!I8))*4} -> 0 | L16: =+K16/$C$4 -> #DIV/0! | N16: {=+SUMPRODUCT('T-12 Inputs'!$O$7:$O$100*('T-12 Inputs'!$A$7:$A$100='OpStatement List - Dropdowns'!I8))*12} -> 0 | O16: =+N16/$C$4 -> #DIV/0! | S16: =+R16/$C$4 -> #DIV/0! | V16: =+U16*-$V$12 -> 0 | W16: =+V16/$C$4 -> #DIV/0!
C17: Bad Debt | E17: {=+SUMPRODUCT('T-12 Inputs'!$D$7:$O$100*('T-12 Inputs'!$A$7:$A$100='OpStatement List - Dropdowns'!$I$9))} -> 0 | F17: =+E17/$C$4 -> #DIV/0! | H17: {=+SUMPRODUCT('T-12 Inputs'!$J$7:$O$100*('T-12 Inputs'!$A$7:$A$100='OpStatement List - Dropdowns'!$I$9))*2} -> 0 | I17: =+H17/$C$4 -> #DIV/0! | K17: {=+SUMPRODUCT('T-12 Inputs'!$M$7:$O$100*('T-12 Inputs'!$A$7:$A$100='OpStatement List - Dropdowns'!I9))*4} -> 0 | L17: =+K17/$C$4 -> #DIV/0! | N17: {=+SUMPRODUCT('T-12 Inputs'!$O$7:$O$100*('T-12 Inputs'!$A$7:$A$100='OpStatement List - Dropdowns'!I9))*12} -> 0 | O17: =+N17/$C$4 -> #DIV/0! | S17: =+R17/$C$4 -> #DIV/0! | V17: =+U17*-$V$12 -> 0 | W17: =+V17/$C$4 -> #DIV/0!
C18: Model/Employee Discount | E18: {=+SUMPRODUCT('T-12 Inputs'!$D$7:$O$100*('T-12 Inputs'!$A$7:$A$100='OpStatement List - Dropdowns'!$I$10))} -> 0 | F18: =+E18/$C$4 -> #DIV/0! | H18: {=+SUMPRODUCT('T-12 Inputs'!$J$7:$O$100*('T-12 Inputs'!$A$7:$A$100='OpStatement List - Dropdowns'!$I$10))*2} -> 0 | I18: =+H18/$C$4 -> #DIV/0! | K18: {=+SUMPRODUCT('T-12 Inputs'!$M$7:$O$100*('T-12 Inputs'!$A$7:$A$100='OpStatement List - Dropdowns'!I10))*4} -> 0 | L18: =+K18/$C$4 -> #DIV/0! | N18: {=+SUMPRODUCT('T-12 Inputs'!$O$7:$O$100*('T-12 Inputs'!$A$7:$A$100='OpStatement List - Dropdowns'!I10))*12} -> 0 | O18: =+N18/$C$4 -> #DIV/0! | S18: =+R18/$C$4 -> #DIV/0! | U18: =-V18/V12 -> #DIV/0! | V18: =-12*1.7*'Rent Schedule'!J31 -> #DIV/0! | W18: =+V18/$C$4 -> #DIV/0!
C19: Economic Vacancy | E19: =+SUM(E16:E18,E14) -> 0 | F19: =SUM(F14:F17) -> #DIV/0! | H19: =+SUM(H16:H18,H14) -> 0 | I19: =SUM(I14:I17) -> #DIV/0! | K19: =+SUM(K16:K18,K14) -> 0 | L19: =SUM(L14:L17) -> #DIV/0! | N19: =+SUM(N16:N18,N14) -> 0 | O19: =SUM(O14:O17) -> #DIV/0! | R19: =SUM(R14:R18) -> 0 | S19: =SUM(S14:S17) -> #DIV/0! | V19: =SUM(V14:V18) -> #DIV/0! | W19: =+V19/$C$4 -> #DIV/0!
C21: Total Rental Income | E21: =+SUM(E12,E19) -> 0 | F21: =+E21/$C$4 -> #DIV/0! | H21: =+SUM(H12,H19) -> 0 | I21: =+H21/$C$4 -> #DIV/0! | K21: =+SUM(K12,K19) -> 0 | L21: =+K21/$C$4 -> #DIV/0! | N21: =+SUM(N12,N19) -> 0 | O21: =+N21/$C$4 -> #DIV/0! | R21: =+R12+R19 -> 0 | S21: =+R21/$C$4 -> #DIV/0! | V21: =+SUM(V12,V19) -> #DIV/0! | W21: =+V21/$C$4 -> #DIV/0!
C23: Administrative Fees | E23: {=+SUMPRODUCT('T-12 Inputs'!$D$7:$O$100*('T-12 Inputs'!$A$7:$A$100=C23))} -> 0 | F23: =+E23/$C$4 -> #DIV/0! | H23: {=+SUMPRODUCT('T-12 Inputs'!$J$7:$O$100*('T-12 Inputs'!$A$7:$A$100=C23))*2} -> 0 | I23: =+H23/$C$4 -> #DIV/0! | K23: {=+SUMPRODUCT('T-12 Inputs'!$M$7:$O$100*('T-12 Inputs'!$A$7:$A$100=C23))*4} -> 0 | L23: =+K23/$C$4 -> #DIV/0! | N23: {=+SUMPRODUCT('T-12 Inputs'!$O$7:$O$100*('T-12 Inputs'!$A$7:$A$100=C23))*12} -> 0 | O23: =+N23/$C$4 -> #DIV/0! | W23: =+V23/$C$4 -> #DIV/0!
C24: Amenity Fee | E24: {=+SUMPRODUCT('T-12 Inputs'!$D$7:$O$100*('T-12 Inputs'!$A$7:$A$100=C24))} -> 0 | F24: =+E24/$C$4 -> #DIV/0! | H24: {=+SUMPRODUCT('T-12 Inputs'!$J$7:$O$100*('T-12 Inputs'!$A$7:$A$100=C24))*2} -> 0 | I24: =+H24/$C$4 -> #DIV/0! | K24: {=+SUMPRODUCT('T-12 Inputs'!$M$7:$O$100*('T-12 Inputs'!$A$7:$A$100=C24))*4} -> 0 | L24: =+K24/$C$4 -> #DIV/0! | N24: {=+SUMPRODUCT('T-12 Inputs'!$O$7:$O$100*('T-12 Inputs'!$A$7:$A$100=C24))*12} -> 0 | O24: =+N24/$C$4 -> #DIV/0! | S24: =+R24/$C$4 -> #DIV/0! | W24: =+V24/$C$4 -> #DIV/0!
C25: Application Fees | E25: {=+SUMPRODUCT('T-12 Inputs'!$D$7:$O$100*('T-12 Inputs'!$A$7:$A$100=C25))} -> 0 | F25: =+E25/$C$4 -> #DIV/0! | H25: {=+SUMPRODUCT('T-12 Inputs'!$J$7:$O$100*('T-12 Inputs'!$A$7:$A$100=C25))*2} -> 0 | I25: =+H25/$C$4 -> #DIV/0! | K25: {=+SUMPRODUCT('T-12 Inputs'!$M$7:$O$100*('T-12 Inputs'!$A$7:$A$100=C25))*4} -> 0 | L25: =+K25/$C$4 -> #DIV/0! | N25: {=+SUMPRODUCT('T-12 Inputs'!$O$7:$O$100*('T-12 Inputs'!$A$7:$A$100=C25))*12} -> 0 | O25: =+N25/$C$4 -> #DIV/0! | S25: =+R25/$C$4 -> #DIV/0! | W25: =+V25/$C$4 -> #DIV/0!
C26: Cable Income | E26: {=+SUMPRODUCT('T-12 Inputs'!$D$7:$O$100*('T-12 Inputs'!$A$7:$A$100=C26))} -> 0 | F26: =+E26/$C$4 -> #DIV/0! | H26: {=+SUMPRODUCT('T-12 Inputs'!$J$7:$O$100*('T-12 Inputs'!$A$7:$A$100=C26))*2} -> 0 | I26: =+H26/$C$4 -> #DIV/0! | K26: {=+SUMPRODUCT('T-12 Inputs'!$M$7:$O$100*('T-12 Inputs'!$A$7:$A$100=C26))*4} -> 0 | L26: =+K26/$C$4 -> #DIV/0! | N26: {=+SUMPRODUCT('T-12 Inputs'!$O$7:$O$100*('T-12 Inputs'!$A$7:$A$100=C26))*12} -> 0 | O26: =+N26/$C$4 -> #DIV/0! | S26: =+R26/$C$4 -> #DIV/0! | W26: =+V26/$C$4 -> #DIV/0!
C27: Cleaning/R&M | E27: {=+SUMPRODUCT('T-12 Inputs'!$D$7:$O$100*('T-12 Inputs'!$A$7:$A$100=C27))} -> 0 | F27: =+E27/$C$4 -> #DIV/0! | H27: {=+SUMPRODUCT('T-12 Inputs'!$J$7:$O$100*('T-12 Inputs'!$A$7:$A$100=C27))*2} -> 0 | I27: =+H27/$C$4 -> #DIV/0! | K27: {=+SUMPRODUCT('T-12 Inputs'!$M$7:$O$100*('T-12 Inputs'!$A$7:$A$100=C27))*4} -> 0 | L27: =+K27/$C$4 -> #DIV/0! | N27: {=+SUMPRODUCT('T-12 Inputs'!$O$7:$O$100*('T-12 Inputs'!$A$7:$A$100=C27))*12} -> 0 | O27: =+N27/$C$4 -> #DIV/0! | S27: =+R27/$C$4 -> #DIV/0! | W27: =+V27/$C$4 -> #DIV/0!
C28: Commercial Income | E28: {=+SUMPRODUCT('T-12 Inputs'!$D$7:$O$100*('T-12 Inputs'!$A$7:$A$100=C28))} -> 0 | F28: =+E28/$C$4 -> #DIV/0! | H28: {=+SUMPRODUCT('T-12 Inputs'!$J$7:$O$100*('T-12 Inputs'!$A$7:$A$100=C28))*2} -> 0 | I28: =+H28/$C$4 -> #DIV/0! | K28: {=+SUMPRODUCT('T-12 Inputs'!$M$7:$O$100*('T-12 Inputs'!$A$7:$A$100=C28))*4} -> 0 | L28: =+K28/$C$4 -> #DIV/0! | N28: {=+SUMPRODUCT('T-12 Inputs'!$O$7:$O$100*('T-12 Inputs'!$A$7:$A$100=C28))*12} -> 0 | O28: =+N28/$C$4 -> #DIV/0! | S28: =+R28/$C$4 -> #DIV/0! | W28: =+V28/$C$4 -> #DIV/0!
C29: Damages/Eviction Fees | E29: {=+SUMPRODUCT('T-12 Inputs'!$D$7:$O$100*('T-12 Inputs'!$A$7:$A$100=C29))} -> 0 | F29: =+E29/$C$4 -> #DIV/0! | H29: {=+SUMPRODUCT('T-12 Inputs'!$J$7:$O$100*('T-12 Inputs'!$A$7:$A$100=C29))*2} -> 0 | I29: =+H29/$C$4 -> #DIV/0! | K29: {=+SUMPRODUCT('T-12 Inputs'!$M$7:$O$100*('T-12 Inputs'!$A$7:$A$100=C29))*4} -> 0 | L29: =+K29/$C$4 -> #DIV/0! | N29: {=+SUMPRODUCT('T-12 Inputs'!$O$7:$O$100*('T-12 Inputs'!$A$7:$A$100=C29))*12} -> 0 | O29: =+N29/$C$4 -> #DIV/0! | S29: =+R29/$C$4 -> #DIV/0! | W29: =+V29/$C$4 -> #DIV/0!
C30: Guest Suite Income | E30: {=+SUMPRODUCT('T-12 Inputs'!$D$7:$O$100*('T-12 Inputs'!$A$7:$A$100=C30))} -> 0 | F30: =+E30/$C$4 -> #DIV/0! | H30: {=+SUMPRODUCT('T-12 Inputs'!$J$7:$O$100*('T-12 Inputs'!$A$7:$A$100=C30))*2} -> 0 | I30: =+H30/$C$4 -> #DIV/0! | K30: {=+SUMPRODUCT('T-12 Inputs'!$M$7:$O$100*('T-12 Inputs'!$A$7:$A$100=C30))*4} -> 0 | L30: =+K30/$C$4 -> #DIV/0! | N30: {=+SUMPRODUCT('T-12 Inputs'!$O$7:$O$100*('T-12 Inputs'!$A$7:$A$100=C30))*12} -> 0 | O30: =+N30/$C$4 -> #DIV/0! | S30: =+R30/$C$4 -> #DIV/0! | W30: =+V30/$C$4 -> #DIV/0!
C31: Late Charges | E31: {=+SUMPRODUCT('T-12 Inputs'!$D$7:$O$100*('T-12 Inputs'!$A$7:$A$100=C31))} -> 0 | F31: =+E31/$C$4 -> #DIV/0! | H31: {=+SUMPRODUCT('T-12 Inputs'!$J$7:$O$100*('T-12 Inputs'!$A$7:$A$100=C31))*2} -> 0 | I31: =+H31/$C$4 -> #DIV/0! | K31: {=+SUMPRODUCT('T-12 Inputs'!$M$7:$O$100*('T-12 Inputs'!$A$7:$A$100=C31))*4} -> 0 | L31: =+K31/$C$4 -> #DIV/0! | N31: {=+SUMPRODUCT('T-12 Inputs'!$O$7:$O$100*('T-12 Inputs'!$A$7:$A$100=C31))*12} -> 0 | O31: =+N31/$C$4 -> #DIV/0! | S31: =+R31/$C$4 -> #DIV/0! | W31: =+V31/$C$4 -> #DIV/0!
C32: Legal Reimbursement | E32: {=+SUMPRODUCT('T-12 Inputs'!$D$7:$O$100*('T-12 Inputs'!$A$7:$A$100=C32))} -> 0 | F32: =+E32/$C$4 -> #DIV/0! | H32: {=+SUMPRODUCT('T-12 Inputs'!$J$7:$O$100*('T-12 Inputs'!$A$7:$A$100=C32))*2} -> 0 | I32: =+H32/$C$4 -> #DIV/0! | K32: {=+SUMPRODUCT('T-12 Inputs'!$M$7:$O$100*('T-12 Inputs'!$A$7:$A$100=C32))*4} -> 0 | L32: =+K32/$C$4 -> #DIV/0! | N32: {=+SUMPRODUCT('T-12 Inputs'!$O$7:$O$100*('T-12 Inputs'!$A$7:$A$100=C32))*12} -> 0 | O32: =+N32/$C$4 -> #DIV/0! | S32: =+R32/$C$4 -> #DIV/0! | W32: =+V32/$C$4 -> #DIV/0!
C33: Liability Insurance | E33: {=+SUMPRODUCT('T-12 Inputs'!$D$7:$O$100*('T-12 Inputs'!$A$7:$A$100=C33))} -> 0 | F33: =+E33/$C$4 -> #DIV/0! | H33: {=+SUMPRODUCT('T-12 Inputs'!$J$7:$O$100*('T-12 Inputs'!$A$7:$A$100=C33))*2} -> 0 | I33: =+H33/$C$4 -> #DIV/0! | K33: {=+SUMPRODUCT('T-12 Inputs'!$M$7:$O$100*('T-12 Inputs'!$A$7:$A$100=C33))*4} -> 0 | L33: =+K33/$C$4 -> #DIV/0! | N33: {=+SUMPRODUCT('T-12 Inputs'!$O$7:$O$100*('T-12 Inputs'!$A$7:$A$100=C33))*12} -> 0 | O33: =+N33/$C$4 -> #DIV/0! | W33: =+V33/$C$4 -> #DIV/0!
C34: MTM Fees | E34: {=+SUMPRODUCT('T-12 Inputs'!$D$7:$O$100*('T-12 Inputs'!$A$7:$A$100=C34))} -> 0 | F34: =+E34/$C$4 -> #DIV/0! | H34: {=+SUMPRODUCT('T-12 Inputs'!$J$7:$O$100*('T-12 Inputs'!$A$7:$A$100=C34))*2} -> 0 | I34: =+H34/$C$4 -> #DIV/0! | K34: {=+SUMPRODUCT('T-12 Inputs'!$M$7:$O$100*('T-12 Inputs'!$A$7:$A$100=C34))*4} -> 0 | L34: =+K34/$C$4 -> #DIV/0! | N34: {=+SUMPRODUCT('T-12 Inputs'!$O$7:$O$100*('T-12 Inputs'!$A$7:$A$100=C34))*12} -> 0 | O34: =+N34/$C$4 -> #DIV/0! | W34: =+V34/$C$4 -> #DIV/0!
C35: NSF Fees | E35: {=+SUMPRODUCT('T-12 Inputs'!$D$7:$O$100*('T-12 Inputs'!$A$7:$A$100=C35))} -> 0 | F35: =+E35/$C$4 -> #DIV/0! | H35: {=+SUMPRODUCT('T-12 Inputs'!$J$7:$O$100*('T-12 Inputs'!$A$7:$A$100=C35))*2} -> 0 | I35: =+H35/$C$4 -> #DIV/0! | K35: {=+SUMPRODUCT('T-12 Inputs'!$M$7:$O$100*('T-12 Inputs'!$A$7:$A$100=C35))*4} -> 0 | L35: =+K35/$C$4 -> #DIV/0! | N35: {=+SUMPRODUCT('T-12 Inputs'!$O$7:$O$100*('T-12 Inputs'!$A$7:$A$100=C35))*12} -> 0 | O35: =+N35/$C$4 -> #DIV/0! | W35: =+V35/$C$4 -> #DIV/0!
C36: Other Income | E36: {=+SUMPRODUCT('T-12 Inputs'!$D$7:$O$100*('T-12 Inputs'!$A$7:$A$100=C36))} -> 0 | F36: =+E36/$C$4 -> #DIV/0! | H36: {=+SUMPRODUCT('T-12 Inputs'!$J$7:$O$100*('T-12 Inputs'!$A$7:$A$100=C36))*2} -> 0 | I36: =+H36/$C$4 -> #DIV/0! | K36: {=+SUMPRODUCT('T-12 Inputs'!$M$7:$O$100*('T-12 Inputs'!$A$7:$A$100=C36))*4} -> 0 | L36: =+K36/$C$4 -> #DIV/0! | N36: {=+SUMPRODUCT('T-12 Inputs'!$O$7:$O$100*('T-12 Inputs'!$A$7:$A$100=C36))*12} -> 0 | O36: =+N36/$C$4 -> #DIV/0! | W36: =+V36/$C$4 -> #DIV/0!
C37: Package Fees | E37: {=+SUMPRODUCT('T-12 Inputs'!$D$7:$O$100*('T-12 Inputs'!$A$7:$A$100=C37))} -> 0 | F37: =+E37/$C$4 -> #DIV/0! | H37: {=+SUMPRODUCT('T-12 Inputs'!$J$7:$O$100*('T-12 Inputs'!$A$7:$A$100=C37))*2} -> 0 | I37: =+H37/$C$4 -> #DIV/0! | K37: {=+SUMPRODUCT('T-12 Inputs'!$M$7:$O$100*('T-12 Inputs'!$A$7:$A$100=C37))*4} -> 0 | L37: =+K37/$C$4 -> #DIV/0! | N37: {=+SUMPRODUCT('T-12 Inputs'!$O$7:$O$100*('T-12 Inputs'!$A$7:$A$100=C37))*12} -> 0 | O37: =+N37/$C$4 -> #DIV/0! | W37: =+V37/$C$4 -> #DIV/0!
C38: Parking | E38: {=+SUMPRODUCT('T-12 Inputs'!$D$7:$O$100*('T-12 Inputs'!$A$7:$A$100=C38))} -> 0 | F38: =+E38/$C$4 -> #DIV/0! | H38: {=+SUMPRODUCT('T-12 Inputs'!$J$7:$O$100*('T-12 Inputs'!$A$7:$A$100=C38))*2} -> 0 | I38: =+H38/$C$4 -> #DIV/0! | K38: {=+SUMPRODUCT('T-12 Inputs'!$M$7:$O$100*('T-12 Inputs'!$A$7:$A$100=C38))*4} -> 0 | L38: =+K38/$C$4 -> #DIV/0! | N38: {=+SUMPRODUCT('T-12 Inputs'!$O$7:$O$100*('T-12 Inputs'!$A$7:$A$100=C38))*12} -> 0 | O38: =+N38/$C$4 -> #DIV/0! | W38: =+V38/$C$4 -> #DIV/0!
C39: Pest | E39: {=+SUMPRODUCT('T-12 Inputs'!$D$7:$O$100*('T-12 Inputs'!$A$7:$A$100=C39))} -> 0 | F39: =+E39/$C$4 -> #DIV/0! | H39: {=+SUMPRODUCT('T-12 Inputs'!$J$7:$O$100*('T-12 Inputs'!$A$7:$A$100=C39))*2} -> 0 | I39: =+H39/$C$4 -> #DIV/0! | K39: {=+SUMPRODUCT('T-12 Inputs'!$M$7:$O$100*('T-12 Inputs'!$A$7:$A$100=C39))*4} -> 0 | L39: =+K39/$C$4 -> #DIV/0! | N39: {=+SUMPRODUCT('T-12 Inputs'!$O$7:$O$100*('T-12 Inputs'!$A$7:$A$100=C39))*12} -> 0 | O39: =+N39/$C$4 -> #DIV/0! | W39: =+V39/$C$4 -> #DIV/0!
C40: Pet | E40: {=+SUMPRODUCT('T-12 Inputs'!$D$7:$O$100*('T-12 Inputs'!$A$7:$A$100=C40))} -> 0 | F40: =+E40/$C$4 -> #DIV/0! | H40: {=+SUMPRODUCT('T-12 Inputs'!$J$7:$O$100*('T-12 Inputs'!$A$7:$A$100=C40))*2} -> 0 | I40: =+H40/$C$4 -> #DIV/0! | K40: {=+SUMPRODUCT('T-12 Inputs'!$M$7:$O$100*('T-12 Inputs'!$A$7:$A$100=C40))*4} -> 0 | L40: =+K40/$C$4 -> #DIV/0! | N40: {=+SUMPRODUCT('T-12 Inputs'!$O$7:$O$100*('T-12 Inputs'!$A$7:$A$100=C40))*12} -> 0 | O40: =+N40/$C$4 -> #DIV/0! | W40: =+V40/$C$4 -> #DIV/0!
C41: Resident Service Fee | E41: {=+SUMPRODUCT('T-12 Inputs'!$D$7:$O$100*('T-12 Inputs'!$A$7:$A$100=C41))} -> 0 | F41: =+E41/$C$4 -> #DIV/0! | H41: {=+SUMPRODUCT('T-12 Inputs'!$J$7:$O$100*('T-12 Inputs'!$A$7:$A$100=C41))*2} -> 0 | I41: =+H41/$C$4 -> #DIV/0! | K41: {=+SUMPRODUCT('T-12 Inputs'!$M$7:$O$100*('T-12 Inputs'!$A$7:$A$100=C41))*4} -> 0 | L41: =+K41/$C$4 -> #DIV/0! | N41: {=+SUMPRODUCT('T-12 Inputs'!$O$7:$O$100*('T-12 Inputs'!$A$7:$A$100=C41))*12} -> 0 | O41: =+N41/$C$4 -> #DIV/0! | W41: =+V41/$C$4 -> #DIV/0!
C42: Storage | E42: {=+SUMPRODUCT('T-12 Inputs'!$D$7:$O$100*('T-12 Inputs'!$A$7:$A$100=C42))} -> 0 | F42: =+E42/$C$4 -> #DIV/0! | H42: {=+SUMPRODUCT('T-12 Inputs'!$J$7:$O$100*('T-12 Inputs'!$A$7:$A$100=C42))*2} -> 0 | I42: =+H42/$C$4 -> #DIV/0! | K42: {=+SUMPRODUCT('T-12 Inputs'!$M$7:$O$100*('T-12 Inputs'!$A$7:$A$100=C42))*4} -> 0 | L42: =+K42/$C$4 -> #DIV/0! | N42: {=+SUMPRODUCT('T-12 Inputs'!$O$7:$O$100*('T-12 Inputs'!$A$7:$A$100=C42))*12} -> 0 | O42: =+N42/$C$4 -> #DIV/0! | W42: =+V42/$C$4 -> #DIV/0!
C43: Tech Package | E43: {=+SUMPRODUCT('T-12 Inputs'!$D$7:$O$100*('T-12 Inputs'!$A$7:$A$100=C43))} -> 0 | F43: =+E43/$C$4 -> #DIV/0! | H43: {=+SUMPRODUCT('T-12 Inputs'!$J$7:$O$100*('T-12 Inputs'!$A$7:$A$100=C43))*2} -> 0 | I43: =+H43/$C$4 -> #DIV/0! | K43: {=+SUMPRODUCT('T-12 Inputs'!$M$7:$O$100*('T-12 Inputs'!$A$7:$A$100=C43))*4} -> 0 | L43: =+K43/$C$4 -> #DIV/0! | N43: {=+SUMPRODUCT('T-12 Inputs'!$O$7:$O$100*('T-12 Inputs'!$A$7:$A$100=C43))*12} -> 0 | O43: =+N43/$C$4 -> #DIV/0! | W43: =+V43/$C$4 -> #DIV/0!
C44: Termination/Transfer Fees | E44: {=+SUMPRODUCT('T-12 Inputs'!$D$7:$O$100*('T-12 Inputs'!$A$7:$A$100=C44))} -> 0 | F44: =+E44/$C$4 -> #DIV/0! | H44: {=+SUMPRODUCT('T-12 Inputs'!$J$7:$O$100*('T-12 Inputs'!$A$7:$A$100=C44))*2} -> 0 | I44: =+H44/$C$4 -> #DIV/0! | K44: {=+SUMPRODUCT('T-12 Inputs'!$M$7:$O$100*('T-12 Inputs'!$A$7:$A$100=C44))*4} -> 0 | L44: =+K44/$C$4 -> #DIV/0! | N44: {=+SUMPRODUCT('T-12 Inputs'!$O$7:$O$100*('T-12 Inputs'!$A$7:$A$100=C44))*12} -> 0 | O44: =+N44/$C$4 -> #DIV/0! | W44: =+V44/$C$4 -> #DIV/0!
... C47: Valet Income | E47: {=+SUMPRODUCT('T-12 Inputs'!$D$7:$O$100*('T-12 Inputs'!$A$7:$A$100=C47))} -> 0 | F47: =+E47/$C$4 -> #DIV/0! | H47: {=+SUMPRODUCT('T-12 Inputs'!$J$7:$O$100*('T-12 Inputs'!$A$7:$A$100=C47))*2} -> 0 | I47: =+H47/$C$4 -> #DIV/0! | K47: {=+SUMPRODUCT('T-12 Inputs'!$M$7:$O$100*('T-12 Inputs'!$A$7:$A$100=C47))*4} -> 0 | L47: =+K47/$C$4 -> #DIV/0! | N47: {=+SUMPRODUCT('T-12 Inputs'!$O$7:$O$100*('T-12 Inputs'!$A$7:$A$100=C47))*12} -> 0 | O47: =+N47/$C$4 -> #DIV/0! | W47: =+V47/$C$4 -> #DIV/0!
C48: Total Other Income | E48: =SUM(E23:E47) -> 0 | F48: =+E48/$C$4 -> #DIV/0! | H48: =SUM(H23:H47) -> 0 | I48: =+H48/$C$4 -> #DIV/0! | K48: =SUM(K23:K47) -> 0 | L48: =+K48/$C$4 -> #DIV/0! | N48: =SUM(N23:N47) -> 0 | O48: =+N48/$C$4 -> #DIV/0! | R48: =SUM(R24:R34) -> 0 | S48: =+R48/$C$4 -> #DIV/0! | V48: =SUM(V23:V47) -> 0 | W48: =+V48/$C$4 -> #DIV/0!
C50: Effective Gross Income | E50: =+E21+E48 -> 0 | F50: =+F21+F48 -> #DIV/0! | H50: =+H21+H48 -> 0 | I50: =+I21+I48 -> #DIV/0! | K50: =+K21+K48 -> 0 | L50: =+L21+L48 -> #DIV/0! | N50: =+N21+N48 -> 0 | O50: =+O21+O48 -> #DIV/0! | R50: =+R21+R48 -> 0 | S50: =+R50/C4 -> #DIV/0! | V50: =+V21+V48 -> #DIV/0! | W50: =+V50/$C$4 -> #DIV/0!
C52: Expenses
C54: Salary - Property Management | E54: {=+SUMPRODUCT('T-12 Inputs'!$D$105:$O$430*('T-12 Inputs'!$A$105:$A$430=C54))} -> 0 | F54: =+E54/$C$4 -> #DIV/0! | H54: {=+SUMPRODUCT('T-12 Inputs'!$J$105:$O$430*('T-12 Inputs'!$A$105:$A$430=C54))*2} -> 0 | I54: =+H54/$C$4 -> #DIV/0! | K54: {=+SUMPRODUCT('T-12 Inputs'!$M$105:$O$430*('T-12 Inputs'!$A$105:$A$430=C54))*4} -> 0 | L54: =+K54/$C$4 -> #DIV/0! | N54: {=+SUMPRODUCT('T-12 Inputs'!$O$105:$O$430*('T-12 Inputs'!$A$105:$A$430=C54))*12} -> 0 | O54: =+N54/$C$4 -> #DIV/0! | S54: =+R54/$C$4 -> #DIV/0! | V54: ='Payroll Schedule'!G21 -> 226040 | W54: =+V54/$C$4 -> #DIV/0! | Y54: Please see Payroll Schedule tab for details.
C55: Salary - Maintenance | E55: {=+SUMPRODUCT('T-12 Inputs'!$D$105:$O$430*('T-12 Inputs'!$A$105:$A$430=C55))} -> 0 | F55: =+E55/$C$4 -> #DIV/0! | H55: {=+SUMPRODUCT('T-12 Inputs'!$J$105:$O$430*('T-12 Inputs'!$A$105:$A$430=C55))*2} -> 0 | I55: =+H55/$C$4 -> #DIV/0! | K55: {=+SUMPRODUCT('T-12 Inputs'!$M$105:$O$430*('T-12 Inputs'!$A$105:$A$430=C55))*4} -> 0 | L55: =+K55/$C$4 -> #DIV/0! | N55: {=+SUMPRODUCT('T-12 Inputs'!$O$105:$O$430*('T-12 Inputs'!$A$105:$A$430=C55))*12} -> 0 | O55: =+N55/$C$4 -> #DIV/0! | S55: =+R55/$C$4 -> #DIV/0! | V55: ='Payroll Schedule'!G34 -> 198640 | W55: =+V55/$C$4 -> #DIV/0! | Y55: Please see Payroll Schedule tab for details.
C56: Payroll - Burden | E56: {=+SUMPRODUCT('T-12 Inputs'!$D$105:$O$430*('T-12 Inputs'!$A$105:$A$430=C56))} -> 0 | F56: =+E56/$C$4 -> #DIV/0! | H56: {=+SUMPRODUCT('T-12 Inputs'!$J$105:$O$430*('T-12 Inputs'!$A$105:$A$430=C56))*2} -> 0 | I56: =+H56/$C$4 -> #DIV/0! | K56: {=+SUMPRODUCT('T-12 Inputs'!$M$105:$O$430*('T-12 Inputs'!$A$105:$A$430=C56))*4} -> 0 | L56: =+K56/$C$4 -> #DIV/0! | N56: {=+SUMPRODUCT('T-12 Inputs'!$O$105:$O$430*('T-12 Inputs'!$A$105:$A$430=C56))*12} -> 0 | O56: =+N56/$C$4 -> #DIV/0! | V56: =+SUM('Payroll Schedule'!H21,'Payroll Schedule'!H34,'Payroll Schedule'!D51) -> 114482.5 | W56: =+V56/$C$4 -> #DIV/0! | Y56: =CONCATENATE("Morgan burden estimated at ",TEXT('Payroll Schedule'!H13,"0%")," vs. in-place burden of ",TEXT(ROUND(E56/SUM(E54:E55),2),"0%"),".") -> #DIV/0!
C57: Payroll - Miscellaneous | E57: {=+SUMPRODUCT('T-12 Inputs'!$D$105:$O$430*('T-12 Inputs'!$A$105:$A$430=C57))} -> 0 | F57: =+E57/$C$4 -> #DIV/0! | H57: {=+SUMPRODUCT('T-12 Inputs'!$J$105:$O$430*('T-12 Inputs'!$A$105:$A$430=C57))*2} -> 0 | I57: =+H57/$C$4 -> #DIV/0! | K57: {=+SUMPRODUCT('T-12 Inputs'!$M$105:$O$430*('T-12 Inputs'!$A$105:$A$430=C57))*4} -> 0 | L57: =+K57/$C$4 -> #DIV/0! | N57: {=+SUMPRODUCT('T-12 Inputs'!$O$105:$O$430*('T-12 Inputs'!$A$105:$A$430=C57))*12} -> 0 | O57: =+N57/$C$4 -> #DIV/0! | V57: 0 | W57: =+V57/$C$4 -> #DIV/0!
C58: Leasing Bonuses | E58: {=+SUMPRODUCT('T-12 Inputs'!$D$105:$O$430*('T-12 Inputs'!$A$105:$A$430=C58))} -> 0 | F58: =+E58/$C$4 -> #DIV/0! | H58: {=+SUMPRODUCT('T-12 Inputs'!$J$105:$O$430*('T-12 Inputs'!$A$105:$A$430=C58))*2} -> 0 | I58: =+H58/$C$4 -> #DIV/0! | K58: {=+SUMPRODUCT('T-12 Inputs'!$M$105:$O$430*('T-12 Inputs'!$A$105:$A$430=C58))*4} -> 0 | L58: =+K58/$C$4 -> #DIV/0! | N58: {=+SUMPRODUCT('T-12 Inputs'!$O$105:$O$430*('T-12 Inputs'!$A$105:$A$430=C58))*12} -> 0 | O58: =+N58/$C$4 -> #DIV/0! | S58: =+R58/$C$4 -> #DIV/0! | V58: =+'Payroll Schedule'!D40 -> 0 | W58: =+V58/$C$4 -> #DIV/0! | Y58: Please see Payroll Schedule tab for details.
C59: Bonuses | E59: {=+SUMPRODUCT('T-12 Inputs'!$D$105:$O$430*('T-12 Inputs'!$A$105:$A$430=C59))} -> 0 | F59: =+E59/$C$4 -> #DIV/0! | H59: {=+SUMPRODUCT('T-12 Inputs'!$J$105:$O$430*('T-12 Inputs'!$A$105:$A$430=C59))*2} -> 0 | I59: =+H59/$C$4 -> #DIV/0! | K59: {=+SUMPRODUCT('T-12 Inputs'!$M$105:$O$430*('T-12 Inputs'!$A$105:$A$430=C59))*4} -> 0 | L59: =+K59/$C$4 -> #DIV/0! | N59: {=+SUMPRODUCT('T-12 Inputs'!$O$105:$O$430*('T-12 Inputs'!$A$105:$A$430=C59))*12} -> 0 | O59: =+N59/$C$4 -> #DIV/0! | S59: =+R59/$C$4 -> #DIV/0! | V59: =+'Payroll Schedule'!C51 -> 33250 | W59: =+V59/$C$4 -> #DIV/0! | Y59: Please see Payroll Schedule tab for details.
C60: Total Payroll | E60: =SUM(E54:E59) -> 0 | F60: =+E60/$C$4 -> #DIV/0! | H60: =SUM(H54:H59) -> 0 | I60: =+H60/$C$4 -> #DIV/0! | K60: =SUM(K54:K59) -> 0 | L60: =+K60/$C$4 -> #DIV/0! | N60: =SUM(N54:N59) -> 0 | O60: =+N60/$C$4 -> #DIV/0! | R60: =SUM(R54:R59) -> 0 | S60: =+R60/$C$4 -> #DIV/0! | V60: =SUM(V54:V59) -> 572412.5 | W60: =+V60/C4 -> #DIV/0!
C62: ='OpStatement List - Dropdowns'!L13 -> G&A | E62: {=+SUMPRODUCT('T-12 Inputs'!$D$105:$O$430*('T-12 Inputs'!$A$105:$A$430=C62))} -> 0 | F62: =+E62/$C$4 -> #DIV/0! | H62: {=+SUMPRODUCT('T-12 Inputs'!$J$105:$O$430*('T-12 Inputs'!$A$105:$A$430=C62))*2} -> 0 | I62: =+H62/$C$4 -> #DIV/0! | K62: {=+SUMPRODUCT('T-12 Inputs'!$M$105:$O$430*('T-12 Inputs'!$A$105:$A$430=C62))*4} -> 0 | L62: =+K62/$C$4 -> #DIV/0! | N62: {=+SUMPRODUCT('T-12 Inputs'!$O$105:$O$430*('T-12 Inputs'!$A$105:$A$430=C62))*12} -> 0 | O62: =+N62/$C$4 -> #DIV/0! | S62: =+R62/$C$4 -> #DIV/0! | V62: =+E62 -> 0 | W62: =+V62/$C$4 -> #DIV/0!
C63: ='OpStatement List - Dropdowns'!L14 -> Supplies | E63: {=+SUMPRODUCT('T-12 Inputs'!$D$105:$O$430*('T-12 Inputs'!$A$105:$A$430=C63))} -> 0 | F63: =+E63/$C$4 -> #DIV/0! | H63: {=+SUMPRODUCT('T-12 Inputs'!$J$105:$O$430*('T-12 Inputs'!$A$105:$A$430=C63))*2} -> 0 | I63: =+H63/$C$4 -> #DIV/0! | K63: {=+SUMPRODUCT('T-12 Inputs'!$M$105:$O$430*('T-12 Inputs'!$A$105:$A$430=C63))*4} -> 0 | L63: =+K63/$C$4 -> #DIV/0! | N63: {=+SUMPRODUCT('T-12 Inputs'!$O$105:$O$430*('T-12 Inputs'!$A$105:$A$430=C63))*12} -> 0 | O63: =+N63/$C$4 -> #DIV/0! | S63: =+R63/$C$4 -> #DIV/0! | V63: =+E63 -> 0 | W63: =+V63/$C$4 -> #DIV/0!
C64: ='OpStatement List - Dropdowns'!L15 -> Memberships | E64: {=+SUMPRODUCT('T-12 Inputs'!$D$105:$O$430*('T-12 Inputs'!$A$105:$A$430=C64))} -> 0 | F64: =+E64/$C$4 -> #DIV/0! | H64: {=+SUMPRODUCT('T-12 Inputs'!$J$105:$O$430*('T-12 Inputs'!$A$105:$A$430=C64))*2} -> 0 | I64: =+H64/$C$4 -> #DIV/0! | K64: {=+SUMPRODUCT('T-12 Inputs'!$M$105:$O$430*('T-12 Inputs'!$A$105:$A$430=C64))*4} -> 0 | L64: =+K64/$C$4 -> #DIV/0! | N64: {=+SUMPRODUCT('T-12 Inputs'!$O$105:$O$430*('T-12 Inputs'!$A$105:$A$430=C64))*12} -> 0 | O64: =+N64/$C$4 -> #DIV/0! | S64: =+R64/$C$4 -> #DIV/0! | V64: =+E64 -> 0 | W64: =+V64/$C$4 -> #DIV/0!
C65: ='OpStatement List - Dropdowns'!L16 -> Telephone | E65: {=+SUMPRODUCT('T-12 Inputs'!$D$105:$O$430*('T-12 Inputs'!$A$105:$A$430=C65))} -> 0 | F65: =+E65/$C$4 -> #DIV/0! | H65: {=+SUMPRODUCT('T-12 Inputs'!$J$105:$O$430*('T-12 Inputs'!$A$105:$A$430=C65))*2} -> 0 | I65: =+H65/$C$4 -> #DIV/0! | K65: {=+SUMPRODUCT('T-12 Inputs'!$M$105:$O$430*('T-12 Inputs'!$A$105:$A$430=C65))*4} -> 0 | L65: =+K65/$C$4 -> #DIV/0! | N65: {=+SUMPRODUCT('T-12 Inputs'!$O$105:$O$430*('T-12 Inputs'!$A$105:$A$430=C65))*12} -> 0 | O65: =+N65/$C$4 -> #DIV/0! | S65: =+R65/$C$4 -> #DIV/0! | V65: =+E65 -> 0 | W65: =+V65/$C$4 -> #DIV/0!
C66: Legal | E66: {=+SUMPRODUCT('T-12 Inputs'!$D$105:$O$430*('T-12 Inputs'!$A$105:$A$430=C66))} -> 0 | F66: =+E66/$C$4 -> #DIV/0! | H66: {=+SUMPRODUCT('T-12 Inputs'!$J$105:$O$430*('T-12 Inputs'!$A$105:$A$430=C66))*2} -> 0 | I66: =+H66/$C$4 -> #DIV/0! | K66: {=+SUMPRODUCT('T-12 Inputs'!$M$105:$O$430*('T-12 Inputs'!$A$105:$A$430=C66))*4} -> 0 | L66: =+K66/$C$4 -> #DIV/0! | N66: {=+SUMPRODUCT('T-12 Inputs'!$O$105:$O$430*('T-12 Inputs'!$A$105:$A$430=C66))*12} -> 0 | O66: =+N66/$C$4 -> #DIV/0! | V66: =+E66 -> 0 | W66: =+V66/$C$4 -> #DIV/0!
C67: Bank Charges | E67: {=+SUMPRODUCT('T-12 Inputs'!$D$105:$O$430*('T-12 Inputs'!$A$105:$A$430=C67))} -> 0 | F67: =+E67/$C$4 -> #DIV/0! | H67: {=+SUMPRODUCT('T-12 Inputs'!$J$105:$O$430*('T-12 Inputs'!$A$105:$A$430=C67))*2} -> 0 | I67: =+H67/$C$4 -> #DIV/0! | K67: {=+SUMPRODUCT('T-12 Inputs'!$M$105:$O$430*('T-12 Inputs'!$A$105:$A$430=C67))*4} -> 0 | L67: =+K67/$C$4 -> #DIV/0! | N67: {=+SUMPRODUCT('T-12 Inputs'!$O$105:$O$430*('T-12 Inputs'!$A$105:$A$430=C67))*12} -> 0 | O67: =+N67/$C$4 -> #DIV/0! | V67: =+E67 -> 0 | W67: =+V67/$C$4 -> #DIV/0!
C68: Eviction Charges | E68: {=+SUMPRODUCT('T-12 Inputs'!$D$105:$O$430*('T-12 Inputs'!$A$105:$A$430=C68))} -> 0 | F68: =+E68/$C$4 -> #DIV/0! | H68: {=+SUMPRODUCT('T-12 Inputs'!$J$105:$O$430*('T-12 Inputs'!$A$105:$A$430=C68))*2} -> 0 | I68: =+H68/$C$4 -> #DIV/0! | K68: {=+SUMPRODUCT('T-12 Inputs'!$M$105:$O$430*('T-12 Inputs'!$A$105:$A$430=C68))*4} -> 0 | L68: =+K68/$C$4 -> #DIV/0! | N68: {=+SUMPRODUCT('T-12 Inputs'!$O$105:$O$430*('T-12 Inputs'!$A$105:$A$430=C68))*12} -> 0 | O68: =+N68/$C$4 -> #DIV/0! | V68: =+E68 -> 0 | W68: =+V68/$C$4 -> #DIV/0!
C69: Internet - GA | E69: {=+SUMPRODUCT('T-12 Inputs'!$D$105:$O$430*('T-12 Inputs'!$A$105:$A$430=C69))} -> 0 | F69: =+E69/$C$4 -> #DIV/0! | H69: {=+SUMPRODUCT('T-12 Inputs'!$J$105:$O$430*('T-12 Inputs'!$A$105:$A$430=C69))*2} -> 0 | I69: =+H69/$C$4 -> #DIV/0! | K69: {=+SUMPRODUCT('T-12 Inputs'!$M$105:$O$430*('T-12 Inputs'!$A$105:$A$430=C69))*4} -> 0 | L69: =+K69/$C$4 -> #DIV/0! | N69: {=+SUMPRODUCT('T-12 Inputs'!$O$105:$O$430*('T-12 Inputs'!$A$105:$A$430=C69))*12} -> 0 | O69: =+N69/$C$4 -> #DIV/0! | V69: =+E69 -> 0 | W69: =+V69/$C$4 -> #DIV/0!
C70: G&A - Miscellaneous | E70: {=+SUMPRODUCT('T-12 Inputs'!$D$105:$O$430*('T-12 Inputs'!$A$105:$A$430=C70))} -> 0 | F70: =+E70/$C$4 -> #DIV/0! | H70: {=+SUMPRODUCT('T-12 Inputs'!$J$105:$O$430*('T-12 Inputs'!$A$105:$A$430=C70))*2} -> 0 | I70: =+H70/$C$4 -> #DIV/0! | K70: {=+SUMPRODUCT('T-12 Inputs'!$M$105:$O$430*('T-12 Inputs'!$A$105:$A$430=C70))*4} -> 0 | L70: =+K70/$C$4 -> #DIV/0! | N70: {=+SUMPRODUCT('T-12 Inputs'!$O$105:$O$430*('T-12 Inputs'!$A$105:$A$430=C70))*12} -> 0 | O70: =+N70/$C$4 -> #DIV/0! | S70: =+R70/$C$4 -> #DIV/0! | V70: =+E70 -> 0 | W70: =+V70/$C$4 -> #DIV/0!
C71: Total G&A | E71: =SUM(E62:E70) -> 0 | F71: =+E71/$C$4 -> #DIV/0! | H71: =SUM(H62:H70) -> 0 | I71: =+H71/$C$4 -> #DIV/0! | K71: =SUM(K62:K70) -> 0 | L71: =+K71/$C$4 -> #DIV/0! | N71: =SUM(N62:N70) -> 0 | O71: =+N71/$C$4 -> #DIV/0! | R71: =SUM(R62:R70) -> 0 | S71: =+R71/$C$4 -> #DIV/0! | V71: =SUM(V62:V70) -> 0 | W71: =+V71/$C$4 -> #DIV/0!
C73: Locator Fees | E73: {=+SUMPRODUCT('T-12 Inputs'!$D$105:$O$430*('T-12 Inputs'!$A$105:$A$430=C73))} -> 0 | F73: =+E73/$C$4 -> #DIV/0! | H73: {=+SUMPRODUCT('T-12 Inputs'!$J$105:$O$430*('T-12 Inputs'!$A$105:$A$430=C73))*2} -> 0 | I73: =+H73/$C$4 -> #DIV/0! | K73: {=+SUMPRODUCT('T-12 Inputs'!$M$105:$O$430*('T-12 Inputs'!$A$105:$A$430=C73))*4} -> 0 | L73: =+K73/$C$4 -> #DIV/0! | N73: {=+SUMPRODUCT('T-12 Inputs'!$O$105:$O$430*('T-12 Inputs'!$A$105:$A$430=C73))*12} -> 0 | O73: =+N73/$C$4 -> #DIV/0! | S73: =+R73/$C$4 -> #DIV/0! | V73: =SUMIF('Marketing Stack'!$B$6:$B$41,'Proforma (Annual)'!C73,'Marketing Stack'!$Q$6:$Q$41) -> 6000 | W73: =+V73/$C$4 -> #DIV/0! | Y73: Please see the Marketing Stack - Stabilized tab for details.
C74: Marketing | E74: {=+SUMPRODUCT('T-12 Inputs'!$D$105:$O$430*('T-12 Inputs'!$A$105:$A$430=C74))} -> 0 | F74: =+E74/$C$4 -> #DIV/0! | H74: {=+SUMPRODUCT('T-12 Inputs'!$J$105:$O$430*('T-12 Inputs'!$A$105:$A$430=C74))*2} -> 0 | I74: =+H74/$C$4 -> #DIV/0! | K74: {=+SUMPRODUCT('T-12 Inputs'!$M$105:$O$430*('T-12 Inputs'!$A$105:$A$430=C74))*4} -> 0 | L74: =+K74/$C$4 -> #DIV/0! | N74: {=+SUMPRODUCT('T-12 Inputs'!$O$105:$O$430*('T-12 Inputs'!$A$105:$A$430=C74))*12} -> 0 | O74: =+N74/$C$4 -> #DIV/0! | S74: =+R74/$C$4 -> #DIV/0! | V74: =SUMIF('Marketing Stack'!$B$6:$B$41,'Proforma (Annual)'!C74,'Marketing Stack'!$Q$6:$Q$41) -> 70632 | W74: =+V74/$C$4 -> #DIV/0! | Y74: Please see the Marketing Stack - Stabilized tab for details.
C75: Referral Fees | E75: {=+SUMPRODUCT('T-12 Inputs'!$D$105:$O$430*('T-12 Inputs'!$A$105:$A$430=C75))} -> 0 | F75: =+E75/$C$4 -> #DIV/0! | H75: {=+SUMPRODUCT('T-12 Inputs'!$J$105:$O$430*('T-12 Inputs'!$A$105:$A$430=C75))*2} -> 0 | I75: =+H75/$C$4 -> #DIV/0! | K75: {=+SUMPRODUCT('T-12 Inputs'!$M$105:$O$430*('T-12 Inputs'!$A$105:$A$430=C75))*4} -> 0 | L75: =+K75/$C$4 -> #DIV/0! | N75: {=+SUMPRODUCT('T-12 Inputs'!$O$105:$O$430*('T-12 Inputs'!$A$105:$A$430=C75))*12} -> 0 | O75: =+N75/$C$4 -> #DIV/0! | S75: =+R75/$C$4 -> #DIV/0! | V75: =SUMIF('Marketing Stack'!$B$6:$B$41,'Proforma (Annual)'!C75,'Marketing Stack'!$Q$6:$Q$41) -> 0 | W75: =+V75/$C$4 -> #DIV/0! | Y75: Please see the Marketing Stack - Stabilized tab for details.
C76: Resident Retention | E76: {=+SUMPRODUCT('T-12 Inputs'!$D$105:$O$430*('T-12 Inputs'!$A$105:$A$430=C76))} -> 0 | F76: =+E76/$C$4 -> #DIV/0! | H76: {=+SUMPRODUCT('T-12 Inputs'!$J$105:$O$430*('T-12 Inputs'!$A$105:$A$430=C76))*2} -> 0 | I76: =+H76/$C$4 -> #DIV/0! | K76: {=+SUMPRODUCT('T-12 Inputs'!$M$105:$O$430*('T-12 Inputs'!$A$105:$A$430=C76))*4} -> 0 | L76: =+K76/$C$4 -> #DIV/0! | N76: {=+SUMPRODUCT('T-12 Inputs'!$O$105:$O$430*('T-12 Inputs'!$A$105:$A$430=C76))*12} -> 0 | O76: =+N76/$C$4 -> #DIV/0! | S76: =+R76/$C$4 -> #DIV/0! | V76: =SUMIF('Marketing Stack'!$B$6:$B$41,'Proforma (Annual)'!C76,'Marketing Stack'!$Q$6:$Q$41) -> 15000 | W76: =+V76/$C$4 -> #DIV/0!
C77: Total Marketing | E77: =SUM(E73:E76) -> 0 | F77: =+E77/$C$4 -> #DIV/0! | H77: =SUM(H73:H76) -> 0 | I77: =+H77/$C$4 -> #DIV/0! | K77: =SUM(K73:K76) -> 0 | L77: =+K77/$C$4 -> #DIV/0! | N77: =SUM(N73:N76) -> 0 | O77: =+N77/$C$4 -> #DIV/0! | R77: =SUM(R73:R76) -> 0 | S77: =+R77/$C$4 -> #DIV/0! | V77: =SUM(V73:V76) -> 91632 | W77: =+V77/C4 -> #DIV/0!
C79: R&M | E79: {=+SUMPRODUCT('T-12 Inputs'!$D$105:$O$430*('T-12 Inputs'!$A$105:$A$430=C79))} -> 0 | F79: =+E79/$C$4 -> #DIV/0! | H79: {=+SUMPRODUCT('T-12 Inputs'!$J$105:$O$430*('T-12 Inputs'!$A$105:$A$430=C79))*2} -> 0 | I79: =+H79/$C$4 -> #DIV/0! | K79: {=+SUMPRODUCT('T-12 Inputs'!$M$105:$O$430*('T-12 Inputs'!$A$105:$A$430=C79))*4} -> 0 | L79: =+K79/$C$4 -> #DIV/0! | N79: {=+SUMPRODUCT('T-12 Inputs'!$O$105:$O$430*('T-12 Inputs'!$A$105:$A$430=C79))*12} -> 0 | O79: =+N79/$C$4 -> #DIV/0! | V79: =+E79 -> 0 | W79: =+V79/$C$4 -> #DIV/0!
C80: Make-Ready/Redec | E80: {=+SUMPRODUCT('T-12 Inputs'!$D$105:$O$430*('T-12 Inputs'!$A$105:$A$430=C80))} -> 0 | F80: =+E80/$C$4 -> #DIV/0! | H80: {=+SUMPRODUCT('T-12 Inputs'!$J$105:$O$430*('T-12 Inputs'!$A$105:$A$430=C80))*2} -> 0 | I80: =+H80/$C$4 -> #DIV/0! | K80: {=+SUMPRODUCT('T-12 Inputs'!$M$105:$O$430*('T-12 Inputs'!$A$105:$A$430=C80))*4} -> 0 | L80: =+K80/$C$4 -> #DIV/0! | N80: {=+SUMPRODUCT('T-12 Inputs'!$O$105:$O$430*('T-12 Inputs'!$A$105:$A$430=C80))*12} -> 0 | O80: =+N80/$C$4 -> #DIV/0! | V80: =+E80 -> 0 | W80: =+V80/$C$4 -> #DIV/0!
C81: Landscaping | E81: {=+SUMPRODUCT('T-12 Inputs'!$D$105:$O$430*('T-12 Inputs'!$A$105:$A$430=C81))} -> 0 | F81: =+E81/$C$4 -> #DIV/0! | H81: {=+SUMPRODUCT('T-12 Inputs'!$J$105:$O$430*('T-12 Inputs'!$A$105:$A$430=C81))*2} -> 0 | I81: =+H81/$C$4 -> #DIV/0! | K81: {=+SUMPRODUCT('T-12 Inputs'!$M$105:$O$430*('T-12 Inputs'!$A$105:$A$430=C81))*4} -> 0 | L81: =+K81/$C$4 -> #DIV/0! | N81: {=+SUMPRODUCT('T-12 Inputs'!$O$105:$O$430*('T-12 Inputs'!$A$105:$A$430=C81))*12} -> 0 | O81: =+N81/$C$4 -> #DIV/0! | V81: =+E81 -> 0 | W81: =+V81/$C$4 -> #DIV/0!
C82: R&M - Trash | E82: {=+SUMPRODUCT('T-12 Inputs'!$D$105:$O$430*('T-12 Inputs'!$A$105:$A$430=C82))} -> 0 | F82: =+E82/$C$4 -> #DIV/0! | H82: {=+SUMPRODUCT('T-12 Inputs'!$J$105:$O$430*('T-12 Inputs'!$A$105:$A$430=C82))*2} -> 0 | I82: =+H82/$C$4 -> #DIV/0! | K82: {=+SUMPRODUCT('T-12 Inputs'!$M$105:$O$430*('T-12 Inputs'!$A$105:$A$430=C82))*4} -> 0 | L82: =+K82/$C$4 -> #DIV/0! | N82: {=+SUMPRODUCT('T-12 Inputs'!$O$105:$O$430*('T-12 Inputs'!$A$105:$A$430=C82))*12} -> 0 | O82: =+N82/$C$4 -> #DIV/0! | V82: =+E82 -> 0 | W82: =+V82/$C$4 -> #DIV/0!
C83: Pest | E83: {=+SUMPRODUCT('T-12 Inputs'!$D$105:$O$430*('T-12 Inputs'!$A$105:$A$430=C83))} -> 0 | F83: =+E83/$C$4 -> #DIV/0! | H83: {=+SUMPRODUCT('T-12 Inputs'!$J$105:$O$430*('T-12 Inputs'!$A$105:$A$430=C83))*2} -> 0 | I83: =+H83/$C$4 -> #DIV/0! | K83: {=+SUMPRODUCT('T-12 Inputs'!$M$105:$O$430*('T-12 Inputs'!$A$105:$A$430=C83))*4} -> 0 | L83: =+K83/$C$4 -> #DIV/0! | N83: {=+SUMPRODUCT('T-12 Inputs'!$O$105:$O$430*('T-12 Inputs'!$A$105:$A$430=C83))*12} -> 0 | O83: =+N83/$C$4 -> #DIV/0! | V83: =+E83 -> 0 | W83: =+V83/$C$4 -> #DIV/0!
C84: Contract Services | E84: {=+SUMPRODUCT('T-12 Inputs'!$D$105:$O$430*('T-12 Inputs'!$A$105:$A$430=C84))} -> 0 | F84: =+E84/$C$4 -> #DIV/0! | H84: {=+SUMPRODUCT('T-12 Inputs'!$J$105:$O$430*('T-12 Inputs'!$A$105:$A$430=C84))*2} -> 0 | I84: =+H84/$C$4 -> #DIV/0! | K84: {=+SUMPRODUCT('T-12 Inputs'!$M$105:$O$430*('T-12 Inputs'!$A$105:$A$430=C84))*4} -> 0 | L84: =+K84/$C$4 -> #DIV/0! | N84: {=+SUMPRODUCT('T-12 Inputs'!$O$105:$O$430*('T-12 Inputs'!$A$105:$A$430=C84))*12} -> 0 | O84: =+N84/$C$4 -> #DIV/0! | V84: =+E84 -> 0 | W84: =+V84/$C$4 -> #DIV/0!
C85: Tenant Billback Expense | E85: {=+SUMPRODUCT('T-12 Inputs'!$D$105:$O$430*('T-12 Inputs'!$A$105:$A$430=C85))} -> 0 | F85: =+E85/$C$4 -> #DIV/0! | H85: {=+SUMPRODUCT('T-12 Inputs'!$J$105:$O$430*('T-12 Inputs'!$A$105:$A$430=C85))*2} -> 0 | I85: =+H85/$C$4 -> #DIV/0! | K85: {=+SUMPRODUCT('T-12 Inputs'!$M$105:$O$430*('T-12 Inputs'!$A$105:$A$430=C85))*4} -> 0 | L85: =+K85/$C$4 -> #DIV/0! | N85: {=+SUMPRODUCT('T-12 Inputs'!$O$105:$O$430*('T-12 Inputs'!$A$105:$A$430=C85))*12} -> 0 | O85: =+N85/$C$4 -> #DIV/0! | V85: =+E85 -> 0 | W85: =+V85/$C$4 -> #DIV/0!
C86: Contract Services - Concierge | E86: {=+SUMPRODUCT('T-12 Inputs'!$D$105:$O$430*('T-12 Inputs'!$A$105:$A$430=C86))} -> 0 | F86: =+E86/$C$4 -> #DIV/0! | H86: {=+SUMPRODUCT('T-12 Inputs'!$J$105:$O$430*('T-12 Inputs'!$A$105:$A$430=C86))*2} -> 0 | I86: =+H86/$C$4 -> #DIV/0! | K86: {=+SUMPRODUCT('T-12 Inputs'!$M$105:$O$430*('T-12 Inputs'!$A$105:$A$430=C86))*4} -> 0 | L86: =+K86/$C$4 -> #DIV/0! | N86: {=+SUMPRODUCT('T-12 Inputs'!$O$105:$O$430*('T-12 Inputs'!$A$105:$A$430=C86))*12} -> 0 | O86: =+N86/$C$4 -> #DIV/0! | V86: =+E86 -> 0 | W86: =+V86/$C$4 -> #DIV/0!
C87: R&M - Trash Reimbursement | E87: {=+SUMPRODUCT('T-12 Inputs'!$D$105:$O$430*('T-12 Inputs'!$A$105:$A$430=C87))} -> 0 | F87: =+E87/$C$4 -> #DIV/0! | H87: {=+SUMPRODUCT('T-12 Inputs'!$J$105:$O$430*('T-12 Inputs'!$A$105:$A$430=C87))*2} -> 0 | I87: =+H87/$C$4 -> #DIV/0! | K87: {=+SUMPRODUCT('T-12 Inputs'!$M$105:$O$430*('T-12 Inputs'!$A$105:$A$430=C87))*4} -> 0 | L87: =+K87/$C$4 -> #DIV/0! | N87: {=+SUMPRODUCT('T-12 Inputs'!$O$105:$O$430*('T-12 Inputs'!$A$105:$A$430=C87))*12} -> 0 | O87: =+N87/$C$4 -> #DIV/0! | V87: =+E87 -> 0 | W87: =+V87/$C$4 -> #DIV/0!
C88: Total R&M | E88: =SUM(E79:E87) -> 0 | F88: =+E88/$C$4 -> #DIV/0! | H88: =SUM(H79:H87) -> 0 | I88: =+H88/$C$4 -> #DIV/0! | K88: =SUM(K79:K87) -> 0 | L88: =+K88/$C$4 -> #DIV/0! | N88: =SUM(N79:N87) -> 0 | O88: =+N88/$C$4 -> #DIV/0! | R88: =SUM(R79:R87) -> 0 | S88: =+R88/$C$4 -> #DIV/0! | V88: =SUM(V79:V87) -> 0 | W88: =+V88/C4 -> #DIV/0!
C90: Electricity | E90: {=+SUMPRODUCT('T-12 Inputs'!$D$105:$O$430*('T-12 Inputs'!$A$105:$A$430=C90))} -> 0 | F90: =+E90/$C$4 -> #DIV/0! | H90: {=+SUMPRODUCT('T-12 Inputs'!$J$105:$O$430*('T-12 Inputs'!$A$105:$A$430=C90))*2} -> 0 | I90: =+H90/$C$4 -> #DIV/0! | K90: {=+SUMPRODUCT('T-12 Inputs'!$M$105:$O$430*('T-12 Inputs'!$A$105:$A$430=C90))*4} -> 0 | L90: =+K90/$C$4 -> #DIV/0! | N90: {=+SUMPRODUCT('T-12 Inputs'!$O$105:$O$430*('T-12 Inputs'!$A$105:$A$430=C90))*12} -> 0 | O90: =+N90/$C$4 -> #DIV/0! | V90: =E90 -> 0 | W90: =+V90/$C$4 -> #DIV/0! | Y90: T-12
C91: Water | E91: {=+SUMPRODUCT('T-12 Inputs'!$D$105:$O$430*('T-12 Inputs'!$A$105:$A$430=C91))} -> 0 | F91: =+E91/$C$4 -> #DIV/0! | H91: {=+SUMPRODUCT('T-12 Inputs'!$J$105:$O$430*('T-12 Inputs'!$A$105:$A$430=C91))*2} -> 0 | I91: =+H91/$C$4 -> #DIV/0! | K91: {=+SUMPRODUCT('T-12 Inputs'!$M$105:$O$430*('T-12 Inputs'!$A$105:$A$430=C91))*4} -> 0 | L91: =+K91/$C$4 -> #DIV/0! | N91: {=+SUMPRODUCT('T-12 Inputs'!$O$105:$O$430*('T-12 Inputs'!$A$105:$A$430=C91))*12} -> 0 | O91: =+N91/$C$4 -> #DIV/0! | V91: =E91 -> 0 | W91: =+V91/$C$4 -> #DIV/0! | Y91: T-12
C92: Trash | E92: {=+SUMPRODUCT('T-12 Inputs'!$D$105:$O$430*('T-12 Inputs'!$A$105:$A$430=C92))} -> 0 | F92: =+E92/$C$4 -> #DIV/0! | H92: {=+SUMPRODUCT('T-12 Inputs'!$J$105:$O$430*('T-12 Inputs'!$A$105:$A$430=C92))*2} -> 0 | I92: =+H92/$C$4 -> #DIV/0! | K92: {=+SUMPRODUCT('T-12 Inputs'!$M$105:$O$430*('T-12 Inputs'!$A$105:$A$430=C92))*4} -> 0 | L92: =+K92/$C$4 -> #DIV/0! | N92: {=+SUMPRODUCT('T-12 Inputs'!$O$105:$O$430*('T-12 Inputs'!$A$105:$A$430=C92))*12} -> 0 | O92: =+N92/$C$4 -> #DIV/0! | V92: =E92 -> 0 | W92: =+V92/$C$4 -> #DIV/0! | Y92: T-12
C93: Gas | E93: {=+SUMPRODUCT('T-12 Inputs'!$D$105:$O$430*('T-12 Inputs'!$A$105:$A$430=C93))} -> 0 | F93: =+E93/$C$4 -> #DIV/0! | H93: {=+SUMPRODUCT('T-12 Inputs'!$J$105:$O$430*('T-12 Inputs'!$A$105:$A$430=C93))*2} -> 0 | I93: =+H93/$C$4 -> #DIV/0! | K93: {=+SUMPRODUCT('T-12 Inputs'!$M$105:$O$430*('T-12 Inputs'!$A$105:$A$430=C93))*4} -> 0 | L93: =+K93/$C$4 -> #DIV/0! | N93: {=+SUMPRODUCT('T-12 Inputs'!$O$105:$O$430*('T-12 Inputs'!$A$105:$A$430=C93))*12} -> 0 | O93: =+N93/$C$4 -> #DIV/0! | V93: =E93 -> 0 | W93: =+V93/$C$4 -> #DIV/0! | Y93: T-12
C94: Utility Fees | E94: {=+SUMPRODUCT('T-12 Inputs'!$D$105:$O$430*('T-12 Inputs'!$A$105:$A$430=C94))} -> 0 | F94: =+E94/$C$4 -> #DIV/0! | H94: {=+SUMPRODUCT('T-12 Inputs'!$J$105:$O$430*('T-12 Inputs'!$A$105:$A$430=C94))*2} -> 0 | I94: =+H94/$C$4 -> #DIV/0! | K94: {=+SUMPRODUCT('T-12 Inputs'!$M$105:$O$430*('T-12 Inputs'!$A$105:$A$430=C94))*4} -> 0 | L94: =+K94/$C$4 -> #DIV/0! | N94: {=+SUMPRODUCT('T-12 Inputs'!$O$105:$O$430*('T-12 Inputs'!$A$105:$A$430=C94))*12} -> 0 | O94: =+N94/$C$4 -> #DIV/0! | V94: =E94 -> 0 | W94: =+V94/$C$4 -> #DIV/0! | Y94: T-12
C95: Internet - Utilities | E95: {=+SUMPRODUCT('T-12 Inputs'!$D$105:$O$430*('T-12 Inputs'!$A$105:$A$430=C95))} -> 0 | F95: =+E95/$C$4 -> #DIV/0! | H95: {=+SUMPRODUCT('T-12 Inputs'!$J$105:$O$430*('T-12 Inputs'!$A$105:$A$430=C95))*2} -> 0 | I95: =+H95/$C$4 -> #DIV/0! | K95: {=+SUMPRODUCT('T-12 Inputs'!$M$105:$O$430*('T-12 Inputs'!$A$105:$A$430=C95))*4} -> 0 | L95: =+K95/$C$4 -> #DIV/0! | N95: {=+SUMPRODUCT('T-12 Inputs'!$O$105:$O$430*('T-12 Inputs'!$A$105:$A$430=C95))*12} -> 0 | O95: =+N95/$C$4 -> #DIV/0! | V95: =E95 -> 0 | W95: =+V95/$C$4 -> #DIV/0!
C96: Trash - Reimbursement | E96: {=+SUMPRODUCT('T-12 Inputs'!$D$105:$O$430*('T-12 Inputs'!$A$105:$A$430=C96))} -> 0 | F96: =+E96/$C$4 -> #DIV/0! | H96: {=+SUMPRODUCT('T-12 Inputs'!$J$105:$O$430*('T-12 Inputs'!$A$105:$A$430=C96))*2} -> 0 | I96: =+H96/$C$4 -> #DIV/0! | K96: {=+SUMPRODUCT('T-12 Inputs'!$M$105:$O$430*('T-12 Inputs'!$A$105:$A$430=C96))*4} -> 0 | L96: =+K96/$C$4 -> #DIV/0! | N96: {=+SUMPRODUCT('T-12 Inputs'!$O$105:$O$430*('T-12 Inputs'!$A$105:$A$430=C96))*12} -> 0 | O96: =+N96/$C$4 -> #DIV/0! | V96: =E96 -> 0 | W96: =+V96/$C$4 -> #DIV/0!
C97: Utility Reimbursement | E97: {=+SUMPRODUCT('T-12 Inputs'!$D$105:$O$430*('T-12 Inputs'!$A$105:$A$430=C97))} -> 0 | F97: =+E97/$C$4 -> #DIV/0! | H97: {=+SUMPRODUCT('T-12 Inputs'!$J$105:$O$430*('T-12 Inputs'!$A$105:$A$430=C97))*2} -> 0 | I97: =+H97/$C$4 -> #DIV/0! | K97: {=+SUMPRODUCT('T-12 Inputs'!$M$105:$O$430*('T-12 Inputs'!$A$105:$A$430=C97))*4} -> 0 | L97: =+K97/$C$4 -> #DIV/0! | N97: {=+SUMPRODUCT('T-12 Inputs'!$O$105:$O$430*('T-12 Inputs'!$A$105:$A$430=C97))*12} -> 0 | O97: =+N97/$C$4 -> #DIV/0! | V97: =E97 -> 0 | W97: =+V97/$C$4 -> #DIV/0!
C98: Total Utilities | E98: =SUM(E90:E97) -> 0 | F98: =+E98/$C$4 -> #DIV/0! | H98: =SUM(H90:H97) -> 0 | I98: =+H98/$C$4 -> #DIV/0! | K98: =SUM(K90:K97) -> 0 | L98: =+K98/$C$4 -> #DIV/0! | N98: =SUM(N90:N97) -> 0 | O98: =+N98/$C$4 -> #DIV/0! | R98: =SUM(R90:R97) -> 0 | S98: =+R98/$C$4 -> #DIV/0! | V98: =SUM(V90:V97) -> 0 | W98: =+V98/C4 -> #DIV/0!
C100: Total Controllable Expenses | E100: =+SUM(E60,E71,E77,E88,E98) -> 0 | F100: =+E100/$C$4 -> #DIV/0! | H100: =+SUM(H60,H71,H77,H88,H98,) -> 0 | I100: =+H100/$C$4 -> #DIV/0! | K100: =+SUM(K60,K71,K77,K88,K98,) -> 0 | L100: =+K100/$C$4 -> #DIV/0! | N100: =+SUM(N60,N71,N77,N88,N98,) -> 0 | O100: =+N100/$C$4 -> #DIV/0! | R100: =+SUM(R47,R59,R65,R75,R82,R88,R92,R98) -> 0 | S100: =+R100/$C$4 -> #DIV/0! | V100: =+SUM(V60,V71,V77,V88,V98,) -> 664044.5 | W100: =+V100/$C$4 -> #DIV/0!
C102: Management Fee | E102: {=+SUMPRODUCT('T-12 Inputs'!$D$105:$O$430*('T-12 Inputs'!$A$105:$A$430=C102))} -> 0 | F102: =+E102/$C$4 -> #DIV/0! | H102: {=+SUMPRODUCT('T-12 Inputs'!$J$105:$O$430*('T-12 Inputs'!$A$105:$A$430=C102))*2} -> 0 | I102: =+H102/$C$4 -> #DIV/0! | K102: {=+SUMPRODUCT('T-12 Inputs'!$M$105:$O$430*('T-12 Inputs'!$A$105:$A$430=C102))*4} -> 0 | L102: =+K102/$C$4 -> #DIV/0! | N102: {=+SUMPRODUCT('T-12 Inputs'!$O$105:$O$430*('T-12 Inputs'!$A$105:$A$430=C102))*12} -> 0 | O102: =+N102/$C$4 -> #DIV/0! | S102: =+R102/C4 -> #DIV/0! | V102: =W102*V50 -> #DIV/0! | W102: 0.025
C103: Management Fee | E103: =+E102 -> 0 | F103: =+E103/$C$4 -> #DIV/0! | H103: =+H102 -> 0 | I103: =+H103/$C$4 -> #DIV/0! | K103: =+K102 -> 0 | L103: =+K103/$C$4 -> #DIV/0! | N103: =+N102 -> 0 | O103: =+N103/$C$4 -> #DIV/0! | R103: =+R102 -> 0 | S103: =+R103/$C$4 -> #DIV/0! | V103: =+V102 -> #DIV/0! | W103: =+V103/C4 -> #DIV/0!
C104: Management Fee (%) | E104: =+E103/E50 -> #DIV/0! | H104: =+H103/H50 -> #DIV/0! | K104: =+K103/K50 -> #DIV/0! | N104: =+N103/N50 -> #DIV/0! | R104: =+R103/R50 -> #DIV/0! | V104: =+V103/$V$50 -> #DIV/0!
C106: Taxes | E106: {=+SUMPRODUCT('T-12 Inputs'!$D$105:$O$430*('T-12 Inputs'!$A$105:$A$430=C106))} -> 0 | F106: =+E106/$C$4 -> #DIV/0! | H106: {=+SUMPRODUCT('T-12 Inputs'!$J$105:$O$430*('T-12 Inputs'!$A$105:$A$430=C106))*2} -> 0 | I106: =+H106/$C$4 -> #DIV/0! | K106: {=+SUMPRODUCT('T-12 Inputs'!$M$105:$O$430*('T-12 Inputs'!$A$105:$A$430=C106))*4} -> 0 | L106: =+K106/$C$4 -> #DIV/0! | N106: {=+SUMPRODUCT('T-12 Inputs'!$O$105:$O$430*('T-12 Inputs'!$A$105:$A$430=C106))*12} -> 0 | O106: =+N106/$C$4 -> #DIV/0! | S106: =+R106/C4 -> #DIV/0! | V106: =E106 -> 0 | W106: =+V106/$C$4 -> #DIV/0! | Y106: T-12
C107: Total Taxes | E107: =+E106 -> 0 | F107: =+E107/$C$4 -> #DIV/0! | H107: =+H106 -> 0 | I107: =+H107/$C$4 -> #DIV/0! | K107: =+K106 -> 0 | L107: =+K107/$C$4 -> #DIV/0! | N107: =+N106 -> 0 | O107: =+N107/$C$4 -> #DIV/0! | R107: =+R106 -> 0 | S107: =+R107/$C$4 -> #DIV/0! | V107: =+V106 -> 0 | W107: =+V107/$C$4 -> #DIV/0! | Y107: T-12
C109: Insurance | E109: {=+SUMPRODUCT('T-12 Inputs'!$D$105:$O$430*('T-12 Inputs'!$A$105:$A$430=C109))} -> 0 | F109: =+E109/$C$4 -> #DIV/0! | H109: {=+SUMPRODUCT('T-12 Inputs'!$J$105:$O$430*('T-12 Inputs'!$A$105:$A$430=C109))*2} -> 0 | I109: =+H109/$C$4 -> #DIV/0! | K109: {=+SUMPRODUCT('T-12 Inputs'!$M$105:$O$430*('T-12 Inputs'!$A$105:$A$430=C109))*4} -> 0 | L109: =+K109/$C$4 -> #DIV/0! | N109: {=+SUMPRODUCT('T-12 Inputs'!$O$105:$O$430*('T-12 Inputs'!$A$105:$A$430=C109))*12} -> 0 | O109: =+N109/$C$4 -> #DIV/0! | S109: =+R109/C4 -> #DIV/0! | V109: =E109 -> 0 | W109: =+V109/$C$4 -> #DIV/0! | Y109: T-12
C110: Total Insurance | E110: =+E109 -> 0 | F110: =+E110/$C$4 -> #DIV/0! | H110: =+H109 -> 0 | I110: =+H110/$C$4 -> #DIV/0! | K110: =+K109 -> 0 | L110: =+K110/$C$4 -> #DIV/0! | N110: =+N109 -> 0 | O110: =+N110/$C$4 -> #DIV/0! | R110: =+R109 -> 0 | S110: =+R110/$C$4 -> #DIV/0! | V110: =+V109 -> 0 | W110: =+V110/C4 -> #DIV/0! | Y110: T-12
C112: Total Operating Expenses | E112: =+SUM(E60,E71,E77,E88,E98,E103,E107,E110) -> 0 | F112: =+E112/$C$4 -> #DIV/0! | H112: =+SUM(H60,H71,H77,H88,H98,H103,H107,H110) -> 0 | I112: =+H112/$C$4 -> #DIV/0! | K112: =+SUM(K60,K71,K77,K88,K98,K103,K107,K110) -> 0 | L112: =+K112/$C$4 -> #DIV/0! | N112: =+SUM(N60,N71,N77,N88,N98,N103,N107,N110) -> 0 | O112: =+N112/$C$4 -> #DIV/0! | R112: =+SUM(R60,R71,R77,R88,R98,R103,R107,R110) -> 0 | S112: =+R112/$C$4 -> #DIV/0! | V112: =+SUM(V60,V71,V77,V88,V98,V103,V107,V110) -> #DIV/0! | W112: =+V112/$C$4 -> #DIV/0!
C113: OpEX % | E113: =+E112/E50 -> #DIV/0! | H113: =+H112/H50 -> #DIV/0! | K113: =+K112/K50 -> #DIV/0! | N113: =+N112/N50 -> #DIV/0! | R113: =+R112/R50 -> #DIV/0! | V113: =+V112/V50 -> #DIV/0!
C115: Net Operating Income | E115: =+E50-E112 -> 0 | F115: =+E115/$C$4 -> #DIV/0! | H115: =+H50-H112 -> 0 | I115: =+H115/$C$4 -> #DIV/0! | K115: =+K50-K112 -> 0 | L115: =+K115/$C$4 -> #DIV/0! | N115: =+N50-N112 -> 0 | O115: =+N115/$C$4 -> #DIV/0! | R115: =+R50-R112 -> 0 | S115: =+R115/$C$4 -> #DIV/0! | V115: =+V50-V112 -> #DIV/0! | W115: =+V115/$C$4 -> #DIV/0!

Sheet 5-Year Projection
D6: Rent Growth Assumptions | F6: 0.015 | G6: 0.02 | H6: 0.02 | I6: 0.015 | J6: 0.015
D7: Loss-to-Lease | F7: 0.07 | G7: 0.055 | H7: 0.035 | I7: 0.02 | J7: 0.02
D8: Vacancy Assumption | F8: 0.07 | G8: 0.07 | H8: 0.07 | I8: 0.07 | J8: 0.07
D9: Concessions | F9: 0.055 | G9: 0.03 | H9: 0.02 | I9: 0.02 | J9: 0.02
D10: Other Income Growth | F10: 0.0125 | G10: 0.015 | H10: 0.015 | I10: 0.015 | J10: 0.015
D11: Expense Growth | F11: 0.02 | G11: 0.02 | H11: 0.02 | I11: 0.02 | J11: 0.02
E14: Trailing - 12 | F14: Year 1 | G14: Year 2 | H14: Year 3 | I14: Year 4 | J14: Year 5
C16: Market Rent | E16: =+'Proforma (Annual)'!E10 -> 0 | F16: =+E16*(1+F6) -> 0 | G16: =+F16*(1+G6) -> 0 | H16: =+G16*(1+H6) -> 0 | I16: =+H16*(1+I6) -> 0 | J16: =+I16*(1+J6) -> 0
C17: Loss to Lease | E17: =+'Proforma (Annual)'!E11 -> 0 | F17: =+F16*-F7 -> 0 | G17: =+G16*-G7 -> 0 | H17: =+H16*-H7 -> 0 | I17: =+I16*-I7 -> 0 | J17: =+J16*-J7 -> 0
C18: Gross Potential Rent | E18: =+SUM(E16:E17) -> 0 | F18: =+SUM(F16:F17) -> 0 | G18: =+SUM(G16:G17) -> 0 | H18: =+SUM(H16:H17) -> 0 | I18: =+SUM(I16:I17) -> 0 | J18: =+SUM(J16:J17) -> 0
C20: Vacancy | E20: =+'Proforma (Annual)'!E14 -> 0 | F20: =+F18*-F8 -> 0 | G20: =+G18*-G8 -> 0 | H20: =+H18*-H8 -> 0 | I20: =+I18*-I8 -> 0 | J20: =+J18*-J8 -> 0
C21: Concessions | E21: =+'Proforma (Annual)'!E16 -> 0 | F21: =+F18*-F9 -> 0 | G21: =+G18*-G9 -> 0 | H21: =+H18*-H9 -> 0 | I21: =+I18*-I9 -> 0 | J21: =+J18*-J9 -> 0
C22: Bad Debt | E22: =+'Proforma (Annual)'!E17 -> 0 | F22: =0.005*-F18 -> 0 | G22: =0.005*-G18 -> 0 | H22: =0.005*-H18 -> 0 | I22: =0.005*-I18 -> 0 | J22: =0.005*-J18 -> 0 | L22: Held at Morgan standard of 0.50%.
C23: Model/Employee Discount | E23: =+'Proforma (Annual)'!E18 -> 0 | F23: =+E23*(1+F6) -> 0 | G23: =+F23*(1+G6) -> 0 | H23: =+G23*(1+H6) -> 0 | I23: =+H23*(1+I6) -> 0 | J23: =+I23*(1+J6) -> 0
C24: Economic Vacancy | E24: =+SUM(E20:E23) -> 0 | F24: =+SUM(F20:F23) -> 0 | G24: =+SUM(G20:G23) -> 0 | H24: =+SUM(H20:H23) -> 0 | I24: =+SUM(I20:I23) -> 0 | J24: =+SUM(J20:J23) -> 0
C26: Total Rental Income | E26: =+SUM(E18,E24) -> 0 | F26: =+SUM(F18,F24) -> 0 | G26: =+SUM(G18,G24) -> 0 | H26: =+SUM(H18,H24) -> 0 | I26: =+SUM(I18,I24) -> 0 | J26: =+SUM(J18,J24) -> 0
C28: =+'Proforma (Annual)'!C23 -> Administrative Fees | E28: =+'Proforma (Annual)'!E23 -> 0 | F28: =+E28*(1+$F$10) -> 0 | G28: =+F28*(1+$G$10) -> 0 | H28: =+G28*(1+$H$10) -> 0 | I28: =+H28*(1+$I$10) -> 0 | J28: =+I28*(1+$J$10) -> 0
C29: =+'Proforma (Annual)'!C24 -> Amenity Fee | E29: =+'Proforma (Annual)'!E24 -> 0 | F29: =+E29*(1+$F$10) -> 0 | G29: =+F29*(1+$G$10) -> 0 | H29: =+G29*(1+$H$10) -> 0 | I29: =+H29*(1+$I$10) -> 0 | J29: =+I29*(1+$J$10) -> 0
C30: =+'Proforma (Annual)'!C25 -> Application Fees | E30: =+'Proforma (Annual)'!E25 -> 0 | F30: =+E30*(1+$F$10) -> 0 | G30: =+F30*(1+$G$10) -> 0 | H30: =+G30*(1+$H$10) -> 0 | I30: =+H30*(1+$I$10) -> 0 | J30: =+I30*(1+$J$10) -> 0
C31: =+'Proforma (Annual)'!C26 -> Cable Income | E31: =+'Proforma (Annual)'!E26 -> 0 | F31: =+E31*(1+$F$10) -> 0 | G31: =+F31*(1+$G$10) -> 0 | H31: =+G31*(1+$H$10) -> 0 | I31: =+H31*(1+$I$10) -> 0 | J31: =+I31*(1+$J$10) -> 0
C32: =+'Proforma (Annual)'!C27 -> Cleaning/R&M | E32: =+'Proforma (Annual)'!E27 -> 0 | F32: =+E32*(1+$F$10) -> 0 | G32: =+F32*(1+$G$10) -> 0 | H32: =+G32*(1+$H$10) -> 0 | I32: =+H32*(1+$I$10) -> 0 | J32: =+I32*(1+$J$10) -> 0
C33: =+'Proforma (Annual)'!C28 -> Commercial Income | E33: =+'Proforma (Annual)'!E28 -> 0 | F33: =+E33*(1+$F$10) -> 0 | G33: =+F33*(1+$G$10) -> 0 | H33: =+G33*(1+$H$10) -> 0 | I33: =+H33*(1+$I$10) -> 0 | J33: =+I33*(1+$J$10) -> 0
C34: =+'Proforma (Annual)'!C29 -> Damages/Eviction Fees | E34: =+'Proforma (Annual)'!E29 -> 0 | F34: =+E34*(1+$F$10) -> 0 | G34: =+F34*(1+$G$10) -> 0 | H34: =+G34*(1+$H$10) -> 0 | I34: =+H34*(1+$I$10) -> 0 | J34: =+I34*(1+$J$10) -> 0
C35: =+'Proforma (Annual)'!C30 -> Guest Suite Income | E35: =+'Proforma (Annual)'!E30 -> 0 | F35: =+E35*(1+$F$10) -> 0 | G35: =+F35*(1+$G$10) -> 0 | H35: =+G35*(1+$H$10) -> 0 | I35: =+H35*(1+$I$10) -> 0 | J35: =+I35*(1+$J$10) -> 0
C36: =+'Proforma (Annual)'!C31 -> Late Charges | E36: =+'Proforma (Annual)'!E31 -> 0 | F36: =+E36*(1+$F$10) -> 0 | G36: =+F36*(1+$G$10) -> 0 | H36: =+G36*(1+$H$10) -> 0 | I36: =+H36*(1+$I$10) -> 0 | J36: =+I36*(1+$J$10) -> 0
C37: =+'Proforma (Annual)'!C32 -> Legal Reimbursement | E37: =+'Proforma (Annual)'!E32 -> 0 | F37: =+E37*(1+$F$10) -> 0 | G37: =+F37*(1+$G$10) -> 0 | H37: =+G37*(1+$H$10) -> 0 | I37: =+H37*(1+$I$10) -> 0 | J37: =+I37*(1+$J$10) -> 0
C38: =+'Proforma (Annual)'!C33 -> Liability Insurance | E38: =+'Proforma (Annual)'!E33 -> 0 | F38: =+E38*(1+$F$10) -> 0 | G38: =+F38*(1+$G$10) -> 0 | H38: =+G38*(1+$H$10) -> 0 | I38: =+H38*(1+$I$10) -> 0 | J38: =+I38*(1+$J$10) -> 0
C39: =+'Proforma (Annual)'!C34 -> MTM Fees | E39: =+'Proforma (Annual)'!E34 -> 0 | F39: =+E39*(1+$F$10) -> 0 | G39: =+F39*(1+$G$10) -> 0 | H39: =+G39*(1+$H$10) -> 0 | I39: =+H39*(1+$I$10) -> 0 | J39: =+I39*(1+$J$10) -> 0
... C52: =+'Proforma (Annual)'!C47 -> Valet Income | E52: =+'Proforma (Annual)'!E47 -> 0 | F52: =+E52*(1+$F$10) -> 0 | G52: =+F52*(1+$G$10) -> 0 | H52: =+G52*(1+$H$10) -> 0 | I52: =+H52*(1+$I$10) -> 0 | J52: =+I52*(1+$J$10) -> 0
C54: Total Other Income | E54: =+SUM(E28:E53) -> 0 | F54: =+SUM(F28:F53) -> 0 | G54: =+SUM(G28:G53) -> 0 | H54: =+SUM(H28:H53) -> 0 | I54: =+SUM(I28:I53) -> 0 | J54: =+SUM(J28:J53) -> 0
C56: Effective Gross Income | E56: =+SUM(E26,E54) -> 0 | F56: =+SUM(F26,F54) -> 0 | G56: =+SUM(G26,G54) -> 0 | H56: =+SUM(H26,H54) -> 0 | I56: =+SUM(I26,I54) -> 0 | J56: =+SUM(J26,J54) -> 0
C58: Expenses
C60: =+'Proforma (Annual)'!C54 -> Salary - Property Management | E60: =+'Proforma (Annual)'!E54 -> 0 | F60: =+SUM('Payroll Schedule'!G21) -> 226040 | G60: =+F60*(1+$F$11) -> 230560.8 | H60: =+G60*(1+$G$11) -> 235172.02 | I60: =+H60*(1+$H$11) -> 239875.46 | J60: =+I60*(1+$I$11) -> 244672.97
C61: =+'Proforma (Annual)'!C55 -> Salary - Maintenance | E61: =+'Proforma (Annual)'!E55 -> 0 | F61: =+'Payroll Schedule'!G34 -> 198640 | G61: =+F61*(1+$F$11) -> 202612.8 | H61: =+G61*(1+$G$11) -> 206665.06 | I61: =+H61*(1+$H$11) -> 210798.36 | J61: =+I61*(1+$I$11) -> 215014.32
C62: =+'Proforma (Annual)'!C56 -> Payroll - Burden | E62: =+'Proforma (Annual)'!E56 -> 0 | F62: =+SUM('Payroll Schedule'!H21,'Payroll Schedule'!H34,'Payroll Schedule'!D51) -> 114482.5 | G62: =+F62*(1+$F$11) -> 116772.15 | H62: =+G62*(1+$G$11) -> 119107.59 | I62: =+H62*(1+$H$11) -> 121489.74 | J62: =+I62*(1+$I$11) -> 123919.54
C63: =+'Proforma (Annual)'!C57 -> Payroll - Miscellaneous | E63: =+'Proforma (Annual)'!E57 -> 0 | G63: =+F63*(1+$F$11) -> 0 | H63: =+G63*(1+$G$11) -> 0 | I63: =+H63*(1+$H$11) -> 0 | J63: =+I63*(1+$I$11) -> 0
C64: =+'Proforma (Annual)'!C58 -> Leasing Bonuses | E64: =+'Proforma (Annual)'!E58 -> 0 | F64: =+'Payroll Schedule'!F40 -> 0 | G64: =+F64*(1+$F$11) -> 0 | H64: =+G64*(1+$G$11) -> 0 | I64: =+H64*(1+$H$11) -> 0 | J64: =+I64*(1+$I$11) -> 0
C65: =+'Proforma (Annual)'!C59 -> Bonuses | E65: =+'Proforma (Annual)'!E59 -> 0 | F65: =+SUM('Payroll Schedule'!C51) -> 33250 | G65: =+F65*(1+$F$11) -> 33915 | H65: =+G65*(1+$G$11) -> 34593.3 | I65: =+H65*(1+$H$11) -> 35285.166 | J65: =+I65*(1+$I$11) -> 35990.869
C66: Total Payroll | E66: =+'Proforma (Annual)'!E60 -> 0 | F66: =+SUM(F60:F65) -> 572412.5 | G66: =+F66*(1+$F$11) -> 583860.75 | H66: =+G66*(1+$G$11) -> 595537.96 | I66: =+H66*(1+$H$11) -> 607448.72 | J66: =+I66*(1+$I$11) -> 619597.7
C68: =+'Proforma (Annual)'!C62 -> G&A | E68: =+'Proforma (Annual)'!E62 -> 0 | F68: =+'Proforma (Annual)'!V62 -> 0 | G68: =+F68*(1+$G$11) -> 0 | H68: =+G68*(1+$H$11) -> 0 | I68: =+H68*(1+$I$11) -> 0 | J68: =+I68*(1+$J$11) -> 0
C69: =+'Proforma (Annual)'!C63 -> Supplies | E69: =+'Proforma (Annual)'!E63 -> 0 | F69: =+'Proforma (Annual)'!V63 -> 0 | G69: =+F69*(1+$G$11) -> 0 | H69: =+G69*(1+$H$11) -> 0 | I69: =+H69*(1+$I$11) -> 0 | J69: =+I69*(1+$J$11) -> 0
C70: =+'Proforma (Annual)'!C64 -> Memberships | E70: =+'Proforma (Annual)'!E64 -> 0 | F70: =+'Proforma (Annual)'!V64 -> 0 | G70: =+F70*(1+$G$11) -> 0 | H70: =+G70*(1+$H$11) -> 0 | I70: =+H70*(1+$I$11) -> 0 | J70: =+I70*(1+$J$11) -> 0
C71: =+'Proforma (Annual)'!C65 -> Telephone | E71: =+'Proforma (Annual)'!E65 -> 0 | F71: =+'Proforma (Annual)'!V65 -> 0 | G71: =+F71*(1+$G$11) -> 0 | H71: =+G71*(1+$H$11) -> 0 | I71: =+H71*(1+$I$11) -> 0 | J71: =+I71*(1+$J$11) -> 0
C72: =+'Proforma (Annual)'!C66 -> Legal | E72: =+'Proforma (Annual)'!E66 -> 0 | F72: =+'Proforma (Annual)'!V66 -> 0 | G72: =+F72*(1+$G$11) -> 0 | H72: =+G72*(1+$H$11) -> 0 | I72: =+H72*(1+$I$11) -> 0 | J72: =+I72*(1+$J$11) -> 0
C73: =+'Proforma (Annual)'!C67 -> Bank Charges | E73: =+'Proforma (Annual)'!E67 -> 0 | F73: =+'Proforma (Annual)'!V67 -> 0 | G73: =+F73*(1+$G$11) -> 0 | H73: =+G73*(1+$H$11) -> 0 | I73: =+H73*(1+$I$11) -> 0 | J73: =+I73*(1+$J$11) -> 0
C74: =+'Proforma (Annual)'!C68 -> Eviction Charges | E74: =+'Proforma (Annual)'!E68 -> 0 | F74: =+'Proforma (Annual)'!V68 -> 0 | G74: =+F74*(1+$G$11) -> 0 | H74: =+G74*(1+$H$11) -> 0 | I74: =+H74*(1+$I$11) -> 0 | J74: =+I74*(1+$J$11) -> 0
C75: =+'Proforma (Annual)'!C69 -> Internet - GA | E75: =+'Proforma (Annual)'!E69 -> 0 | F75: =+'Proforma (Annual)'!V69 -> 0 | G75: =+F75*(1+$G$11) -> 0 | H75: =+G75*(1+$H$11) -> 0 | I75: =+H75*(1+$I$11) -> 0 | J75: =+I75*(1+$J$11) -> 0
C76: =+'Proforma (Annual)'!C70 -> G&A - Miscellaneous | E76: =+'Proforma (Annual)'!E70 -> 0 | F76: =+'Proforma (Annual)'!V70 -> 0 | G76: =+F76*(1+$G$11) -> 0 | H76: =+G76*(1+$H$11) -> 0 | I76: =+H76*(1+$I$11) -> 0 | J76: =+I76*(1+$J$11) -> 0
C77: Total G&A | E77: =+'Proforma (Annual)'!E71 -> 0 | F77: =+SUM(F68:F76) -> 0 | G77: =+SUM(G68:G76) -> 0 | H77: =+SUM(H68:H76) -> 0 | I77: =+SUM(I68:I76) -> 0 | J77: =+SUM(J68:J76) -> 0
C79: =+'Proforma (Annual)'!C73 -> Locator Fees | E79: =+'Proforma (Annual)'!E73 -> 0 | F79: =SUMIF('Marketing Stack'!$B$6:$B$41,C79,'Marketing Stack'!$Q$6:$Q$41) -> 6000 | G79: =+F79*(1+$G$11) -> 6120 | H79: =+G79*(1+$H$11) -> 6242.4 | I79: =+H79*(1+$I$11) -> 6367.248 | J79: =+I79*(1+$J$11) -> 6494.593
C80: =+'Proforma (Annual)'!C74 -> Marketing | E80: =+'Proforma (Annual)'!E74 -> 0 | F80: =SUMIF('Marketing Stack'!$B$6:$B$41,C80,'Marketing Stack'!$Q$6:$Q$41) -> 70632 | G80: =+F80*(1+$G$11) -> 72044.64 | H80: =+G80*(1+$H$11) -> 73485.533 | I80: =+H80*(1+$I$11) -> 74955.243 | J80: =+I80*(1+$J$11) -> 76454.348
C81: =+'Proforma (Annual)'!C75 -> Referral Fees | E81: =+'Proforma (Annual)'!E75 -> 0 | F81: =SUMIF('Marketing Stack'!$B$6:$B$41,C81,'Marketing Stack'!$Q$6:$Q$41) -> 0 | G81: =+F81*(1+$G$11) -> 0 | H81: =+G81*(1+$H$11) -> 0 | I81: =+H81*(1+$I$11) -> 0 | J81: =+I81*(1+$J$11) -> 0
C82: =+'Proforma (Annual)'!C76 -> Resident Retention | E82: =+'Proforma (Annual)'!E76 -> 0 | F82: =SUMIF('Marketing Stack'!$B$6:$B$41,C82,'Marketing Stack'!$Q$6:$Q$41) -> 15000 | G82: =+F82*(1+$G$11) -> 15300 | H82: =+G82*(1+$H$11) -> 15606 | I82: =+H82*(1+$I$11) -> 15918.12 | J82: =+I82*(1+$J$11) -> 16236.482
C83: Total Marketing | E83: =+SUM(E79:E82) -> 0 | F83: =+SUM(F79:F82) -> 91632 | G83: =+SUM(G79:G82) -> 93464.64 | H83: =+SUM(H79:H82) -> 95333.933 | I83: =+SUM(I79:I82) -> 97240.611 | J83: =+SUM(J79:J82) -> 99185.424
C85: =+'Proforma (Annual)'!C79 -> R&M | E85: =+'Proforma (Annual)'!E79 -> 0 | F85: =+E85*(1+$F$11) -> 0 | G85: =+'Proforma (Annual)'!V79 -> 0 | H85: =+G85*(1+$H$11) -> 0 | I85: =+H85*(1+$I$11) -> 0 | J85: =+I85*(1+$J$11) -> 0
C86: =+'Proforma (Annual)'!C80 -> Make-Ready/Redec | E86: =+'Proforma (Annual)'!E80 -> 0 | F86: =+E86*(1+$F$11) -> 0 | G86: =+'Proforma (Annual)'!V80 -> 0 | H86: =+G86*(1+$H$11) -> 0 | I86: =+H86*(1+$I$11) -> 0 | J86: =+I86*(1+$J$11) -> 0
C87: =+'Proforma (Annual)'!C81 -> Landscaping | E87: =+'Proforma (Annual)'!E81 -> 0 | F87: =+E87*(1+$F$11) -> 0 | G87: =+'Proforma (Annual)'!V81 -> 0 | H87: =+G87*(1+$H$11) -> 0 | I87: =+H87*(1+$I$11) -> 0 | J87: =+I87*(1+$J$11) -> 0
C88: =+'Proforma (Annual)'!C82 -> R&M - Trash | E88: =+'Proforma (Annual)'!E82 -> 0 | F88: =+E88*(1+$F$11) -> 0 | G88: =+'Proforma (Annual)'!V82 -> 0 | H88: =+G88*(1+$H$11) -> 0 | I88: =+H88*(1+$I$11) -> 0 | J88: =+I88*(1+$J$11) -> 0
C89: =+'Proforma (Annual)'!C83 -> Pest | E89: =+'Proforma (Annual)'!E83 -> 0 | F89: =+E89*(1+$F$11) -> 0 | G89: =+'Proforma (Annual)'!V83 -> 0 | H89: =+G89*(1+$H$11) -> 0 | I89: =+H89*(1+$I$11) -> 0 | J89: =+I89*(1+$J$11) -> 0
C90: =+'Proforma (Annual)'!C84 -> Contract Services | E90: =+'Proforma (Annual)'!E84 -> 0 | F90: =+E90*(1+$F$11) -> 0 | G90: =+'Proforma (Annual)'!V84 -> 0 | H90: =+G90*(1+$H$11) -> 0 | I90: =+H90*(1+$I$11) -> 0 | J90: =+I90*(1+$J$11) -> 0
C91: =IFERROR('Proforma (Annual)'!C85,0) -> Tenant Billback Expense | E91: =+'Proforma (Annual)'!E85 -> 0 | F91: =+E91*(1+$F$11) -> 0 | G91: =+'Proforma (Annual)'!V85 -> 0 | H91: =+G91*(1+$H$11) -> 0 | I91: =+H91*(1+$I$11) -> 0 | J91: =+I91*(1+$J$11) -> 0
C92: =+'Proforma (Annual)'!C86 -> Contract Services - Concierge | E92: =+'Proforma (Annual)'!E86 -> 0 | F92: =+E92*(1+$F$11) -> 0 | G92: =+'Proforma (Annual)'!V86 -> 0 | H92: =+G92*(1+$H$11) -> 0 | I92: =+H92*(1+$I$11) -> 0 | J92: =+I92*(1+$J$11) -> 0
C93: =+'Proforma (Annual)'!C87 -> R&M - Trash Reimbursement | E93: =+'Proforma (Annual)'!E87 -> 0 | F93: =+E93*(1+$F$11) -> 0 | G93: =+'Proforma (Annual)'!V87 -> 0 | H93: =+G93*(1+$H$11) -> 0 | I93: =+H93*(1+$I$11) -> 0 | J93: =+I93*(1+$J$11) -> 0
C94: Total R&M | E94: =+SUM(E85:E93) -> 0 | F94: =+SUM(F85:F93) -> 0 | G94: =+SUM(G85:G93) -> 0 | H94: =+SUM(H85:H93) -> 0 | I94: =+SUM(I85:I93) -> 0 | J94: =+SUM(J85:J93) -> 0
C96: =+'Proforma (Annual)'!C90 -> Electricity | E96: =+'Proforma (Annual)'!E90 -> 0 | F96: =+'Proforma (Annual)'!V90 -> 0 | G96: =+F96*(1+$G$11) -> 0 | H96: =+G96*(1+$H$11) -> 0 | I96: =+H96*(1+$I$11) -> 0 | J96: =+I96*(1+$J$11) -> 0
C97: =+'Proforma (Annual)'!C91 -> Water | E97: =+'Proforma (Annual)'!E91 -> 0 | F97: =+'Proforma (Annual)'!V91 -> 0 | G97: =+F97*(1+$G$11) -> 0 | H97: =+G97*(1+$H$11) -> 0 | I97: =+H97*(1+$I$11) -> 0 | J97: =+I97*(1+$J$11) -> 0
C98: =+'Proforma (Annual)'!C92 -> Trash | E98: =+'Proforma (Annual)'!E92 -> 0 | F98: =+'Proforma (Annual)'!V92 -> 0 | G98: =+F98*(1+$G$11) -> 0 | H98: =+G98*(1+$H$11) -> 0 | I98: =+H98*(1+$I$11) -> 0 | J98: =+I98*(1+$J$11) -> 0
C99: =+'Proforma (Annual)'!C93 -> Gas | E99: =+'Proforma (Annual)'!E93 -> 0 | F99: =+'Proforma (Annual)'!V93 -> 0 | G99: =+F99*(1+$G$11) -> 0 | H99: =+G99*(1+$H$11) -> 0 | I99: =+H99*(1+$I$11) -> 0 | J99: =+I99*(1+$J$11) -> 0
C100: =+'Proforma (Annual)'!C94 -> Utility Fees | E100: =+'Proforma (Annual)'!E94 -> 0 | F100: =+'Proforma (Annual)'!V94 -> 0 | G100: =+F100*(1+$G$11) -> 0 | H100: =+G100*(1+$H$11) -> 0 | I100: =+H100*(1+$I$11) -> 0 | J100: =+I100*(1+$J$11) -> 0
C101: =+'Proforma (Annual)'!C95 -> Internet - Utilities | E101: =+'Proforma (Annual)'!E95 -> 0 | F101: =+'Proforma (Annual)'!V95 -> 0 | G101: =+F101*(1+$G$11) -> 0 | H101: =+G101*(1+$H$11) -> 0 | I101: =+H101*(1+$I$11) -> 0 | J101: =+I101*(1+$J$11) -> 0
C102: =+'Proforma (Annual)'!C96 -> Trash - Reimbursement | E102: =+'Proforma (Annual)'!E96 -> 0 | F102: =+'Proforma (Annual)'!V96 -> 0 | G102: =+F102*(1+$G$11) -> 0 | H102: =+G102*(1+$H$11) -> 0 | I102: =+H102*(1+$I$11) -> 0 | J102: =+I102*(1+$J$11) -> 0
C103: =+'Proforma (Annual)'!C97 -> Utility Reimbursement | E103: =+'Proforma (Annual)'!E97 -> 0 | F103: =+'Proforma (Annual)'!V97 -> 0 | G103: =+F103*(1+$G$11) -> 0 | H103: =+G103*(1+$H$11) -> 0 | I103: =+H103*(1+$I$11) -> 0 | J103: =+I103*(1+$J$11) -> 0
C104: Total Utilities | E104: =SUM(E96:E103) -> 0 | F104: =SUM(F96:F103) -> 0 | G104: =SUM(G96:G103) -> 0 | H104: =SUM(H96:H103) -> 0 | I104: =SUM(I96:I103) -> 0 | J104: =SUM(J96:J103) -> 0
C106: Total Controllable Expenses | E106: =+SUM(E104,E94,E83,E77,E66) -> 0 | F106: =+SUM(F104,F94,F83,F77,F66) -> 664044.5 | G106: =+SUM(G104,G94,G83,G77,G66) -> 677325.39 | H106: =+SUM(H104,H94,H83,H77,H66) -> 690871.9 | I106: =+SUM(I104,I94,I83,I77,I66) -> 704689.34 | J106: =+SUM(J104,J94,J83,J77,J66) -> 718783.12
C108: Management Fee | E108: =+'Proforma (Annual)'!E102 -> 0 | F108: =+F110*F56 -> 0 | G108: =+G110*G56 -> 0 | H108: =+H110*H56 -> 0 | I108: =+I110*I56 -> 0 | J108: =+J110*J56 -> 0
C109: Management Fee | E109: =+'Proforma (Annual)'!E103 -> 0 | F109: =+F108 -> 0 | G109: =+G108 -> 0 | H109: =+H108 -> 0 | I109: =+I108 -> 0 | J109: =+J108 -> 0
C110: Management Fee (%) | E110: =+'Proforma (Annual)'!$W$102 -> 0.025 | F110: =+'Proforma (Annual)'!$W$102 -> 0.025 | G110: =+'Proforma (Annual)'!$W$102 -> 0.025 | H110: =+'Proforma (Annual)'!$W$102 -> 0.025 | I110: =+'Proforma (Annual)'!$W$102 -> 0.025 | J110: =+'Proforma (Annual)'!$W$102 -> 0.025
C112: Taxes | E112: =+'Proforma (Annual)'!E106 -> 0 | F112: =+'Proforma (Annual)'!V106 -> 0 | G112: =+F112*(1+G11) -> 0 | H112: =+G112*(1+H11) -> 0 | I112: =+H112*(1+I11) -> 0 | J112: =+I112*(1+J11) -> 0
C113: Total Taxes | E113: =+E112 -> 0 | F113: =+F112 -> 0 | G113: =+G112 -> 0 | H113: =+H112 -> 0 | I113: =+I112 -> 0 | J113: =+J112 -> 0
C115: Insurance | E115: =+'Proforma (Annual)'!E109 -> 0 | F115: =+'Proforma (Annual)'!V109 -> 0 | G115: =+F115*(1+G11) -> 0 | H115: =+G115*(1+H11) -> 0 | I115: =+H115*(1+I11) -> 0 | J115: =+I115*(1+J11) -> 0
C116: Total Insurance | E116: =+'Proforma (Annual)'!E110 -> 0 | F116: =+F115 -> 0 | G116: =+G115 -> 0 | H116: =+H115 -> 0 | I116: =+I115 -> 0 | J116: =+J115 -> 0
C118: Total Operating Expenses | E118: =+'Proforma (Annual)'!E112 -> 0 | F118: =+SUM(F106,F109,F113,F116) -> 664044.5 | G118: =+SUM(G106,G109,G113,G116) -> 677325.39 | H118: =+SUM(H106,H109,H113,H116) -> 690871.9 | I118: =+SUM(I106,I109,I113,I116) -> 704689.34 | J118: =+SUM(J106,J109,J113,J116) -> 718783.12
C119: OpEX % | E119: =+'Proforma (Annual)'!E113 -> #DIV/0! | F119: =+F118/F56 -> #DIV/0! | G119: =+G118/G56 -> #DIV/0! | H119: =+H118/H56 -> #DIV/0! | I119: =+I118/I56 -> #DIV/0! | J119: =+J118/J56 -> #DIV/0!
C121: Net Operating Income | E121: =+'Proforma (Annual)'!E115 -> 0 | F121: =+F56-F118 -> -664044.5 | G121: =+G56-G118 -> -677325.39 | H121: =+H56-H118 -> -690871.9 | I121: =+I56-I118 -> -704689.34 | J121: =+J56-J118 -> -718783.12

Sheet Operating Budget - Monthly
B2: Lease-Up Budget (Monthly)
B4: Property Name | C4: Target Occupancy
B5: ='Lease-Up Proforma'!C2 -> 0 | C5: =1-'Proforma (Annual)'!U14 -> 1 | E5: Available Units | K5: 0 | L5: =SUM(K5:K6) -> 0 | M5: =SUM(L5:L6) -> 0 | N5: =SUM(M5:M6) -> 0 | O5: =SUM(N5:N6) -> 0 | P5: =SUM(O5:O6) -> 0 | Q5: =SUM(P5:P6) -> 0 | R5: =SUM(Q5:Q6) -> 0 | S5: =SUM(R5:R6) -> 0 | ... AH5: =SUM(AG5:AG6) -> 0
B6: Units | C6: Min. Units | E6: Units Delivered | K6: =+'Absorption Schedule'!I38 -> 0 | L6: =+'Absorption Schedule'!J38 -> 0 | M6: =+'Absorption Schedule'!K38 -> 0 | N6: =+'Absorption Schedule'!L38 -> 0 | O6: =+'Absorption Schedule'!M38 -> 0 | P6: =+'Absorption Schedule'!N38 -> 0 | Q6: =+'Absorption Schedule'!O38 -> 0 | R6: =+'Absorption Schedule'!P38 -> 0 | ... AH6: =+'Absorption Schedule'!AF38 -> 0
B7: ='Rent Schedule'!E31 -> 0 | C7: =B7*C5 -> 0 | E7: Absorption | K7: =+'Absorption Schedule'!H35 -> 0 | L7: =+'Absorption Schedule'!I35 -> 20 | M7: =+'Absorption Schedule'!J35 -> 22 | N7: =+'Absorption Schedule'!K35 -> 22 | O7: =+'Absorption Schedule'!L35 -> 21 | P7: =+'Absorption Schedule'!M35 -> 17 | Q7: =+'Absorption Schedule'!N35 -> 17 | R7: =+'Absorption Schedule'!O35 -> 18 | ... AH7: =+'Absorption Schedule'!AE35 -> 7
B8: Pre-Lease End | C8: Monthly Absorption
B9: 46053 | C9: ='Absorption Schedule'!#REF! -> #REF! | E9: Vacant Units | K9: =$B$7-K10 -> #DIV/0! | L9: =+$B$7-'Absorption Schedule'!I37 -> #DIV/0! | M9: =+$B$7-'Absorption Schedule'!J37 -> #DIV/0! | N9: =+$B$7-'Absorption Schedule'!K37 -> #DIV/0! | O9: =+$B$7-'Absorption Schedule'!L37 -> #DIV/0! | P9: =+$B$7-'Absorption Schedule'!M37 -> #DIV/0! | Q9: =+$B$7-'Absorption Schedule'!N37 -> #DIV/0! | R9: =+$B$7-'Absorption Schedule'!O37 -> #DIV/0! | S9: =+$B$7-'Absorption Schedule'!P37 -> #DIV/0! | ... AH9: =+$B$7-'Absorption Schedule'!AE37 -> #DIV/0!
E10: Occupied Units | J10: 0 | K10: =+'Absorption Schedule'!H37 -> #DIV/0! | L10: =+'Absorption Schedule'!I37 -> #DIV/0! | M10: =+'Absorption Schedule'!J37 -> #DIV/0! | N10: =+'Absorption Schedule'!K37 -> #DIV/0! | O10: =+'Absorption Schedule'!L37 -> #DIV/0! | P10: =+'Absorption Schedule'!M37 -> #DIV/0! | Q10: =+'Absorption Schedule'!N37 -> #DIV/0! | R10: =+'Absorption Schedule'!O37 -> #DIV/0! | ... AH10: =+'Absorption Schedule'!AE37 -> #DIV/0!
E11: Occupancy | J11: 0 | K11: =K10/$B$7 -> #DIV/0! | L11: =L10/$B$7 -> #DIV/0! | M11: =M10/$B$7 -> #DIV/0! | N11: =N10/$B$7 -> #DIV/0! | O11: =O10/$B$7 -> #DIV/0! | P11: =P10/$B$7 -> #DIV/0! | Q11: =Q10/$B$7 -> #DIV/0! | R11: =R10/$B$7 -> #DIV/0! | ... AH11: =AH10/$B$7 -> #DIV/0!
H13: -2 | I13: -1 | J13: 0 | K13: 1 | L13: 2 | M13: 3 | N13: 4 | O13: 5 | P13: 6 | Q13: 7 | R13: 8 | S13: 9 | T13: 10 | U13: 11 | V13: 12 | W13: 13 | X13: 14 | Y13: 15 | Z13: 16 | AA13: 17 | AB13: 18 | AC13: 19 | AD13: 20 | AE13: 21 | AF13: 22 | AG13: 23 | AH13: 24
E14: Month | H14: =EOMONTH('Absorption Schedule'!F25,0) -> 46142 | I14: =+EOMONTH(H14,1) -> 46173 | J14: =+EOMONTH(I14,1) -> 46203 | K14: =+EOMONTH(J14,1) -> 46234 | L14: =+EOMONTH(K14,1) -> 46265 | M14: =+EOMONTH(L14,1) -> 46295 | N14: =+EOMONTH(M14,1) -> 46326 | O14: =+EOMONTH(N14,1) -> 46356 | P14: =+EOMONTH(O14,1) -> 46387 | ... AH14: =+EOMONTH(AG14,1) -> 46934
H15: Pre-Leasing | K15: Lease Up
E16: Market Rent | F16: 0.02 | K16: ='Rent Schedule'!$P$31/12 -> 0 | L16: ='Rent Schedule'!$P$31/12 -> 0 | M16: ='Rent Schedule'!$P$31/12 -> 0 | N16: ='Rent Schedule'!$P$31/12 -> 0 | O16: ='Rent Schedule'!$P$31/12 -> 0 | P16: ='Rent Schedule'!$P$31/12 -> 0 | Q16: ='Rent Schedule'!$P$31/12 -> 0 | R16: ='Rent Schedule'!$P$31/12 -> 0 | ... V16: ='Rent Schedule'!$P$31/12 -> 0 | W16: =('Rent Schedule'!$P$31*(1+$F$16))/12 -> 0 | X16: =('Rent Schedule'!$P$31*(1+$F$16))/12 -> 0 | Y16: =('Rent Schedule'!$P$31*(1+$F$16))/12 -> 0 | Z16: =('Rent Schedule'!$P$31*(1+$F$16))/12 -> 0 | AA16: =('Rent Schedule'!$P$31*(1+$F$16))/12 -> 0 | AB16: =('Rent Schedule'!$P$31*(1+$F$16))/12 -> 0 | AC16: =('Rent Schedule'!$P$31*(1+$F$16))/12 -> 0 | AD16: =('Rent Schedule'!$P$31*(1+$F$16))/12 -> 0 | ... AH16: =('Rent Schedule'!$P$31*(1+$F$16))/12 -> 0
E17: Loss to Lease | F17: 0.001 | K17: 0 | L17: 0 | M17: 0 | N17: 0 | O17: 0 | P17: 0 | Q17: 0 | R17: 0 | S17: 0 | T17: 0 | U17: 0 | V17: 0 | W17: =-$F$17*W16 -> 0 | X17: =-$F$17*X16 -> 0 | Y17: =-$F$17*Y16 -> 0 | Z17: =-$F$17*Z16 -> 0 | AA17: =-$F$17*AA16 -> 0 | AB17: =-$F$17*AB16 -> 0 | AC17: =-$F$17*AC16 -> 0 | AD17: =-$F$17*AD16 -> 0 | ... AH17: =-$F$17*AH16 -> 0
E18: Gross Potential Rent | H18: 0 | I18: 0 | J18: 0 | K18: =SUM(K16:K17) -> 0 | L18: =SUM(L16:L17) -> 0 | M18: =SUM(M16:M17) -> 0 | N18: =SUM(N16:N17) -> 0 | O18: =SUM(O16:O17) -> 0 | P18: =SUM(P16:P17) -> 0 | Q18: =SUM(Q16:Q17) -> 0 | R18: =SUM(R16:R17) -> 0 | ... AH18: =SUM(AH16:AH17) -> 0
E20: Vacancy | H20: 0 | I20: 0 | J20: 0 | K20: =-K21*K18 -> #DIV/0! | L20: =-L21*L18 -> #DIV/0! | M20: =-M21*M18 -> #DIV/0! | N20: =-N21*N18 -> #DIV/0! | O20: =-O21*O18 -> #DIV/0! | P20: =-P21*P18 -> #DIV/0! | Q20: =-Q21*Q18 -> #DIV/0! | R20: =-R21*R18 -> #DIV/0! | ... AH20: =-AH21*AH18 -> #DIV/0!
E21: Vacancy (%) | H21: 1 | I21: 1 | J21: 1 | K21: =1-K11 -> #DIV/0! | L21: =1-L11 -> #DIV/0! | M21: =1-M11 -> #DIV/0! | N21: =1-N11 -> #DIV/0! | O21: =1-O11 -> #DIV/0! | P21: =1-P11 -> #DIV/0! | Q21: =1-Q11 -> #DIV/0! | R21: =1-R11 -> #DIV/0! | ... AH21: =1-AH11 -> #DIV/0!
E22: Concessions (Monthly/Unit) | F22: ='Rent Schedule'!L31 -> #DIV/0! | K22: ='Absorption Schedule'!#REF! -> #REF! | L22: ='Absorption Schedule'!#REF! -> #REF! | M22: ='Absorption Schedule'!#REF! -> #REF! | N22: ='Absorption Schedule'!#REF! -> #REF! | O22: ='Absorption Schedule'!#REF! -> #REF! | P22: ='Absorption Schedule'!#REF! -> #REF! | Q22: ='Absorption Schedule'!#REF! -> #REF! | R22: ='Absorption Schedule'!#REF! -> #REF! | ... AH22: ='Absorption Schedule'!#REF! -> #REF!
E23: Bad Debt | F23: 0.001 | K23: =-$F$23*K18 -> 0 | L23: =-$F$23*L18 -> 0 | M23: =-$F$23*M18 -> 0 | N23: =-$F$23*N18 -> 0 | O23: =-$F$23*O18 -> 0 | P23: =-$F$23*P18 -> 0 | Q23: =-$F$23*Q18 -> 0 | R23: =-$F$23*R18 -> 0 | ... AH23: =-$F$23*AH18 -> 0
E24: Model/Employee Discount | F24: 0.0066 | K24: =-$F$24*K18 -> 0 | L24: =-$F$24*L18 -> 0 | M24: =-$F$24*M18 -> 0 | N24: =-$F$24*N18 -> 0 | O24: =-$F$24*O18 -> 0 | P24: =-$F$24*P18 -> 0 | Q24: =-$F$24*Q18 -> 0 | R24: =-$F$24*R18 -> 0 | ... AH24: =-$F$24*AH18 -> 0
E25: Economic Vacancy | H25: 0 | I25: 0 | J25: 0 | K25: =SUM(K20,K22:K24) -> #DIV/0! | L25: =SUM(L20,L22:L24) -> #DIV/0! | M25: =SUM(M20,M22:M24) -> #DIV/0! | N25: =SUM(N20,N22:N24) -> #DIV/0! | O25: =SUM(O20,O22:O24) -> #DIV/0! | P25: =SUM(P20,P22:P24) -> #DIV/0! | Q25: =SUM(Q20,Q22:Q24) -> #DIV/0! | R25: =SUM(R20,R22:R24) -> #DIV/0! | ... AH25: =SUM(AH20,AH22:AH24) -> #DIV/0!
E27: Total Rental Income | H27: 0 | I27: 0 | J27: 0 | K27: =SUM(K25,K18) -> #DIV/0! | L27: =SUM(L25,L18) -> #DIV/0! | M27: =SUM(M25,M18) -> #DIV/0! | N27: =SUM(N25,N18) -> #DIV/0! | O27: =SUM(O25,O18) -> #DIV/0! | P27: =SUM(P25,P18) -> #DIV/0! | Q27: =SUM(Q25,Q18) -> #DIV/0! | R27: =SUM(R25,R18) -> #DIV/0! | ... AH27: =SUM(AH25,AH18) -> #DIV/0!
E29: Administrative Fees | F29: =IFERROR(INDEX('Other Income Assumptions'!$D:$D, MATCH(E29, 'Other Income Assumptions'!$C:$C, 0)), "") -> 0 | K29: =SUMIF('Other Income Assumptions'!$C:$C,$E$29,'Other Income Assumptions'!D:D) -> 0 | L29: =SUMIF('Other Income Assumptions'!$C:$C,$E$29,'Other Income Assumptions'!E:E) -> 0 | M29: =SUMIF('Other Income Assumptions'!$C:$C,$E$29,'Other Income Assumptions'!F:F) -> 0 | N29: =SUMIF('Other Income Assumptions'!$C:$C,$E$29,'Other Income Assumptions'!G:G) -> 0 | O29: =SUMIF('Other Income Assumptions'!$C:$C,$E$29,'Other Income Assumptions'!H:H) -> 0 | P29: =SUMIF('Other Income Assumptions'!$C:$C,$E$29,'Other Income Assumptions'!I:I) -> 0 | Q29: =SUMIF('Other Income Assumptions'!$C:$C,$E$29,'Other Income Assumptions'!J:J) -> 0 | R29: =SUMIF('Other Income Assumptions'!$C:$C,$E$29,'Other Income Assumptions'!K:K) -> 0 | S29: =SUMIF('Other Income Assumptions'!$C:$C,$E$29,'Other Income Assumptions'!L:L) -> 0 | T29: =SUMIF('Other Income Assumptions'!$C:$C,$E$29,'Other Income Assumptions'!M:M) -> 0 | U29: =SUMIF('Other Income Assumptions'!$C:$C,$E$29,'Other Income Assumptions'!N:N) -> 0 | V29: =SUMIF('Other Income Assumptions'!$C:$C,$E$29,'Other Income Assumptions'!O:O) -> 0
E30: Amenity Fee | F30: =IFERROR(INDEX('Other Income Assumptions'!$D:$D, MATCH(E30, 'Other Income Assumptions'!$C:$C, 0)), "") | K30: =SUMIF('Other Income Assumptions'!$C:$C,$E$30,'Other Income Assumptions'!D:D) -> 0 | L30: =SUMIF('Other Income Assumptions'!$C:$C,$E$30,'Other Income Assumptions'!E:E) -> 0 | M30: =SUMIF('Other Income Assumptions'!$C:$C,$E$30,'Other Income Assumptions'!F:F) -> 0 | N30: =SUMIF('Other Income Assumptions'!$C:$C,$E$30,'Other Income Assumptions'!G:G) -> 0 | O30: =SUMIF('Other Income Assumptions'!$C:$C,$E$30,'Other Income Assumptions'!H:H) -> 0 | P30: =SUMIF('Other Income Assumptions'!$C:$C,$E$30,'Other Income Assumptions'!I:I) -> 0 | Q30: =SUMIF('Other Income Assumptions'!$C:$C,$E$30,'Other Income Assumptions'!J:J) -> 0 | R30: =SUMIF('Other Income Assumptions'!$C:$C,$E$30,'Other Income Assumptions'!K:K) -> 0 | S30: =SUMIF('Other Income Assumptions'!$C:$C,$E$30,'Other Income Assumptions'!L:L) -> 0 | T30: =SUMIF('Other Income Assumptions'!$C:$C,$E$30,'Other Income Assumptions'!M:M) -> 0 | U30: =SUMIF('Other Income Assumptions'!$C:$C,$E$30,'Other Income Assumptions'!N:N) -> 0 | V30: =SUMIF('Other Income Assumptions'!$C:$C,$E$30,'Other Income Assumptions'!O:O) -> 0
E31: Application Fees | F31: =IFERROR(INDEX('Other Income Assumptions'!$D:$D, MATCH(E31, 'Other Income Assumptions'!$C:$C, 0)), "") -> 0 | K31: =SUMIF('Other Income Assumptions'!$C:$C,$E$31,'Other Income Assumptions'!D:D) -> 0 | L31: =SUMIF('Other Income Assumptions'!$C:$C,$E$31,'Other Income Assumptions'!E:E) -> 0 | M31: =SUMIF('Other Income Assumptions'!$C:$C,$E$31,'Other Income Assumptions'!F:F) -> 0 | N31: =SUMIF('Other Income Assumptions'!$C:$C,$E$31,'Other Income Assumptions'!G:G) -> 0 | O31: =SUMIF('Other Income Assumptions'!$C:$C,$E$31,'Other Income Assumptions'!H:H) -> 0 | P31: =SUMIF('Other Income Assumptions'!$C:$C,$E$31,'Other Income Assumptions'!I:I) -> 0 | Q31: =SUMIF('Other Income Assumptions'!$C:$C,$E$31,'Other Income Assumptions'!J:J) -> 0 | R31: =SUMIF('Other Income Assumptions'!$C:$C,$E$31,'Other Income Assumptions'!K:K) -> 0 | S31: =SUMIF('Other Income Assumptions'!$C:$C,$E$31,'Other Income Assumptions'!L:L) -> 0 | T31: =SUMIF('Other Income Assumptions'!$C:$C,$E$31,'Other Income Assumptions'!M:M) -> 0 | U31: =SUMIF('Other Income Assumptions'!$C:$C,$E$31,'Other Income Assumptions'!N:N) -> 0 | V31: =SUMIF('Other Income Assumptions'!$C:$C,$E$31,'Other Income Assumptions'!O:O) -> 0
E32: Cable Income | F32: =IFERROR(INDEX('Other Income Assumptions'!$D:$D, MATCH(E32, 'Other Income Assumptions'!$C:$C, 0)), "") | K32: =SUMIF('Other Income Assumptions'!$C:$C,$E$32,'Other Income Assumptions'!D:D) -> 0 | L32: =SUMIF('Other Income Assumptions'!$C:$C,$E$32,'Other Income Assumptions'!E:E) -> 0 | M32: =SUMIF('Other Income Assumptions'!$C:$C,$E$32,'Other Income Assumptions'!F:F) -> 0 | N32: =SUMIF('Other Income Assumptions'!$C:$C,$E$32,'Other Income Assumptions'!G:G) -> 0 | O32: =SUMIF('Other Income Assumptions'!$C:$C,$E$32,'Other Income Assumptions'!H:H) -> 0 | P32: =SUMIF('Other Income Assumptions'!$C:$C,$E$32,'Other Income Assumptions'!I:I) -> 0 | Q32: =SUMIF('Other Income Assumptions'!$C:$C,$E$32,'Other Income Assumptions'!J:J) -> 0 | R32: =SUMIF('Other Income Assumptions'!$C:$C,$E$32,'Other Income Assumptions'!K:K) -> 0 | S32: =SUMIF('Other Income Assumptions'!$C:$C,$E$32,'Other Income Assumptions'!L:L) -> 0 | T32: =SUMIF('Other Income Assumptions'!$C:$C,$E$32,'Other Income Assumptions'!M:M) -> 0 | U32: =SUMIF('Other Income Assumptions'!$C:$C,$E$32,'Other Income Assumptions'!N:N) -> 0 | V32: =SUMIF('Other Income Assumptions'!$C:$C,$E$32,'Other Income Assumptions'!O:O) -> 0
E33: Cleaning/R&M | F33: =IFERROR(INDEX('Other Income Assumptions'!$D:$D, MATCH(E33, 'Other Income Assumptions'!$C:$C, 0)), "") | K33: =SUMIF('Other Income Assumptions'!$C:$C,$E$33,'Other Income Assumptions'!D:D) -> 0 | L33: =SUMIF('Other Income Assumptions'!$C:$C,$E$33,'Other Income Assumptions'!E:E) -> 0 | M33: =SUMIF('Other Income Assumptions'!$C:$C,$E$33,'Other Income Assumptions'!F:F) -> 0 | N33: =SUMIF('Other Income Assumptions'!$C:$C,$E$33,'Other Income Assumptions'!G:G) -> 0 | O33: =SUMIF('Other Income Assumptions'!$C:$C,$E$33,'Other Income Assumptions'!H:H) -> 0 | P33: =SUMIF('Other Income Assumptions'!$C:$C,$E$33,'Other Income Assumptions'!I:I) -> 0 | Q33: =SUMIF('Other Income Assumptions'!$C:$C,$E$33,'Other Income Assumptions'!J:J) -> 0 | R33: =SUMIF('Other Income Assumptions'!$C:$C,$E$33,'Other Income Assumptions'!K:K) -> 0 | S33: =SUMIF('Other Income Assumptions'!$C:$C,$E$33,'Other Income Assumptions'!L:L) -> 0 | T33: =SUMIF('Other Income Assumptions'!$C:$C,$E$33,'Other Income Assumptions'!M:M) -> 0 | U33: =SUMIF('Other Income Assumptions'!$C:$C,$E$33,'Other Income Assumptions'!N:N) -> 0 | V33: =SUMIF('Other Income Assumptions'!$C:$C,$E$33,'Other Income Assumptions'!O:O) -> 0
E34: Commercial Income | F34: =IFERROR(INDEX('Other Income Assumptions'!$D:$D, MATCH(E34, 'Other Income Assumptions'!$C:$C, 0)), "") | K34: =SUMIF('Other Income Assumptions'!$C:$C,$E$34,'Other Income Assumptions'!D:D) -> 0 | L34: =SUMIF('Other Income Assumptions'!$C:$C,$E$34,'Other Income Assumptions'!E:E) -> 0 | M34: =SUMIF('Other Income Assumptions'!$C:$C,$E$34,'Other Income Assumptions'!F:F) -> 0 | N34: =SUMIF('Other Income Assumptions'!$C:$C,$E$34,'Other Income Assumptions'!G:G) -> 0 | O34: =SUMIF('Other Income Assumptions'!$C:$C,$E$34,'Other Income Assumptions'!H:H) -> 0 | P34: =SUMIF('Other Income Assumptions'!$C:$C,$E$34,'Other Income Assumptions'!I:I) -> 0 | Q34: =SUMIF('Other Income Assumptions'!$C:$C,$E$34,'Other Income Assumptions'!J:J) -> 0 | R34: =SUMIF('Other Income Assumptions'!$C:$C,$E$34,'Other Income Assumptions'!K:K) -> 0 | S34: =SUMIF('Other Income Assumptions'!$C:$C,$E$34,'Other Income Assumptions'!L:L) -> 0 | T34: =SUMIF('Other Income Assumptions'!$C:$C,$E$34,'Other Income Assumptions'!M:M) -> 0 | U34: =SUMIF('Other Income Assumptions'!$C:$C,$E$34,'Other Income Assumptions'!N:N) -> 0 | V34: =SUMIF('Other Income Assumptions'!$C:$C,$E$34,'Other Income Assumptions'!O:O) -> 0
E35: Damages/Eviction Fees | F35: =IFERROR(INDEX('Other Income Assumptions'!$D:$D, MATCH(E35, 'Other Income Assumptions'!$C:$C, 0)), "") | K35: =SUMIF('Other Income Assumptions'!$C:$C,$E$35,'Other Income Assumptions'!D:D) -> 0 | L35: =SUMIF('Other Income Assumptions'!$C:$C,$E$35,'Other Income Assumptions'!E:E) -> 0 | M35: =SUMIF('Other Income Assumptions'!$C:$C,$E$35,'Other Income Assumptions'!F:F) -> 0 | N35: =SUMIF('Other Income Assumptions'!$C:$C,$E$35,'Other Income Assumptions'!G:G) -> 0 | O35: =SUMIF('Other Income Assumptions'!$C:$C,$E$35,'Other Income Assumptions'!H:H) -> 0 | P35: =SUMIF('Other Income Assumptions'!$C:$C,$E$35,'Other Income Assumptions'!I:I) -> 0 | Q35: =SUMIF('Other Income Assumptions'!$C:$C,$E$35,'Other Income Assumptions'!J:J) -> 0 | R35: =SUMIF('Other Income Assumptions'!$C:$C,$E$35,'Other Income Assumptions'!K:K) -> 0 | S35: =SUMIF('Other Income Assumptions'!$C:$C,$E$35,'Other Income Assumptions'!L:L) -> 0 | T35: =SUMIF('Other Income Assumptions'!$C:$C,$E$35,'Other Income Assumptions'!M:M) -> 0 | U35: =SUMIF('Other Income Assumptions'!$C:$C,$E$35,'Other Income Assumptions'!N:N) -> 0 | V35: =SUMIF('Other Income Assumptions'!$C:$C,$E$35,'Other Income Assumptions'!O:O) -> 0
E36: Guest Suite Income | F36: =IFERROR(INDEX('Other Income Assumptions'!$D:$D, MATCH(E36, 'Other Income Assumptions'!$C:$C, 0)), "") | K36: =SUMIF('Other Income Assumptions'!$C:$C,$E$36,'Other Income Assumptions'!D:D) -> 0 | L36: =SUMIF('Other Income Assumptions'!$C:$C,$E$36,'Other Income Assumptions'!E:E) -> 0 | M36: =SUMIF('Other Income Assumptions'!$C:$C,$E$36,'Other Income Assumptions'!F:F) -> 0 | N36: =SUMIF('Other Income Assumptions'!$C:$C,$E$36,'Other Income Assumptions'!G:G) -> 0 | O36: =SUMIF('Other Income Assumptions'!$C:$C,$E$36,'Other Income Assumptions'!H:H) -> 0 | P36: =SUMIF('Other Income Assumptions'!$C:$C,$E$36,'Other Income Assumptions'!I:I) -> 0 | Q36: =SUMIF('Other Income Assumptions'!$C:$C,$E$36,'Other Income Assumptions'!J:J) -> 0 | R36: =SUMIF('Other Income Assumptions'!$C:$C,$E$36,'Other Income Assumptions'!K:K) -> 0 | S36: =SUMIF('Other Income Assumptions'!$C:$C,$E$36,'Other Income Assumptions'!L:L) -> 0 | T36: =SUMIF('Other Income Assumptions'!$C:$C,$E$36,'Other Income Assumptions'!M:M) -> 0 | U36: =SUMIF('Other Income Assumptions'!$C:$C,$E$36,'Other Income Assumptions'!N:N) -> 0 | V36: =SUMIF('Other Income Assumptions'!$C:$C,$E$36,'Other Income Assumptions'!O:O) -> 0
E37: Late Charges | F37: =IFERROR(INDEX('Other Income Assumptions'!$D:$D, MATCH(E37, 'Other Income Assumptions'!$C:$C, 0)), "") | K37: =SUMIF('Other Income Assumptions'!$C:$C,$E$37,'Other Income Assumptions'!D:D) -> 0 | L37: =SUMIF('Other Income Assumptions'!$C:$C,$E$37,'Other Income Assumptions'!E:E) -> 0 | M37: =SUMIF('Other Income Assumptions'!$C:$C,$E$37,'Other Income Assumptions'!F:F) -> 0 | N37: =SUMIF('Other Income Assumptions'!$C:$C,$E$37,'Other Income Assumptions'!G:G) -> 0 | O37: =SUMIF('Other Income Assumptions'!$C:$C,$E$37,'Other Income Assumptions'!H:H) -> 0 | P37: =SUMIF('Other Income Assumptions'!$C:$C,$E$37,'Other Income Assumptions'!I:I) -> 0 | Q37: =SUMIF('Other Income Assumptions'!$C:$C,$E$37,'Other Income Assumptions'!J:J) -> 0 | R37: =SUMIF('Other Income Assumptions'!$C:$C,$E$37,'Other Income Assumptions'!K:K) -> 0 | S37: =SUMIF('Other Income Assumptions'!$C:$C,$E$37,'Other Income Assumptions'!L:L) -> 0 | T37: =SUMIF('Other Income Assumptions'!$C:$C,$E$37,'Other Income Assumptions'!M:M) -> 0 | U37: =SUMIF('Other Income Assumptions'!$C:$C,$E$37,'Other Income Assumptions'!N:N) -> 0 | V37: =SUMIF('Other Income Assumptions'!$C:$C,$E$37,'Other Income Assumptions'!O:O) -> 0
E38: Legal Reimbursement | F38: =IFERROR(INDEX('Other Income Assumptions'!$D:$D, MATCH(E38, 'Other Income Assumptions'!$C:$C, 0)), "") | K38: =SUMIF('Other Income Assumptions'!$C:$C,$E$38,'Other Income Assumptions'!D:D) -> 0 | L38: =SUMIF('Other Income Assumptions'!$C:$C,$E$38,'Other Income Assumptions'!E:E) -> 0 | M38: =SUMIF('Other Income Assumptions'!$C:$C,$E$38,'Other Income Assumptions'!F:F) -> 0 | N38: =SUMIF('Other Income Assumptions'!$C:$C,$E$38,'Other Income Assumptions'!G:G) -> 0 | O38: =SUMIF('Other Income Assumptions'!$C:$C,$E$38,'Other Income Assumptions'!H:H) -> 0 | P38: =SUMIF('Other Income Assumptions'!$C:$C,$E$38,'Other Income Assumptions'!I:I) -> 0 | Q38: =SUMIF('Other Income Assumptions'!$C:$C,$E$38,'Other Income Assumptions'!J:J) -> 0 | R38: =SUMIF('Other Income Assumptions'!$C:$C,$E$38,'Other Income Assumptions'!K:K) -> 0 | S38: =SUMIF('Other Income Assumptions'!$C:$C,$E$38,'Other Income Assumptions'!L:L) -> 0 | T38: =SUMIF('Other Income Assumptions'!$C:$C,$E$38,'Other Income Assumptions'!M:M) -> 0 | U38: =SUMIF('Other Income Assumptions'!$C:$C,$E$38,'Other Income Assumptions'!N:N) -> 0 | V38: =SUMIF('Other Income Assumptions'!$C:$C,$E$38,'Other Income Assumptions'!O:O) -> 0
E39: Liability Insurance | F39: =IFERROR(INDEX('Other Income Assumptions'!$D:$D, MATCH(E39, 'Other Income Assumptions'!$C:$C, 0)), "") | K39: =SUMIF('Other Income Assumptions'!$C:$C,$E$39,'Other Income Assumptions'!D:D) -> 0 | L39: =SUMIF('Other Income Assumptions'!$C:$C,$E$39,'Other Income Assumptions'!E:E) -> 0 | M39: =SUMIF('Other Income Assumptions'!$C:$C,$E$39,'Other Income Assumptions'!F:F) -> 0 | N39: =SUMIF('Other Income Assumptions'!$C:$C,$E$39,'Other Income Assumptions'!G:G) -> 0 | O39: =SUMIF('Other Income Assumptions'!$C:$C,$E$39,'Other Income Assumptions'!H:H) -> 0 | P39: =SUMIF('Other Income Assumptions'!$C:$C,$E$39,'Other Income Assumptions'!I:I) -> 0 | Q39: =SUMIF('Other Income Assumptions'!$C:$C,$E$39,'Other Income Assumptions'!J:J) -> 0 | R39: =SUMIF('Other Income Assumptions'!$C:$C,$E$39,'Other Income Assumptions'!K:K) -> 0 | S39: =SUMIF('Other Income Assumptions'!$C:$C,$E$39,'Other Income Assumptions'!L:L) -> 0 | T39: =SUMIF('Other Income Assumptions'!$C:$C,$E$39,'Other Income Assumptions'!M:M) -> 0 | U39: =SUMIF('Other Income Assumptions'!$C:$C,$E$39,'Other Income Assumptions'!N:N) -> 0 | V39: =SUMIF('Other Income Assumptions'!$C:$C,$E$39,'Other Income Assumptions'!O:O) -> 0
E40: MTM Fees | F40: =IFERROR(INDEX('Other Income Assumptions'!$D:$D, MATCH(E40, 'Other Income Assumptions'!$C:$C, 0)), "") | K40: =SUMIF('Other Income Assumptions'!$C:$C,$E$40,'Other Income Assumptions'!D:D) -> 0 | L40: =SUMIF('Other Income Assumptions'!$C:$C,$E$40,'Other Income Assumptions'!E:E) -> 0 | M40: =SUMIF('Other Income Assumptions'!$C:$C,$E$40,'Other Income Assumptions'!F:F) -> 0 | N40: =SUMIF('Other Income Assumptions'!$C:$C,$E$40,'Other Income Assumptions'!G:G) -> 0 | O40: =SUMIF('Other Income Assumptions'!$C:$C,$E$40,'Other Income Assumptions'!H:H) -> 0 | P40: =SUMIF('Other Income Assumptions'!$C:$C,$E$40,'Other Income Assumptions'!I:I) -> 0 | Q40: =SUMIF('Other Income Assumptions'!$C:$C,$E$40,'Other Income Assumptions'!J:J) -> 0 | R40: =SUMIF('Other Income Assumptions'!$C:$C,$E$40,'Other Income Assumptions'!K:K) -> 0 | S40: =SUMIF('Other Income Assumptions'!$C:$C,$E$40,'Other Income Assumptions'!L:L) -> 0 | T40: =SUMIF('Other Income Assumptions'!$C:$C,$E$40,'Other Income Assumptions'!M:M) -> 0 | U40: =SUMIF('Other Income Assumptions'!$C:$C,$E$40,'Other Income Assumptions'!N:N) -> 0 | V40: =SUMIF('Other Income Assumptions'!$C:$C,$E$40,'Other Income Assumptions'!O:O) -> 0
E41: NSF Fees | F41: =IFERROR(INDEX('Other Income Assumptions'!$D:$D, MATCH(E41, 'Other Income Assumptions'!$C:$C, 0)), "") -> 0 | K41: =SUMIF('Other Income Assumptions'!$C:$C,$E$41,'Other Income Assumptions'!D:D) -> 0 | L41: =SUMIF('Other Income Assumptions'!$C:$C,$E$41,'Other Income Assumptions'!E:E) -> 0 | M41: =SUMIF('Other Income Assumptions'!$C:$C,$E$41,'Other Income Assumptions'!F:F) -> 0 | N41: =SUMIF('Other Income Assumptions'!$C:$C,$E$41,'Other Income Assumptions'!G:G) -> 0 | O41: =SUMIF('Other Income Assumptions'!$C:$C,$E$41,'Other Income Assumptions'!H:H) -> 0 | P41: =SUMIF('Other Income Assumptions'!$C:$C,$E$41,'Other Income Assumptions'!I:I) -> 0 | Q41: =SUMIF('Other Income Assumptions'!$C:$C,$E$41,'Other Income Assumptions'!J:J) -> 0 | R41: =SUMIF('Other Income Assumptions'!$C:$C,$E$41,'Other Income Assumptions'!K:K) -> 0 | S41: =SUMIF('Other Income Assumptions'!$C:$C,$E$41,'Other Income Assumptions'!L:L) -> 0 | T41: =SUMIF('Other Income Assumptions'!$C:$C,$E$41,'Other Income Assumptions'!M:M) -> 0 | U41: =SUMIF('Other Income Assumptions'!$C:$C,$E$41,'Other Income Assumptions'!N:N) -> 0 | V41: =SUMIF('Other Income Assumptions'!$C:$C,$E$41,'Other Income Assumptions'!O:O) -> 0
E42: Other Income | F42: =IFERROR(INDEX('Other Income Assumptions'!$D:$D, MATCH(E42, 'Other Income Assumptions'!$C:$C, 0)), "") | K42: =SUMIF('Other Income Assumptions'!$C:$C,$E$42,'Other Income Assumptions'!D:D) -> 0 | L42: =SUMIF('Other Income Assumptions'!$C:$C,$E$42,'Other Income Assumptions'!E:E) -> 0 | M42: =SUMIF('Other Income Assumptions'!$C:$C,$E$42,'Other Income Assumptions'!F:F) -> 0 | N42: =SUMIF('Other Income Assumptions'!$C:$C,$E$42,'Other Income Assumptions'!G:G) -> 0 | O42: =SUMIF('Other Income Assumptions'!$C:$C,$E$42,'Other Income Assumptions'!H:H) -> 0 | P42: =SUMIF('Other Income Assumptions'!$C:$C,$E$42,'Other Income Assumptions'!I:I) -> 0 | Q42: =SUMIF('Other Income Assumptions'!$C:$C,$E$42,'Other Income Assumptions'!J:J) -> 0 | R42: =SUMIF('Other Income Assumptions'!$C:$C,$E$42,'Other Income Assumptions'!K:K) -> 0 | S42: =SUMIF('Other Income Assumptions'!$C:$C,$E$42,'Other Income Assumptions'!L:L) -> 0 | T42: =SUMIF('Other Income Assumptions'!$C:$C,$E$42,'Other Income Assumptions'!M:M) -> 0 | U42: =SUMIF('Other Income Assumptions'!$C:$C,$E$42,'Other Income Assumptions'!N:N) -> 0 | V42: =SUMIF('Other Income Assumptions'!$C:$C,$E$42,'Other Income Assumptions'!O:O) -> 0
E43: Package Fees | F43: =IFERROR(INDEX('Other Income Assumptions'!$D:$D, MATCH(E43, 'Other Income Assumptions'!$C:$C, 0)), "") | K43: =SUMIF('Other Income Assumptions'!$C:$C,$E$43,'Other Income Assumptions'!D:D) -> 0 | L43: =SUMIF('Other Income Assumptions'!$C:$C,$E$43,'Other Income Assumptions'!E:E) -> 0 | M43: =SUMIF('Other Income Assumptions'!$C:$C,$E$43,'Other Income Assumptions'!F:F) -> 0 | N43: =SUMIF('Other Income Assumptions'!$C:$C,$E$43,'Other Income Assumptions'!G:G) -> 0 | O43: =SUMIF('Other Income Assumptions'!$C:$C,$E$43,'Other Income Assumptions'!H:H) -> 0 | P43: =SUMIF('Other Income Assumptions'!$C:$C,$E$43,'Other Income Assumptions'!I:I) -> 0 | Q43: =SUMIF('Other Income Assumptions'!$C:$C,$E$43,'Other Income Assumptions'!J:J) -> 0 | R43: =SUMIF('Other Income Assumptions'!$C:$C,$E$43,'Other Income Assumptions'!K:K) -> 0 | S43: =SUMIF('Other Income Assumptions'!$C:$C,$E$43,'Other Income Assumptions'!L:L) -> 0 | T43: =SUMIF('Other Income Assumptions'!$C:$C,$E$43,'Other Income Assumptions'!M:M) -> 0 | U43: =SUMIF('Other Income Assumptions'!$C:$C,$E$43,'Other Income Assumptions'!N:N) -> 0 | V43: =SUMIF('Other Income Assumptions'!$C:$C,$E$43,'Other Income Assumptions'!O:O) -> 0
E44: Parking | F44: =IFERROR(INDEX('Other Income Assumptions'!$D:$D, MATCH(E44, 'Other Income Assumptions'!$C:$C, 0)), "") | K44: =SUMIF('Other Income Assumptions'!$C:$C,$E$44,'Other Income Assumptions'!D:D) -> 0 | L44: =SUMIF('Other Income Assumptions'!$C:$C,$E$44,'Other Income Assumptions'!E:E) -> 0 | M44: =SUMIF('Other Income Assumptions'!$C:$C,$E$44,'Other Income Assumptions'!F:F) -> 0 | N44: =SUMIF('Other Income Assumptions'!$C:$C,$E$44,'Other Income Assumptions'!G:G) -> 0 | O44: =SUMIF('Other Income Assumptions'!$C:$C,$E$44,'Other Income Assumptions'!H:H) -> 0 | P44: =SUMIF('Other Income Assumptions'!$C:$C,$E$44,'Other Income Assumptions'!I:I) -> 0 | Q44: =SUMIF('Other Income Assumptions'!$C:$C,$E$44,'Other Income Assumptions'!J:J) -> 0 | R44: =SUMIF('Other Income Assumptions'!$C:$C,$E$44,'Other Income Assumptions'!K:K) -> 0 | S44: =SUMIF('Other Income Assumptions'!$C:$C,$E$44,'Other Income Assumptions'!L:L) -> 0 | T44: =SUMIF('Other Income Assumptions'!$C:$C,$E$44,'Other Income Assumptions'!M:M) -> 0 | U44: =SUMIF('Other Income Assumptions'!$C:$C,$E$44,'Other Income Assumptions'!N:N) -> 0 | V44: =SUMIF('Other Income Assumptions'!$C:$C,$E$44,'Other Income Assumptions'!O:O) -> 0
E45: Pest | F45: =IFERROR(INDEX('Other Income Assumptions'!$D:$D, MATCH(E45, 'Other Income Assumptions'!$C:$C, 0)), "") | K45: =SUMIF('Other Income Assumptions'!$C:$C,$E$45,'Other Income Assumptions'!D:D) -> 0 | L45: =SUMIF('Other Income Assumptions'!$C:$C,$E$45,'Other Income Assumptions'!E:E) -> 0 | M45: =SUMIF('Other Income Assumptions'!$C:$C,$E$45,'Other Income Assumptions'!F:F) -> 0 | N45: =SUMIF('Other Income Assumptions'!$C:$C,$E$45,'Other Income Assumptions'!G:G) -> 0 | O45: =SUMIF('Other Income Assumptions'!$C:$C,$E$45,'Other Income Assumptions'!H:H) -> 0 | P45: =SUMIF('Other Income Assumptions'!$C:$C,$E$45,'Other Income Assumptions'!I:I) -> 0 | Q45: =SUMIF('Other Income Assumptions'!$C:$C,$E$45,'Other Income Assumptions'!J:J) -> 0 | R45: =SUMIF('Other Income Assumptions'!$C:$C,$E$45,'Other Income Assumptions'!K:K) -> 0 | S45: =SUMIF('Other Income Assumptions'!$C:$C,$E$45,'Other Income Assumptions'!L:L) -> 0 | T45: =SUMIF('Other Income Assumptions'!$C:$C,$E$45,'Other Income Assumptions'!M:M) -> 0 | U45: =SUMIF('Other Income Assumptions'!$C:$C,$E$45,'Other Income Assumptions'!N:N) -> 0 | V45: =SUMIF('Other Income Assumptions'!$C:$C,$E$45,'Other Income Assumptions'!O:O) -> 0
E46: Pet | F46: =IFERROR(INDEX('Other Income Assumptions'!$D:$D, MATCH(E46, 'Other Income Assumptions'!$C:$C, 0)), "") | K46: =SUMIF('Other Income Assumptions'!$C:$C,$E$46,'Other Income Assumptions'!D:D) -> 0 | L46: =SUMIF('Other Income Assumptions'!$C:$C,$E$46,'Other Income Assumptions'!E:E) -> 0 | M46: =SUMIF('Other Income Assumptions'!$C:$C,$E$46,'Other Income Assumptions'!F:F) -> 0 | N46: =SUMIF('Other Income Assumptions'!$C:$C,$E$46,'Other Income Assumptions'!G:G) -> 0 | O46: =SUMIF('Other Income Assumptions'!$C:$C,$E$46,'Other Income Assumptions'!H:H) -> 0 | P46: =SUMIF('Other Income Assumptions'!$C:$C,$E$46,'Other Income Assumptions'!I:I) -> 0 | Q46: =SUMIF('Other Income Assumptions'!$C:$C,$E$46,'Other Income Assumptions'!J:J) -> 0 | R46: =SUMIF('Other Income Assumptions'!$C:$C,$E$46,'Other Income Assumptions'!K:K) -> 0 | S46: =SUMIF('Other Income Assumptions'!$C:$C,$E$46,'Other Income Assumptions'!L:L) -> 0 | T46: =SUMIF('Other Income Assumptions'!$C:$C,$E$46,'Other Income Assumptions'!M:M) -> 0 | U46: =SUMIF('Other Income Assumptions'!$C:$C,$E$46,'Other Income Assumptions'!N:N) -> 0 | V46: =SUMIF('Other Income Assumptions'!$C:$C,$E$46,'Other Income Assumptions'!O:O) -> 0
E47: Resident Service Fee | F47: =IFERROR(INDEX('Other Income Assumptions'!$D:$D, MATCH(E47, 'Other Income Assumptions'!$C:$C, 0)), "") | K47: =SUMIF('Other Income Assumptions'!$C:$C,$E$47,'Other Income Assumptions'!D:D) -> 0 | L47: =SUMIF('Other Income Assumptions'!$C:$C,$E$47,'Other Income Assumptions'!E:E) -> 0 | M47: =SUMIF('Other Income Assumptions'!$C:$C,$E$47,'Other Income Assumptions'!F:F) -> 0 | N47: =SUMIF('Other Income Assumptions'!$C:$C,$E$47,'Other Income Assumptions'!G:G) -> 0 | O47: =SUMIF('Other Income Assumptions'!$C:$C,$E$47,'Other Income Assumptions'!H:H) -> 0 | P47: =SUMIF('Other Income Assumptions'!$C:$C,$E$47,'Other Income Assumptions'!I:I) -> 0 | Q47: =SUMIF('Other Income Assumptions'!$C:$C,$E$47,'Other Income Assumptions'!J:J) -> 0 | R47: =SUMIF('Other Income Assumptions'!$C:$C,$E$47,'Other Income Assumptions'!K:K) -> 0 | S47: =SUMIF('Other Income Assumptions'!$C:$C,$E$47,'Other Income Assumptions'!L:L) -> 0 | T47: =SUMIF('Other Income Assumptions'!$C:$C,$E$47,'Other Income Assumptions'!M:M) -> 0 | U47: =SUMIF('Other Income Assumptions'!$C:$C,$E$47,'Other Income Assumptions'!N:N) -> 0 | V47: =SUMIF('Other Income Assumptions'!$C:$C,$E$47,'Other Income Assumptions'!O:O) -> 0
E48: Storage | F48: =IFERROR(INDEX('Other Income Assumptions'!$D:$D, MATCH(E48, 'Other Income Assumptions'!$C:$C, 0)), "") | K48: =SUMIF('Other Income Assumptions'!$C:$C,$E$48,'Other Income Assumptions'!D:D) -> 0 | L48: =SUMIF('Other Income Assumptions'!$C:$C,$E$48,'Other Income Assumptions'!E:E) -> 0 | M48: =SUMIF('Other Income Assumptions'!$C:$C,$E$48,'Other Income Assumptions'!F:F) -> 0 | N48: =SUMIF('Other Income Assumptions'!$C:$C,$E$48,'Other Income Assumptions'!G:G) -> 0 | O48: =SUMIF('Other Income Assumptions'!$C:$C,$E$48,'Other Income Assumptions'!H:H) -> 0 | P48: =SUMIF('Other Income Assumptions'!$C:$C,$E$48,'Other Income Assumptions'!I:I) -> 0 | Q48: =SUMIF('Other Income Assumptions'!$C:$C,$E$48,'Other Income Assumptions'!J:J) -> 0 | R48: =SUMIF('Other Income Assumptions'!$C:$C,$E$48,'Other Income Assumptions'!K:K) -> 0 | S48: =SUMIF('Other Income Assumptions'!$C:$C,$E$48,'Other Income Assumptions'!L:L) -> 0 | T48: =SUMIF('Other Income Assumptions'!$C:$C,$E$48,'Other Income Assumptions'!M:M) -> 0 | U48: =SUMIF('Other Income Assumptions'!$C:$C,$E$48,'Other Income Assumptions'!N:N) -> 0 | V48: =SUMIF('Other Income Assumptions'!$C:$C,$E$48,'Other Income Assumptions'!O:O) -> 0
E49: Tech Package | F49: =IFERROR(INDEX('Other Income Assumptions'!$D:$D, MATCH(E49, 'Other Income Assumptions'!$C:$C, 0)), "") | K49: =SUMIF('Other Income Assumptions'!$C:$C,$E$49,'Other Income Assumptions'!D:D) -> 0 | L49: =SUMIF('Other Income Assumptions'!$C:$C,$E$49,'Other Income Assumptions'!E:E) -> 0 | M49: =SUMIF('Other Income Assumptions'!$C:$C,$E$49,'Other Income Assumptions'!F:F) -> 0 | N49: =SUMIF('Other Income Assumptions'!$C:$C,$E$49,'Other Income Assumptions'!G:G) -> 0 | O49: =SUMIF('Other Income Assumptions'!$C:$C,$E$49,'Other Income Assumptions'!H:H) -> 0 | P49: =SUMIF('Other Income Assumptions'!$C:$C,$E$49,'Other Income Assumptions'!I:I) -> 0 | Q49: =SUMIF('Other Income Assumptions'!$C:$C,$E$49,'Other Income Assumptions'!J:J) -> 0 | R49: =SUMIF('Other Income Assumptions'!$C:$C,$E$49,'Other Income Assumptions'!K:K) -> 0 | S49: =SUMIF('Other Income Assumptions'!$C:$C,$E$49,'Other Income Assumptions'!L:L) -> 0 | T49: =SUMIF('Other Income Assumptions'!$C:$C,$E$49,'Other Income Assumptions'!M:M) -> 0 | U49: =SUMIF('Other Income Assumptions'!$C:$C,$E$49,'Other Income Assumptions'!N:N) -> 0 | V49: =SUMIF('Other Income Assumptions'!$C:$C,$E$49,'Other Income Assumptions'!O:O) -> 0
E50: Termination/Transfer Fees | F50: =IFERROR(INDEX('Other Income Assumptions'!$D:$D, MATCH(E50, 'Other Income Assumptions'!$C:$C, 0)), "") | K50: =SUMIF('Other Income Assumptions'!$C:$C,$E$50,'Other Income Assumptions'!D:D) -> 0 | L50: =SUMIF('Other Income Assumptions'!$C:$C,$E$50,'Other Income Assumptions'!E:E) -> 0 | M50: =SUMIF('Other Income Assumptions'!$C:$C,$E$50,'Other Income Assumptions'!F:F) -> 0 | N50: =SUMIF('Other Income Assumptions'!$C:$C,$E$50,'Other Income Assumptions'!G:G) -> 0 | O50: =SUMIF('Other Income Assumptions'!$C:$C,$E$50,'Other Income Assumptions'!H:H) -> 0 | P50: =SUMIF('Other Income Assumptions'!$C:$C,$E$50,'Other Income Assumptions'!I:I) -> 0 | Q50: =SUMIF('Other Income Assumptions'!$C:$C,$E$50,'Other Income Assumptions'!J:J) -> 0 | R50: =SUMIF('Other Income Assumptions'!$C:$C,$E$50,'Other Income Assumptions'!K:K) -> 0 | S50: =SUMIF('Other Income Assumptions'!$C:$C,$E$50,'Other Income Assumptions'!L:L) -> 0 | T50: =SUMIF('Other Income Assumptions'!$C:$C,$E$50,'Other Income Assumptions'!M:M) -> 0 | U50: =SUMIF('Other Income Assumptions'!$C:$C,$E$50,'Other Income Assumptions'!N:N) -> 0 | V50: =SUMIF('Other Income Assumptions'!$C:$C,$E$50,'Other Income Assumptions'!O:O) -> 0
E51: Trash | K51: =SUMIF('Other Income Assumptions'!$C:$C,$E$50,'Other Income Assumptions'!D:D) -> 0 | L51: =SUMIF('Other Income Assumptions'!$C:$C,$E$50,'Other Income Assumptions'!E:E) -> 0 | M51: =SUMIF('Other Income Assumptions'!$C:$C,$E$50,'Other Income Assumptions'!F:F) -> 0 | N51: =SUMIF('Other Income Assumptions'!$C:$C,$E$50,'Other Income Assumptions'!G:G) -> 0 | O51: =SUMIF('Other Income Assumptions'!$C:$C,$E$50,'Other Income Assumptions'!H:H) -> 0 | P51: =SUMIF('Other Income Assumptions'!$C:$C,$E$50,'Other Income Assumptions'!I:I) -> 0 | Q51: =SUMIF('Other Income Assumptions'!$C:$C,$E$50,'Other Income Assumptions'!J:J) -> 0 | R51: =SUMIF('Other Income Assumptions'!$C:$C,$E$50,'Other Income Assumptions'!K:K) -> 0 | S51: =SUMIF('Other Income Assumptions'!$C:$C,$E$50,'Other Income Assumptions'!L:L) -> 0 | T51: =SUMIF('Other Income Assumptions'!$C:$C,$E$50,'Other Income Assumptions'!M:M) -> 0 | U51: =SUMIF('Other Income Assumptions'!$C:$C,$E$50,'Other Income Assumptions'!N:N) -> 0 | V51: =SUMIF('Other Income Assumptions'!$C:$C,$E$50,'Other Income Assumptions'!O:O) -> 0
E52: Utility Reimbursement | K52: =SUMIF('Other Income Assumptions'!$C:$C,$E$50,'Other Income Assumptions'!D:D) -> 0 | L52: =SUMIF('Other Income Assumptions'!$C:$C,$E$50,'Other Income Assumptions'!E:E) -> 0 | M52: =SUMIF('Other Income Assumptions'!$C:$C,$E$50,'Other Income Assumptions'!F:F) -> 0 | N52: =SUMIF('Other Income Assumptions'!$C:$C,$E$50,'Other Income Assumptions'!G:G) -> 0 | O52: =SUMIF('Other Income Assumptions'!$C:$C,$E$50,'Other Income Assumptions'!H:H) -> 0 | P52: =SUMIF('Other Income Assumptions'!$C:$C,$E$50,'Other Income Assumptions'!I:I) -> 0 | Q52: =SUMIF('Other Income Assumptions'!$C:$C,$E$50,'Other Income Assumptions'!J:J) -> 0 | R52: =SUMIF('Other Income Assumptions'!$C:$C,$E$50,'Other Income Assumptions'!K:K) -> 0 | S52: =SUMIF('Other Income Assumptions'!$C:$C,$E$50,'Other Income Assumptions'!L:L) -> 0 | T52: =SUMIF('Other Income Assumptions'!$C:$C,$E$50,'Other Income Assumptions'!M:M) -> 0 | U52: =SUMIF('Other Income Assumptions'!$C:$C,$E$50,'Other Income Assumptions'!N:N) -> 0 | V52: =SUMIF('Other Income Assumptions'!$C:$C,$E$50,'Other Income Assumptions'!O:O) -> 0
E53: Valet Income | K53: =SUMIF('Other Income Assumptions'!$C:$C,$E$50,'Other Income Assumptions'!D:D) -> 0 | L53: =SUMIF('Other Income Assumptions'!$C:$C,$E$50,'Other Income Assumptions'!E:E) -> 0 | M53: =SUMIF('Other Income Assumptions'!$C:$C,$E$50,'Other Income Assumptions'!F:F) -> 0 | N53: =SUMIF('Other Income Assumptions'!$C:$C,$E$50,'Other Income Assumptions'!G:G) -> 0 | O53: =SUMIF('Other Income Assumptions'!$C:$C,$E$50,'Other Income Assumptions'!H:H) -> 0 | P53: =SUMIF('Other Income Assumptions'!$C:$C,$E$50,'Other Income Assumptions'!I:I) -> 0 | Q53: =SUMIF('Other Income Assumptions'!$C:$C,$E$50,'Other Income Assumptions'!J:J) -> 0 | R53: =SUMIF('Other Income Assumptions'!$C:$C,$E$50,'Other Income Assumptions'!K:K) -> 0 | S53: =SUMIF('Other Income Assumptions'!$C:$C,$E$50,'Other Income Assumptions'!L:L) -> 0 | T53: =SUMIF('Other Income Assumptions'!$C:$C,$E$50,'Other Income Assumptions'!M:M) -> 0 | U53: =SUMIF('Other Income Assumptions'!$C:$C,$E$50,'Other Income Assumptions'!N:N) -> 0 | V53: =SUMIF('Other Income Assumptions'!$C:$C,$E$50,'Other Income Assumptions'!O:O) -> 0
K54: =SUMIF('Other Income Assumptions'!$C:$C,$E$50,'Other Income Assumptions'!D:D) -> 0 | L54: =SUMIF('Other Income Assumptions'!$C:$C,$E$50,'Other Income Assumptions'!E:E) -> 0 | M54: =SUMIF('Other Income Assumptions'!$C:$C,$E$50,'Other Income Assumptions'!F:F) -> 0 | N54: =SUMIF('Other Income Assumptions'!$C:$C,$E$50,'Other Income Assumptions'!G:G) -> 0 | O54: =SUMIF('Other Income Assumptions'!$C:$C,$E$50,'Other Income Assumptions'!H:H) -> 0 | P54: =SUMIF('Other Income Assumptions'!$C:$C,$E$50,'Other Income Assumptions'!I:I) -> 0 | Q54: =SUMIF('Other Income Assumptions'!$C:$C,$E$50,'Other Income Assumptions'!J:J) -> 0 | R54: =SUMIF('Other Income Assumptions'!$C:$C,$E$50,'Other Income Assumptions'!K:K) -> 0 | S54: =SUMIF('Other Income Assumptions'!$C:$C,$E$50,'Other Income Assumptions'!L:L) -> 0 | T54: =SUMIF('Other Income Assumptions'!$C:$C,$E$50,'Other Income Assumptions'!M:M) -> 0 | U54: =SUMIF('Other Income Assumptions'!$C:$C,$E$50,'Other Income Assumptions'!N:N) -> 0 | V54: =SUMIF('Other Income Assumptions'!$C:$C,$E$50,'Other Income Assumptions'!O:O) -> 0
F55: =IFERROR(INDEX('Other Income Assumptions'!$D:$D, MATCH(E55, 'Other Income Assumptions'!$C:$C, 0)), "") | K55: =SUMIF('Other Income Assumptions'!$C:$C,$E$55,'Other Income Assumptions'!D:D) -> 0 | L55: =SUMIF('Other Income Assumptions'!$C:$C,$E$55,'Other Income Assumptions'!E:E) -> 0 | M55: =SUMIF('Other Income Assumptions'!$C:$C,$E$55,'Other Income Assumptions'!F:F) -> 0 | N55: =SUMIF('Other Income Assumptions'!$C:$C,$E$55,'Other Income Assumptions'!G:G) -> 0 | O55: =SUMIF('Other Income Assumptions'!$C:$C,$E$55,'Other Income Assumptions'!H:H) -> 0 | P55: =SUMIF('Other Income Assumptions'!$C:$C,$E$55,'Other Income Assumptions'!I:I) -> 0 | Q55: =SUMIF('Other Income Assumptions'!$C:$C,$E$55,'Other Income Assumptions'!J:J) -> 0 | R55: =SUMIF('Other Income Assumptions'!$C:$C,$E$55,'Other Income Assumptions'!K:K) -> 0 | S55: =SUMIF('Other Income Assumptions'!$C:$C,$E$55,'Other Income Assumptions'!L:L) -> 0 | T55: =SUMIF('Other Income Assumptions'!$C:$C,$E$55,'Other Income Assumptions'!M:M) -> 0 | U55: =SUMIF('Other Income Assumptions'!$C:$C,$E$55,'Other Income Assumptions'!N:N) -> 0 | V55: =SUMIF('Other Income Assumptions'!$C:$C,$E$55,'Other Income Assumptions'!O:O) -> 0
E56: Total Other Income | H56: =SUM(H29:H55) -> 0 | I56: =SUM(I29:I55) -> 0 | J56: =SUM(J29:J55) -> 0 | K56: =SUM(K29:K55) -> 0 | L56: =SUM(L29:L55) -> 0 | M56: =SUM(M29:M55) -> 0 | N56: =SUM(N29:N55) -> 0 | O56: =SUM(O29:O55) -> 0 | ... AH56: =SUM(AH29:AH55) -> 0
E58: Effective Gross Income | H58: =SUM(H56,H27) -> 0 | I58: =SUM(I56,I27) -> 0 | J58: =SUM(J56,J27) -> 0 | K58: =SUM(K56,K27) -> #DIV/0! | L58: =SUM(L56,L27) -> #DIV/0! | M58: =SUM(M56,M27) -> #DIV/0! | N58: =SUM(N56,N27) -> #DIV/0! | O58: =SUM(O56,O27) -> #DIV/0! | ... AH58: =SUM(AH56,AH27) -> #DIV/0!
E60: Expenses
E62: Salary - Property Management | K62: ='Payroll Schedule'!$G$21/12 -> 18836.667
E63: Salary - Maintenance
E64: Payroll - Burden
E65: Leasing Bonuses
E69: Total Payroll | H69: =SUM(H62:H68) -> 0 | I69: =SUM(I62:I68) -> 0 | J69: =SUM(J62:J68) -> 0 | K69: =SUM(K62:K68) -> 18836.667 | L69: =SUM(L62:L68) -> 0 | M69: =SUM(M62:M68) -> 0 | N69: =SUM(N62:N68) -> 0 | O69: =SUM(O62:O68) -> 0 | ... AH69: =SUM(AH62:AH68) -> 0
E71: G&A | K71: =SUMIF('G&A Assumptions'!$B:$B,$E71,'G&A Assumptions'!E:E) -> 0 | L71: =SUMIF('G&A Assumptions'!$B:$B,$E71,'G&A Assumptions'!F:F) -> 0 | M71: =SUMIF('G&A Assumptions'!$B:$B,$E71,'G&A Assumptions'!G:G) -> 0 | N71: =SUMIF('G&A Assumptions'!$B:$B,$E71,'G&A Assumptions'!H:H) -> 0 | O71: =SUMIF('G&A Assumptions'!$B:$B,$E71,'G&A Assumptions'!I:I) -> 0 | P71: =SUMIF('G&A Assumptions'!$B:$B,$E71,'G&A Assumptions'!J:J) -> 0 | Q71: =SUMIF('G&A Assumptions'!$B:$B,$E71,'G&A Assumptions'!K:K) -> 0 | R71: =SUMIF('G&A Assumptions'!$B:$B,$E71,'G&A Assumptions'!L:L) -> 0 | S71: =SUMIF('G&A Assumptions'!$B:$B,$E71,'G&A Assumptions'!M:M) -> 0 | T71: =SUMIF('G&A Assumptions'!$B:$B,$E71,'G&A Assumptions'!N:N) -> 0 | U71: =SUMIF('G&A Assumptions'!$B:$B,$E71,'G&A Assumptions'!O:O) -> 0 | V71: =SUMIF('G&A Assumptions'!$B:$B,$E71,'G&A Assumptions'!P:P) -> 0 | W71: =SUMIF('G&A Assumptions'!$B:$B,$E71,'G&A Assumptions'!E:E) -> 0 | X71: =SUMIF('G&A Assumptions'!$B:$B,$E71,'G&A Assumptions'!F:F) -> 0 | Y71: =SUMIF('G&A Assumptions'!$B:$B,$E71,'G&A Assumptions'!G:G) -> 0 | Z71: =SUMIF('G&A Assumptions'!$B:$B,$E71,'G&A Assumptions'!H:H) -> 0 | AA71: =SUMIF('G&A Assumptions'!$B:$B,$E71,'G&A Assumptions'!I:I) -> 0 | AB71: =SUMIF('G&A Assumptions'!$B:$B,$E71,'G&A Assumptions'!J:J) -> 0 | AC71: =SUMIF('G&A Assumptions'!$B:$B,$E71,'G&A Assumptions'!K:K) -> 0 | AD71: =SUMIF('G&A Assumptions'!$B:$B,$E71,'G&A Assumptions'!L:L) -> 0 | AE71: =SUMIF('G&A Assumptions'!$B:$B,$E71,'G&A Assumptions'!M:M) -> 0 | AF71: =SUMIF('G&A Assumptions'!$B:$B,$E71,'G&A Assumptions'!N:N) -> 0 | AG71: =SUMIF('G&A Assumptions'!$B:$B,$E71,'G&A Assumptions'!O:O) -> 0 | AH71: =SUMIF('G&A Assumptions'!$B:$B,$E71,'G&A Assumptions'!P:P) -> 0
E72: Supplies | K72: =SUMIF('G&A Assumptions'!$B:$B,$E72,'G&A Assumptions'!E:E) -> 0 | L72: =SUMIF('G&A Assumptions'!$B:$B,$E72,'G&A Assumptions'!F:F) -> 0 | M72: =SUMIF('G&A Assumptions'!$B:$B,$E72,'G&A Assumptions'!G:G) -> 0 | N72: =SUMIF('G&A Assumptions'!$B:$B,$E72,'G&A Assumptions'!H:H) -> 0 | O72: =SUMIF('G&A Assumptions'!$B:$B,$E72,'G&A Assumptions'!I:I) -> 0 | P72: =SUMIF('G&A Assumptions'!$B:$B,$E72,'G&A Assumptions'!J:J) -> 0 | Q72: =SUMIF('G&A Assumptions'!$B:$B,$E72,'G&A Assumptions'!K:K) -> 0 | R72: =SUMIF('G&A Assumptions'!$B:$B,$E72,'G&A Assumptions'!L:L) -> 0 | S72: =SUMIF('G&A Assumptions'!$B:$B,$E72,'G&A Assumptions'!M:M) -> 0 | T72: =SUMIF('G&A Assumptions'!$B:$B,$E72,'G&A Assumptions'!N:N) -> 0 | U72: =SUMIF('G&A Assumptions'!$B:$B,$E72,'G&A Assumptions'!O:O) -> 0 | V72: =SUMIF('G&A Assumptions'!$B:$B,$E72,'G&A Assumptions'!P:P) -> 0 | W72: =SUMIF('G&A Assumptions'!$B:$B,$E72,'G&A Assumptions'!E:E) -> 0 | X72: =SUMIF('G&A Assumptions'!$B:$B,$E72,'G&A Assumptions'!F:F) -> 0 | Y72: =SUMIF('G&A Assumptions'!$B:$B,$E72,'G&A Assumptions'!G:G) -> 0 | Z72: =SUMIF('G&A Assumptions'!$B:$B,$E72,'G&A Assumptions'!H:H) -> 0 | AA72: =SUMIF('G&A Assumptions'!$B:$B,$E72,'G&A Assumptions'!I:I) -> 0 | AB72: =SUMIF('G&A Assumptions'!$B:$B,$E72,'G&A Assumptions'!J:J) -> 0 | AC72: =SUMIF('G&A Assumptions'!$B:$B,$E72,'G&A Assumptions'!K:K) -> 0 | AD72: =SUMIF('G&A Assumptions'!$B:$B,$E72,'G&A Assumptions'!L:L) -> 0 | AE72: =SUMIF('G&A Assumptions'!$B:$B,$E72,'G&A Assumptions'!M:M) -> 0 | AF72: =SUMIF('G&A Assumptions'!$B:$B,$E72,'G&A Assumptions'!N:N) -> 0 | AG72: =SUMIF('G&A Assumptions'!$B:$B,$E72,'G&A Assumptions'!O:O) -> 0 | AH72: =SUMIF('G&A Assumptions'!$B:$B,$E72,'G&A Assumptions'!P:P) -> 0
E73: Memberships | K73: =SUMIF('G&A Assumptions'!$B:$B,$E73,'G&A Assumptions'!E:E) -> 0 | L73: =SUMIF('G&A Assumptions'!$B:$B,$E73,'G&A Assumptions'!F:F) -> 0 | M73: =SUMIF('G&A Assumptions'!$B:$B,$E73,'G&A Assumptions'!G:G) -> 0 | N73: =SUMIF('G&A Assumptions'!$B:$B,$E73,'G&A Assumptions'!H:H) -> 0 | O73: =SUMIF('G&A Assumptions'!$B:$B,$E73,'G&A Assumptions'!I:I) -> 0 | P73: =SUMIF('G&A Assumptions'!$B:$B,$E73,'G&A Assumptions'!J:J) -> 0 | Q73: =SUMIF('G&A Assumptions'!$B:$B,$E73,'G&A Assumptions'!K:K) -> 0 | R73: =SUMIF('G&A Assumptions'!$B:$B,$E73,'G&A Assumptions'!L:L) -> 0 | S73: =SUMIF('G&A Assumptions'!$B:$B,$E73,'G&A Assumptions'!M:M) -> 0 | T73: =SUMIF('G&A Assumptions'!$B:$B,$E73,'G&A Assumptions'!N:N) -> 0 | U73: =SUMIF('G&A Assumptions'!$B:$B,$E73,'G&A Assumptions'!O:O) -> 0 | V73: =SUMIF('G&A Assumptions'!$B:$B,$E73,'G&A Assumptions'!P:P) -> 0 | W73: =SUMIF('G&A Assumptions'!$B:$B,$E73,'G&A Assumptions'!E:E) -> 0 | X73: =SUMIF('G&A Assumptions'!$B:$B,$E73,'G&A Assumptions'!F:F) -> 0 | Y73: =SUMIF('G&A Assumptions'!$B:$B,$E73,'G&A Assumptions'!G:G) -> 0 | Z73: =SUMIF('G&A Assumptions'!$B:$B,$E73,'G&A Assumptions'!H:H) -> 0 | AA73: =SUMIF('G&A Assumptions'!$B:$B,$E73,'G&A Assumptions'!I:I) -> 0 | AB73: =SUMIF('G&A Assumptions'!$B:$B,$E73,'G&A Assumptions'!J:J) -> 0 | AC73: =SUMIF('G&A Assumptions'!$B:$B,$E73,'G&A Assumptions'!K:K) -> 0 | AD73: =SUMIF('G&A Assumptions'!$B:$B,$E73,'G&A Assumptions'!L:L) -> 0 | AE73: =SUMIF('G&A Assumptions'!$B:$B,$E73,'G&A Assumptions'!M:M) -> 0 | AF73: =SUMIF('G&A Assumptions'!$B:$B,$E73,'G&A Assumptions'!N:N) -> 0 | AG73: =SUMIF('G&A Assumptions'!$B:$B,$E73,'G&A Assumptions'!O:O) -> 0 | AH73: =SUMIF('G&A Assumptions'!$B:$B,$E73,'G&A Assumptions'!P:P) -> 0
E74: Telephone | K74: =SUMIF('G&A Assumptions'!$B:$B,$E74,'G&A Assumptions'!E:E) -> 0 | L74: =SUMIF('G&A Assumptions'!$B:$B,$E74,'G&A Assumptions'!F:F) -> 0 | M74: =SUMIF('G&A Assumptions'!$B:$B,$E74,'G&A Assumptions'!G:G) -> 0 | N74: =SUMIF('G&A Assumptions'!$B:$B,$E74,'G&A Assumptions'!H:H) -> 0 | O74: =SUMIF('G&A Assumptions'!$B:$B,$E74,'G&A Assumptions'!I:I) -> 0 | P74: =SUMIF('G&A Assumptions'!$B:$B,$E74,'G&A Assumptions'!J:J) -> 0 | Q74: =SUMIF('G&A Assumptions'!$B:$B,$E74,'G&A Assumptions'!K:K) -> 0 | R74: =SUMIF('G&A Assumptions'!$B:$B,$E74,'G&A Assumptions'!L:L) -> 0 | S74: =SUMIF('G&A Assumptions'!$B:$B,$E74,'G&A Assumptions'!M:M) -> 0 | T74: =SUMIF('G&A Assumptions'!$B:$B,$E74,'G&A Assumptions'!N:N) -> 0 | U74: =SUMIF('G&A Assumptions'!$B:$B,$E74,'G&A Assumptions'!O:O) -> 0 | V74: =SUMIF('G&A Assumptions'!$B:$B,$E74,'G&A Assumptions'!P:P) -> 0 | W74: =SUMIF('G&A Assumptions'!$B:$B,$E74,'G&A Assumptions'!E:E) -> 0 | X74: =SUMIF('G&A Assumptions'!$B:$B,$E74,'G&A Assumptions'!F:F) -> 0 | Y74: =SUMIF('G&A Assumptions'!$B:$B,$E74,'G&A Assumptions'!G:G) -> 0 | Z74: =SUMIF('G&A Assumptions'!$B:$B,$E74,'G&A Assumptions'!H:H) -> 0 | AA74: =SUMIF('G&A Assumptions'!$B:$B,$E74,'G&A Assumptions'!I:I) -> 0 | AB74: =SUMIF('G&A Assumptions'!$B:$B,$E74,'G&A Assumptions'!J:J) -> 0 | AC74: =SUMIF('G&A Assumptions'!$B:$B,$E74,'G&A Assumptions'!K:K) -> 0 | AD74: =SUMIF('G&A Assumptions'!$B:$B,$E74,'G&A Assumptions'!L:L) -> 0 | AE74: =SUMIF('G&A Assumptions'!$B:$B,$E74,'G&A Assumptions'!M:M) -> 0 | AF74: =SUMIF('G&A Assumptions'!$B:$B,$E74,'G&A Assumptions'!N:N) -> 0 | AG74: =SUMIF('G&A Assumptions'!$B:$B,$E74,'G&A Assumptions'!O:O) -> 0 | AH74: =SUMIF('G&A Assumptions'!$B:$B,$E74,'G&A Assumptions'!P:P) -> 0
K75: =SUMIF('G&A Assumptions'!$B:$B,$E75,'G&A Assumptions'!E:E) -> 0 | L75: =SUMIF('G&A Assumptions'!$B:$B,$E75,'G&A Assumptions'!F:F) -> 0 | M75: =SUMIF('G&A Assumptions'!$B:$B,$E75,'G&A Assumptions'!G:G) -> 0 | N75: =SUMIF('G&A Assumptions'!$B:$B,$E75,'G&A Assumptions'!H:H) -> 0 | O75: =SUMIF('G&A Assumptions'!$B:$B,$E75,'G&A Assumptions'!I:I) -> 0 | P75: =SUMIF('G&A Assumptions'!$B:$B,$E75,'G&A Assumptions'!J:J) -> 0 | Q75: =SUMIF('G&A Assumptions'!$B:$B,$E75,'G&A Assumptions'!K:K) -> 0 | R75: =SUMIF('G&A Assumptions'!$B:$B,$E75,'G&A Assumptions'!L:L) -> 0 | S75: =SUMIF('G&A Assumptions'!$B:$B,$E75,'G&A Assumptions'!M:M) -> 0 | T75: =SUMIF('G&A Assumptions'!$B:$B,$E75,'G&A Assumptions'!N:N) -> 0 | U75: =SUMIF('G&A Assumptions'!$B:$B,$E75,'G&A Assumptions'!O:O) -> 0 | V75: =SUMIF('G&A Assumptions'!$B:$B,$E75,'G&A Assumptions'!P:P) -> 0 | W75: =SUMIF('G&A Assumptions'!$B:$B,$E75,'G&A Assumptions'!E:E) -> 0 | X75: =SUMIF('G&A Assumptions'!$B:$B,$E75,'G&A Assumptions'!F:F) -> 0 | Y75: =SUMIF('G&A Assumptions'!$B:$B,$E75,'G&A Assumptions'!G:G) -> 0 | Z75: =SUMIF('G&A Assumptions'!$B:$B,$E75,'G&A Assumptions'!H:H) -> 0 | AA75: =SUMIF('G&A Assumptions'!$B:$B,$E75,'G&A Assumptions'!I:I) -> 0 | AB75: =SUMIF('G&A Assumptions'!$B:$B,$E75,'G&A Assumptions'!J:J) -> 0 | AC75: =SUMIF('G&A Assumptions'!$B:$B,$E75,'G&A Assumptions'!K:K) -> 0 | AD75: =SUMIF('G&A Assumptions'!$B:$B,$E75,'G&A Assumptions'!L:L) -> 0 | AE75: =SUMIF('G&A Assumptions'!$B:$B,$E75,'G&A Assumptions'!M:M) -> 0 | AF75: =SUMIF('G&A Assumptions'!$B:$B,$E75,'G&A Assumptions'!N:N) -> 0 | AG75: =SUMIF('G&A Assumptions'!$B:$B,$E75,'G&A Assumptions'!O:O) -> 0 | AH75: =SUMIF('G&A Assumptions'!$B:$B,$E75,'G&A Assumptions'!P:P) -> 0
E76: Legal | K76: =SUMIF('G&A Assumptions'!$B:$B,$E76,'G&A Assumptions'!E:E) -> 0 | L76: =SUMIF('G&A Assumptions'!$B:$B,$E76,'G&A Assumptions'!F:F) -> 0 | M76: =SUMIF('G&A Assumptions'!$B:$B,$E76,'G&A Assumptions'!G:G) -> 0 | N76: =SUMIF('G&A Assumptions'!$B:$B,$E76,'G&A Assumptions'!H:H) -> 0 | O76: =SUMIF('G&A Assumptions'!$B:$B,$E76,'G&A Assumptions'!I:I) -> 0 | P76: =SUMIF('G&A Assumptions'!$B:$B,$E76,'G&A Assumptions'!J:J) -> 0 | Q76: =SUMIF('G&A Assumptions'!$B:$B,$E76,'G&A Assumptions'!K:K) -> 0 | R76: =SUMIF('G&A Assumptions'!$B:$B,$E76,'G&A Assumptions'!L:L) -> 0 | S76: =SUMIF('G&A Assumptions'!$B:$B,$E76,'G&A Assumptions'!M:M) -> 0 | T76: =SUMIF('G&A Assumptions'!$B:$B,$E76,'G&A Assumptions'!N:N) -> 0 | U76: =SUMIF('G&A Assumptions'!$B:$B,$E76,'G&A Assumptions'!O:O) -> 0 | V76: =SUMIF('G&A Assumptions'!$B:$B,$E76,'G&A Assumptions'!P:P) -> 0 | W76: =SUMIF('G&A Assumptions'!$B:$B,$E76,'G&A Assumptions'!E:E) -> 0 | X76: =SUMIF('G&A Assumptions'!$B:$B,$E76,'G&A Assumptions'!F:F) -> 0 | Y76: =SUMIF('G&A Assumptions'!$B:$B,$E76,'G&A Assumptions'!G:G) -> 0 | Z76: =SUMIF('G&A Assumptions'!$B:$B,$E76,'G&A Assumptions'!H:H) -> 0 | AA76: =SUMIF('G&A Assumptions'!$B:$B,$E76,'G&A Assumptions'!I:I) -> 0 | AB76: =SUMIF('G&A Assumptions'!$B:$B,$E76,'G&A Assumptions'!J:J) -> 0 | AC76: =SUMIF('G&A Assumptions'!$B:$B,$E76,'G&A Assumptions'!K:K) -> 0 | AD76: =SUMIF('G&A Assumptions'!$B:$B,$E76,'G&A Assumptions'!L:L) -> 0 | AE76: =SUMIF('G&A Assumptions'!$B:$B,$E76,'G&A Assumptions'!M:M) -> 0 | AF76: =SUMIF('G&A Assumptions'!$B:$B,$E76,'G&A Assumptions'!N:N) -> 0 | AG76: =SUMIF('G&A Assumptions'!$B:$B,$E76,'G&A Assumptions'!O:O) -> 0 | AH76: =SUMIF('G&A Assumptions'!$B:$B,$E76,'G&A Assumptions'!P:P) -> 0
E77: Bank Charges | K77: =SUMIF('G&A Assumptions'!$B:$B,$E77,'G&A Assumptions'!E:E) -> 0 | L77: =SUMIF('G&A Assumptions'!$B:$B,$E77,'G&A Assumptions'!F:F) -> 0 | M77: =SUMIF('G&A Assumptions'!$B:$B,$E77,'G&A Assumptions'!G:G) -> 0 | N77: =SUMIF('G&A Assumptions'!$B:$B,$E77,'G&A Assumptions'!H:H) -> 0 | O77: =SUMIF('G&A Assumptions'!$B:$B,$E77,'G&A Assumptions'!I:I) -> 0 | P77: =SUMIF('G&A Assumptions'!$B:$B,$E77,'G&A Assumptions'!J:J) -> 0 | Q77: =SUMIF('G&A Assumptions'!$B:$B,$E77,'G&A Assumptions'!K:K) -> 0 | R77: =SUMIF('G&A Assumptions'!$B:$B,$E77,'G&A Assumptions'!L:L) -> 0 | S77: =SUMIF('G&A Assumptions'!$B:$B,$E77,'G&A Assumptions'!M:M) -> 0 | T77: =SUMIF('G&A Assumptions'!$B:$B,$E77,'G&A Assumptions'!N:N) -> 0 | U77: =SUMIF('G&A Assumptions'!$B:$B,$E77,'G&A Assumptions'!O:O) -> 0 | V77: =SUMIF('G&A Assumptions'!$B:$B,$E77,'G&A Assumptions'!P:P) -> 0 | W77: =SUMIF('G&A Assumptions'!$B:$B,$E77,'G&A Assumptions'!E:E) -> 0 | X77: =SUMIF('G&A Assumptions'!$B:$B,$E77,'G&A Assumptions'!F:F) -> 0 | Y77: =SUMIF('G&A Assumptions'!$B:$B,$E77,'G&A Assumptions'!G:G) -> 0 | Z77: =SUMIF('G&A Assumptions'!$B:$B,$E77,'G&A Assumptions'!H:H) -> 0 | AA77: =SUMIF('G&A Assumptions'!$B:$B,$E77,'G&A Assumptions'!I:I) -> 0 | AB77: =SUMIF('G&A Assumptions'!$B:$B,$E77,'G&A Assumptions'!J:J) -> 0 | AC77: =SUMIF('G&A Assumptions'!$B:$B,$E77,'G&A Assumptions'!K:K) -> 0 | AD77: =SUMIF('G&A Assumptions'!$B:$B,$E77,'G&A Assumptions'!L:L) -> 0 | AE77: =SUMIF('G&A Assumptions'!$B:$B,$E77,'G&A Assumptions'!M:M) -> 0 | AF77: =SUMIF('G&A Assumptions'!$B:$B,$E77,'G&A Assumptions'!N:N) -> 0 | AG77: =SUMIF('G&A Assumptions'!$B:$B,$E77,'G&A Assumptions'!O:O) -> 0 | AH77: =SUMIF('G&A Assumptions'!$B:$B,$E77,'G&A Assumptions'!P:P) -> 0
E78: Eviction Charges | K78: =SUMIF('G&A Assumptions'!$B:$B,$E78,'G&A Assumptions'!E:E) -> 0 | L78: =SUMIF('G&A Assumptions'!$B:$B,$E78,'G&A Assumptions'!F:F) -> 0 | M78: =SUMIF('G&A Assumptions'!$B:$B,$E78,'G&A Assumptions'!G:G) -> 0 | N78: =SUMIF('G&A Assumptions'!$B:$B,$E78,'G&A Assumptions'!H:H) -> 0 | O78: =SUMIF('G&A Assumptions'!$B:$B,$E78,'G&A Assumptions'!I:I) -> 0 | P78: =SUMIF('G&A Assumptions'!$B:$B,$E78,'G&A Assumptions'!J:J) -> 0 | Q78: =SUMIF('G&A Assumptions'!$B:$B,$E78,'G&A Assumptions'!K:K) -> 0 | R78: =SUMIF('G&A Assumptions'!$B:$B,$E78,'G&A Assumptions'!L:L) -> 0 | S78: =SUMIF('G&A Assumptions'!$B:$B,$E78,'G&A Assumptions'!M:M) -> 0 | T78: =SUMIF('G&A Assumptions'!$B:$B,$E78,'G&A Assumptions'!N:N) -> 0 | U78: =SUMIF('G&A Assumptions'!$B:$B,$E78,'G&A Assumptions'!O:O) -> 0 | V78: =SUMIF('G&A Assumptions'!$B:$B,$E78,'G&A Assumptions'!P:P) -> 0 | W78: =SUMIF('G&A Assumptions'!$B:$B,$E78,'G&A Assumptions'!E:E) -> 0 | X78: =SUMIF('G&A Assumptions'!$B:$B,$E78,'G&A Assumptions'!F:F) -> 0 | Y78: =SUMIF('G&A Assumptions'!$B:$B,$E78,'G&A Assumptions'!G:G) -> 0 | Z78: =SUMIF('G&A Assumptions'!$B:$B,$E78,'G&A Assumptions'!H:H) -> 0 | AA78: =SUMIF('G&A Assumptions'!$B:$B,$E78,'G&A Assumptions'!I:I) -> 0 | AB78: =SUMIF('G&A Assumptions'!$B:$B,$E78,'G&A Assumptions'!J:J) -> 0 | AC78: =SUMIF('G&A Assumptions'!$B:$B,$E78,'G&A Assumptions'!K:K) -> 0 | AD78: =SUMIF('G&A Assumptions'!$B:$B,$E78,'G&A Assumptions'!L:L) -> 0 | AE78: =SUMIF('G&A Assumptions'!$B:$B,$E78,'G&A Assumptions'!M:M) -> 0 | AF78: =SUMIF('G&A Assumptions'!$B:$B,$E78,'G&A Assumptions'!N:N) -> 0 | AG78: =SUMIF('G&A Assumptions'!$B:$B,$E78,'G&A Assumptions'!O:O) -> 0 | AH78: =SUMIF('G&A Assumptions'!$B:$B,$E78,'G&A Assumptions'!P:P) -> 0
E79: Internet | K79: =SUMIF('G&A Assumptions'!$B:$B,$E79,'G&A Assumptions'!E:E) -> 0 | L79: =SUMIF('G&A Assumptions'!$B:$B,$E79,'G&A Assumptions'!F:F) -> 0 | M79: =SUMIF('G&A Assumptions'!$B:$B,$E79,'G&A Assumptions'!G:G) -> 0 | N79: =SUMIF('G&A Assumptions'!$B:$B,$E79,'G&A Assumptions'!H:H) -> 0 | O79: =SUMIF('G&A Assumptions'!$B:$B,$E79,'G&A Assumptions'!I:I) -> 0 | P79: =SUMIF('G&A Assumptions'!$B:$B,$E79,'G&A Assumptions'!J:J) -> 0 | Q79: =SUMIF('G&A Assumptions'!$B:$B,$E79,'G&A Assumptions'!K:K) -> 0 | R79: =SUMIF('G&A Assumptions'!$B:$B,$E79,'G&A Assumptions'!L:L) -> 0 | S79: =SUMIF('G&A Assumptions'!$B:$B,$E79,'G&A Assumptions'!M:M) -> 0 | T79: =SUMIF('G&A Assumptions'!$B:$B,$E79,'G&A Assumptions'!N:N) -> 0 | U79: =SUMIF('G&A Assumptions'!$B:$B,$E79,'G&A Assumptions'!O:O) -> 0 | V79: =SUMIF('G&A Assumptions'!$B:$B,$E79,'G&A Assumptions'!P:P) -> 0 | W79: =SUMIF('G&A Assumptions'!$B:$B,$E79,'G&A Assumptions'!E:E) -> 0 | X79: =SUMIF('G&A Assumptions'!$B:$B,$E79,'G&A Assumptions'!F:F) -> 0 | Y79: =SUMIF('G&A Assumptions'!$B:$B,$E79,'G&A Assumptions'!G:G) -> 0 | Z79: =SUMIF('G&A Assumptions'!$B:$B,$E79,'G&A Assumptions'!H:H) -> 0 | AA79: =SUMIF('G&A Assumptions'!$B:$B,$E79,'G&A Assumptions'!I:I) -> 0 | AB79: =SUMIF('G&A Assumptions'!$B:$B,$E79,'G&A Assumptions'!J:J) -> 0 | AC79: =SUMIF('G&A Assumptions'!$B:$B,$E79,'G&A Assumptions'!K:K) -> 0 | AD79: =SUMIF('G&A Assumptions'!$B:$B,$E79,'G&A Assumptions'!L:L) -> 0 | AE79: =SUMIF('G&A Assumptions'!$B:$B,$E79,'G&A Assumptions'!M:M) -> 0 | AF79: =SUMIF('G&A Assumptions'!$B:$B,$E79,'G&A Assumptions'!N:N) -> 0 | AG79: =SUMIF('G&A Assumptions'!$B:$B,$E79,'G&A Assumptions'!O:O) -> 0 | AH79: =SUMIF('G&A Assumptions'!$B:$B,$E79,'G&A Assumptions'!P:P) -> 0
E80: G&A - Miscellaneous | K80: =SUMIF('G&A Assumptions'!$B:$B,$E80,'G&A Assumptions'!E:E) -> 0 | L80: =SUMIF('G&A Assumptions'!$B:$B,$E80,'G&A Assumptions'!F:F) -> 0 | M80: =SUMIF('G&A Assumptions'!$B:$B,$E80,'G&A Assumptions'!G:G) -> 0 | N80: =SUMIF('G&A Assumptions'!$B:$B,$E80,'G&A Assumptions'!H:H) -> 0 | O80: =SUMIF('G&A Assumptions'!$B:$B,$E80,'G&A Assumptions'!I:I) -> 0 | P80: =SUMIF('G&A Assumptions'!$B:$B,$E80,'G&A Assumptions'!J:J) -> 0 | Q80: =SUMIF('G&A Assumptions'!$B:$B,$E80,'G&A Assumptions'!K:K) -> 0 | R80: =SUMIF('G&A Assumptions'!$B:$B,$E80,'G&A Assumptions'!L:L) -> 0 | S80: =SUMIF('G&A Assumptions'!$B:$B,$E80,'G&A Assumptions'!M:M) -> 0 | T80: =SUMIF('G&A Assumptions'!$B:$B,$E80,'G&A Assumptions'!N:N) -> 0 | U80: =SUMIF('G&A Assumptions'!$B:$B,$E80,'G&A Assumptions'!O:O) -> 0 | V80: =SUMIF('G&A Assumptions'!$B:$B,$E80,'G&A Assumptions'!P:P) -> 0 | W80: =SUMIF('G&A Assumptions'!$B:$B,$E80,'G&A Assumptions'!E:E) -> 0 | X80: =SUMIF('G&A Assumptions'!$B:$B,$E80,'G&A Assumptions'!F:F) -> 0 | Y80: =SUMIF('G&A Assumptions'!$B:$B,$E80,'G&A Assumptions'!G:G) -> 0 | Z80: =SUMIF('G&A Assumptions'!$B:$B,$E80,'G&A Assumptions'!H:H) -> 0 | AA80: =SUMIF('G&A Assumptions'!$B:$B,$E80,'G&A Assumptions'!I:I) -> 0 | AB80: =SUMIF('G&A Assumptions'!$B:$B,$E80,'G&A Assumptions'!J:J) -> 0 | AC80: =SUMIF('G&A Assumptions'!$B:$B,$E80,'G&A Assumptions'!K:K) -> 0 | AD80: =SUMIF('G&A Assumptions'!$B:$B,$E80,'G&A Assumptions'!L:L) -> 0 | AE80: =SUMIF('G&A Assumptions'!$B:$B,$E80,'G&A Assumptions'!M:M) -> 0 | AF80: =SUMIF('G&A Assumptions'!$B:$B,$E80,'G&A Assumptions'!N:N) -> 0 | AG80: =SUMIF('G&A Assumptions'!$B:$B,$E80,'G&A Assumptions'!O:O) -> 0 | AH80: =SUMIF('G&A Assumptions'!$B:$B,$E80,'G&A Assumptions'!P:P) -> 0
E81: Total G&A | H81: =SUM(H71:H80) -> 0 | I81: =SUM(I71:I80) -> 0 | J81: =SUM(J71:J80) -> 0 | K81: =SUM(K71:K80) -> 0 | L81: =SUM(L71:L80) -> 0 | M81: =SUM(M71:M80) -> 0 | N81: =SUM(N71:N80) -> 0 | O81: =SUM(O71:O80) -> 0 | ... AH81: =SUM(AH71:AH80) -> 0
E83: Locator Fees | K83: =SUMIF('Marketing Stack - Lease-Up'!$B$6:$B$40,$E83,'Marketing Stack - Lease-Up'!E$6:E$40) -> 2750 | L83: =SUMIF('Marketing Stack - Lease-Up'!$B$6:$B$40,$E83,'Marketing Stack - Lease-Up'!F$6:F$40) -> 2750 | M83: =IF('Absorption Schedule'!#REF!<90%,SUMIF('Marketing Stack - Lease-Up'!$B$6:$B$40,$E83,'Marketing Stack - Lease-Up'!G$6:G$40),SUMIF('Marketing Stack'!$B$6:$B$40,$E83,'Marketing Stack'!G$6:G$40)) -> #REF! | N83: =IF('Absorption Schedule'!#REF!<90%,SUMIF('Marketing Stack - Lease-Up'!$B$6:$B$40,$E83,'Marketing Stack - Lease-Up'!H$6:H$40),SUMIF('Marketing Stack'!$B$6:$B$40,$E83,'Marketing Stack'!H$6:H$40)) -> #REF! | O83: =IF('Absorption Schedule'!#REF!<90%,SUMIF('Marketing Stack - Lease-Up'!$B$6:$B$40,$E83,'Marketing Stack - Lease-Up'!I$6:I$40),SUMIF('Marketing Stack'!$B$6:$B$40,$E83,'Marketing Stack'!I$6:I$40)) -> #REF! | P83: =IF('Absorption Schedule'!#REF!<90%,SUMIF('Marketing Stack - Lease-Up'!$B$6:$B$40,$E83,'Marketing Stack - Lease-Up'!J$6:J$40),SUMIF('Marketing Stack'!$B$6:$B$40,$E83,'Marketing Stack'!J$6:J$40)) -> #REF! | Q83: =IF('Absorption Schedule'!#REF!<90%,SUMIF('Marketing Stack - Lease-Up'!$B$6:$B$40,$E83,'Marketing Stack - Lease-Up'!K$6:K$40),SUMIF('Marketing Stack'!$B$6:$B$40,$E83,'Marketing Stack'!K$6:K$40)) -> #REF! | R83: =IF('Absorption Schedule'!#REF!<90%,SUMIF('Marketing Stack - Lease-Up'!$B$6:$B$40,$E83,'Marketing Stack - Lease-Up'!L$6:L$40),SUMIF('Marketing Stack'!$B$6:$B$40,$E83,'Marketing Stack'!L$6:L$40)) -> #REF! | S83: =IF('Absorption Schedule'!#REF!<90%,SUMIF('Marketing Stack - Lease-Up'!$B$6:$B$40,$E83,'Marketing Stack - Lease-Up'!M$6:M$40),SUMIF('Marketing Stack'!$B$6:$B$40,$E83,'Marketing Stack'!M$6:M$40)) -> #REF! | T83: =IF('Absorption Schedule'!#REF!<90%,SUMIF('Marketing Stack - Lease-Up'!$B$6:$B$40,$E83,'Marketing Stack - Lease-Up'!N$6:N$40),SUMIF('Marketing Stack'!$B$6:$B$40,$E83,'Marketing Stack'!N$6:N$40)) -> #REF! | ... V83: =IF('Absorption Schedule'!#REF!<90%,SUMIF('Marketing Stack - Lease-Up'!$B$6:$B$40,$E83,'Marketing Stack - Lease-Up'!P$6:P$40),SUMIF('Marketing Stack'!$B$6:$B$40,$E83,'Marketing Stack'!P$6:P$40)) -> #REF! | W83: =IF('Absorption Schedule'!#REF!<90%,SUMIF('Marketing Stack - Lease-Up'!$B$6:$B$40,$E83,'Marketing Stack - Lease-Up'!E$6:E$40),SUMIF('Marketing Stack'!$B$6:$B$40,$E83,'Marketing Stack'!E$6:E$40)) -> #REF! | X83: =IF('Absorption Schedule'!#REF!<90%,SUMIF('Marketing Stack - Lease-Up'!$B$6:$B$40,$E83,'Marketing Stack - Lease-Up'!F$6:F$40),SUMIF('Marketing Stack'!$B$6:$B$40,$E83,'Marketing Stack'!F$6:F$40)) -> #REF! | Y83: =IF('Absorption Schedule'!#REF!<90%,SUMIF('Marketing Stack - Lease-Up'!$B$6:$B$40,$E83,'Marketing Stack - Lease-Up'!G$6:G$40),SUMIF('Marketing Stack'!$B$6:$B$40,$E83,'Marketing Stack'!G$6:G$40)) -> #REF! | Z83: =IF('Absorption Schedule'!#REF!<90%,SUMIF('Marketing Stack - Lease-Up'!$B$6:$B$40,$E83,'Marketing Stack - Lease-Up'!H$6:H$40),SUMIF('Marketing Stack'!$B$6:$B$40,$E83,'Marketing Stack'!H$6:H$40)) -> #REF! | AA83: =IF('Absorption Schedule'!#REF!<90%,SUMIF('Marketing Stack - Lease-Up'!$B$6:$B$40,$E83,'Marketing Stack - Lease-Up'!I$6:I$40),SUMIF('Marketing Stack'!$B$6:$B$40,$E83,'Marketing Stack'!I$6:I$40)) -> #REF! | AB83: =IF('Absorption Schedule'!#REF!<90%,SUMIF('Marketing Stack - Lease-Up'!$B$6:$B$40,$E83,'Marketing Stack - Lease-Up'!J$6:J$40),SUMIF('Marketing Stack'!$B$6:$B$40,$E83,'Marketing Stack'!J$6:J$40)) -> #REF! | AC83: =IF('Absorption Schedule'!#REF!<90%,SUMIF('Marketing Stack - Lease-Up'!$B$6:$B$40,$E83,'Marketing Stack - Lease-Up'!K$6:K$40),SUMIF('Marketing Stack'!$B$6:$B$40,$E83,'Marketing Stack'!K$6:K$40)) -> #REF! | AD83: =IF('Absorption Schedule'!#REF!<90%,SUMIF('Marketing Stack - Lease-Up'!$B$6:$B$40,$E83,'Marketing Stack - Lease-Up'!L$6:L$40),SUMIF('Marketing Stack'!$B$6:$B$40,$E83,'Marketing Stack'!L$6:L$40)) -> #REF! | ... AH83: =IF('Absorption Schedule'!#REF!<90%,SUMIF('Marketing Stack - Lease-Up'!$B$6:$B$40,$E83,'Marketing Stack - Lease-Up'!P$6:P$40),SUMIF('Marketing Stack'!$B$6:$B$40,$E83,'Marketing Stack'!P$6:P$40)) -> #REF!
K84: =SUMIF('Marketing Stack - Lease-Up'!$B$6:$B$40,$E84,'Marketing Stack - Lease-Up'!E$6:E$40) -> 0 | L84: =SUMIF('Marketing Stack - Lease-Up'!$B$6:$B$40,$E84,'Marketing Stack - Lease-Up'!F$6:F$40) -> 0 | M84: =IF('Absorption Schedule'!#REF!<90%,SUMIF('Marketing Stack - Lease-Up'!$B$6:$B$40,$E84,'Marketing Stack - Lease-Up'!G$6:G$40),SUMIF('Marketing Stack'!$B$6:$B$40,$E84,'Marketing Stack'!G$6:G$40)) -> #REF! | N84: =IF('Absorption Schedule'!#REF!<90%,SUMIF('Marketing Stack - Lease-Up'!$B$6:$B$40,$E84,'Marketing Stack - Lease-Up'!H$6:H$40),SUMIF('Marketing Stack'!$B$6:$B$40,$E84,'Marketing Stack'!H$6:H$40)) -> #REF! | O84: =IF('Absorption Schedule'!#REF!<90%,SUMIF('Marketing Stack - Lease-Up'!$B$6:$B$40,$E84,'Marketing Stack - Lease-Up'!I$6:I$40),SUMIF('Marketing Stack'!$B$6:$B$40,$E84,'Marketing Stack'!I$6:I$40)) -> #REF! | P84: =IF('Absorption Schedule'!#REF!<90%,SUMIF('Marketing Stack - Lease-Up'!$B$6:$B$40,$E84,'Marketing Stack - Lease-Up'!J$6:J$40),SUMIF('Marketing Stack'!$B$6:$B$40,$E84,'Marketing Stack'!J$6:J$40)) -> #REF! | Q84: =IF('Absorption Schedule'!#REF!<90%,SUMIF('Marketing Stack - Lease-Up'!$B$6:$B$40,$E84,'Marketing Stack - Lease-Up'!K$6:K$40),SUMIF('Marketing Stack'!$B$6:$B$40,$E84,'Marketing Stack'!K$6:K$40)) -> #REF! | R84: =IF('Absorption Schedule'!#REF!<90%,SUMIF('Marketing Stack - Lease-Up'!$B$6:$B$40,$E84,'Marketing Stack - Lease-Up'!L$6:L$40),SUMIF('Marketing Stack'!$B$6:$B$40,$E84,'Marketing Stack'!L$6:L$40)) -> #REF! | S84: =IF('Absorption Schedule'!#REF!<90%,SUMIF('Marketing Stack - Lease-Up'!$B$6:$B$40,$E84,'Marketing Stack - Lease-Up'!M$6:M$40),SUMIF('Marketing Stack'!$B$6:$B$40,$E84,'Marketing Stack'!M$6:M$40)) -> #REF! | T84: =IF('Absorption Schedule'!#REF!<90%,SUMIF('Marketing Stack - Lease-Up'!$B$6:$B$40,$E84,'Marketing Stack - Lease-Up'!N$6:N$40),SUMIF('Marketing Stack'!$B$6:$B$40,$E84,'Marketing Stack'!N$6:N$40)) -> #REF! | ... V84: =IF('Absorption Schedule'!#REF!<90%,SUMIF('Marketing Stack - Lease-Up'!$B$6:$B$40,$E84,'Marketing Stack - Lease-Up'!P$6:P$40),SUMIF('Marketing Stack'!$B$6:$B$40,$E84,'Marketing Stack'!P$6:P$40)) -> #REF! | W84: =IF('Absorption Schedule'!#REF!<90%,SUMIF('Marketing Stack - Lease-Up'!$B$6:$B$40,$E84,'Marketing Stack - Lease-Up'!E$6:E$40),SUMIF('Marketing Stack'!$B$6:$B$40,$E84,'Marketing Stack'!E$6:E$40)) -> #REF! | X84: =IF('Absorption Schedule'!#REF!<90%,SUMIF('Marketing Stack - Lease-Up'!$B$6:$B$40,$E84,'Marketing Stack - Lease-Up'!F$6:F$40),SUMIF('Marketing Stack'!$B$6:$B$40,$E84,'Marketing Stack'!F$6:F$40)) -> #REF! | Y84: =IF('Absorption Schedule'!#REF!<90%,SUMIF('Marketing Stack - Lease-Up'!$B$6:$B$40,$E84,'Marketing Stack - Lease-Up'!G$6:G$40),SUMIF('Marketing Stack'!$B$6:$B$40,$E84,'Marketing Stack'!G$6:G$40)) -> #REF! | Z84: =IF('Absorption Schedule'!#REF!<90%,SUMIF('Marketing Stack - Lease-Up'!$B$6:$B$40,$E84,'Marketing Stack - Lease-Up'!H$6:H$40),SUMIF('Marketing Stack'!$B$6:$B$40,$E84,'Marketing Stack'!H$6:H$40)) -> #REF! | AA84: =IF('Absorption Schedule'!#REF!<90%,SUMIF('Marketing Stack - Lease-Up'!$B$6:$B$40,$E84,'Marketing Stack - Lease-Up'!I$6:I$40),SUMIF('Marketing Stack'!$B$6:$B$40,$E84,'Marketing Stack'!I$6:I$40)) -> #REF! | AB84: =IF('Absorption Schedule'!#REF!<90%,SUMIF('Marketing Stack - Lease-Up'!$B$6:$B$40,$E84,'Marketing Stack - Lease-Up'!J$6:J$40),SUMIF('Marketing Stack'!$B$6:$B$40,$E84,'Marketing Stack'!J$6:J$40)) -> #REF! | AC84: =IF('Absorption Schedule'!#REF!<90%,SUMIF('Marketing Stack - Lease-Up'!$B$6:$B$40,$E84,'Marketing Stack - Lease-Up'!K$6:K$40),SUMIF('Marketing Stack'!$B$6:$B$40,$E84,'Marketing Stack'!K$6:K$40)) -> #REF! | AD84: =IF('Absorption Schedule'!#REF!<90%,SUMIF('Marketing Stack - Lease-Up'!$B$6:$B$40,$E84,'Marketing Stack - Lease-Up'!L$6:L$40),SUMIF('Marketing Stack'!$B$6:$B$40,$E84,'Marketing Stack'!L$6:L$40)) -> #REF! | ... AH84: =IF('Absorption Schedule'!#REF!<90%,SUMIF('Marketing Stack - Lease-Up'!$B$6:$B$40,$E84,'Marketing Stack - Lease-Up'!P$6:P$40),SUMIF('Marketing Stack'!$B$6:$B$40,$E84,'Marketing Stack'!P$6:P$40)) -> #REF!
E85: Marketing | K85: =SUMIF('Marketing Stack - Lease-Up'!$B$6:$B$40,$E85,'Marketing Stack - Lease-Up'!E$6:E$40) -> 6214 | L85: =SUMIF('Marketing Stack - Lease-Up'!$B$6:$B$40,$E85,'Marketing Stack - Lease-Up'!F$6:F$40) -> 4839 | M85: =IF('Absorption Schedule'!#REF!<90%,SUMIF('Marketing Stack - Lease-Up'!$B$6:$B$40,$E85,'Marketing Stack - Lease-Up'!G$6:G$40),SUMIF('Marketing Stack'!$B$6:$B$40,$E85,'Marketing Stack'!G$6:G$40)) -> #REF! | N85: =IF('Absorption Schedule'!#REF!<90%,SUMIF('Marketing Stack - Lease-Up'!$B$6:$B$40,$E85,'Marketing Stack - Lease-Up'!H$6:H$40),SUMIF('Marketing Stack'!$B$6:$B$40,$E85,'Marketing Stack'!H$6:H$40)) -> #REF! | O85: =IF('Absorption Schedule'!#REF!<90%,SUMIF('Marketing Stack - Lease-Up'!$B$6:$B$40,$E85,'Marketing Stack - Lease-Up'!I$6:I$40),SUMIF('Marketing Stack'!$B$6:$B$40,$E85,'Marketing Stack'!I$6:I$40)) -> #REF! | P85: =IF('Absorption Schedule'!#REF!<90%,SUMIF('Marketing Stack - Lease-Up'!$B$6:$B$40,$E85,'Marketing Stack - Lease-Up'!J$6:J$40),SUMIF('Marketing Stack'!$B$6:$B$40,$E85,'Marketing Stack'!J$6:J$40)) -> #REF! | Q85: =IF('Absorption Schedule'!#REF!<90%,SUMIF('Marketing Stack - Lease-Up'!$B$6:$B$40,$E85,'Marketing Stack - Lease-Up'!K$6:K$40),SUMIF('Marketing Stack'!$B$6:$B$40,$E85,'Marketing Stack'!K$6:K$40)) -> #REF! | R85: =IF('Absorption Schedule'!#REF!<90%,SUMIF('Marketing Stack - Lease-Up'!$B$6:$B$40,$E85,'Marketing Stack - Lease-Up'!L$6:L$40),SUMIF('Marketing Stack'!$B$6:$B$40,$E85,'Marketing Stack'!L$6:L$40)) -> #REF! | S85: =IF('Absorption Schedule'!#REF!<90%,SUMIF('Marketing Stack - Lease-Up'!$B$6:$B$40,$E85,'Marketing Stack - Lease-Up'!M$6:M$40),SUMIF('Marketing Stack'!$B$6:$B$40,$E85,'Marketing Stack'!M$6:M$40)) -> #REF! | T85: =IF('Absorption Schedule'!#REF!<90%,SUMIF('Marketing Stack - Lease-Up'!$B$6:$B$40,$E85,'Marketing Stack - Lease-Up'!N$6:N$40),SUMIF('Marketing Stack'!$B$6:$B$40,$E85,'Marketing Stack'!N$6:N$40)) -> #REF! | ... V85: =IF('Absorption Schedule'!#REF!<90%,SUMIF('Marketing Stack - Lease-Up'!$B$6:$B$40,$E85,'Marketing Stack - Lease-Up'!P$6:P$40),SUMIF('Marketing Stack'!$B$6:$B$40,$E85,'Marketing Stack'!P$6:P$40)) -> #REF! | W85: =IF('Absorption Schedule'!#REF!<90%,SUMIF('Marketing Stack - Lease-Up'!$B$6:$B$40,$E85,'Marketing Stack - Lease-Up'!E$6:E$40),SUMIF('Marketing Stack'!$B$6:$B$40,$E85,'Marketing Stack'!E$6:E$40)) -> #REF! | X85: =IF('Absorption Schedule'!#REF!<90%,SUMIF('Marketing Stack - Lease-Up'!$B$6:$B$40,$E85,'Marketing Stack - Lease-Up'!F$6:F$40),SUMIF('Marketing Stack'!$B$6:$B$40,$E85,'Marketing Stack'!F$6:F$40)) -> #REF! | Y85: =IF('Absorption Schedule'!#REF!<90%,SUMIF('Marketing Stack - Lease-Up'!$B$6:$B$40,$E85,'Marketing Stack - Lease-Up'!G$6:G$40),SUMIF('Marketing Stack'!$B$6:$B$40,$E85,'Marketing Stack'!G$6:G$40)) -> #REF! | Z85: =IF('Absorption Schedule'!#REF!<90%,SUMIF('Marketing Stack - Lease-Up'!$B$6:$B$40,$E85,'Marketing Stack - Lease-Up'!H$6:H$40),SUMIF('Marketing Stack'!$B$6:$B$40,$E85,'Marketing Stack'!H$6:H$40)) -> #REF! | AA85: =IF('Absorption Schedule'!#REF!<90%,SUMIF('Marketing Stack - Lease-Up'!$B$6:$B$40,$E85,'Marketing Stack - Lease-Up'!I$6:I$40),SUMIF('Marketing Stack'!$B$6:$B$40,$E85,'Marketing Stack'!I$6:I$40)) -> #REF! | AB85: =IF('Absorption Schedule'!#REF!<90%,SUMIF('Marketing Stack - Lease-Up'!$B$6:$B$40,$E85,'Marketing Stack - Lease-Up'!J$6:J$40),SUMIF('Marketing Stack'!$B$6:$B$40,$E85,'Marketing Stack'!J$6:J$40)) -> #REF! | AC85: =IF('Absorption Schedule'!#REF!<90%,SUMIF('Marketing Stack - Lease-Up'!$B$6:$B$40,$E85,'Marketing Stack - Lease-Up'!K$6:K$40),SUMIF('Marketing Stack'!$B$6:$B$40,$E85,'Marketing Stack'!K$6:K$40)) -> #REF! | AD85: =IF('Absorption Schedule'!#REF!<90%,SUMIF('Marketing Stack - Lease-Up'!$B$6:$B$40,$E85,'Marketing Stack - Lease-Up'!L$6:L$40),SUMIF('Marketing Stack'!$B$6:$B$40,$E85,'Marketing Stack'!L$6:L$40)) -> #REF! | ... AH85: =IF('Absorption Schedule'!#REF!<90%,SUMIF('Marketing Stack - Lease-Up'!$B$6:$B$40,$E85,'Marketing Stack - Lease-Up'!P$6:P$40),SUMIF('Marketing Stack'!$B$6:$B$40,$E85,'Marketing Stack'!P$6:P$40)) -> #REF!
E86: Referral Fees | K86: =SUMIF('Marketing Stack - Lease-Up'!$B$6:$B$40,$E86,'Marketing Stack - Lease-Up'!E$6:E$40) -> 1761 | L86: =SUMIF('Marketing Stack - Lease-Up'!$B$6:$B$40,$E86,'Marketing Stack - Lease-Up'!F$6:F$40) -> 1761 | M86: =IF('Absorption Schedule'!#REF!<90%,SUMIF('Marketing Stack - Lease-Up'!$B$6:$B$40,$E86,'Marketing Stack - Lease-Up'!G$6:G$40),SUMIF('Marketing Stack'!$B$6:$B$40,$E86,'Marketing Stack'!G$6:G$40)) -> #REF! | N86: =IF('Absorption Schedule'!#REF!<90%,SUMIF('Marketing Stack - Lease-Up'!$B$6:$B$40,$E86,'Marketing Stack - Lease-Up'!H$6:H$40),SUMIF('Marketing Stack'!$B$6:$B$40,$E86,'Marketing Stack'!H$6:H$40)) -> #REF! | O86: =IF('Absorption Schedule'!#REF!<90%,SUMIF('Marketing Stack - Lease-Up'!$B$6:$B$40,$E86,'Marketing Stack - Lease-Up'!I$6:I$40),SUMIF('Marketing Stack'!$B$6:$B$40,$E86,'Marketing Stack'!I$6:I$40)) -> #REF! | P86: =IF('Absorption Schedule'!#REF!<90%,SUMIF('Marketing Stack - Lease-Up'!$B$6:$B$40,$E86,'Marketing Stack - Lease-Up'!J$6:J$40),SUMIF('Marketing Stack'!$B$6:$B$40,$E86,'Marketing Stack'!J$6:J$40)) -> #REF! | Q86: =IF('Absorption Schedule'!#REF!<90%,SUMIF('Marketing Stack - Lease-Up'!$B$6:$B$40,$E86,'Marketing Stack - Lease-Up'!K$6:K$40),SUMIF('Marketing Stack'!$B$6:$B$40,$E86,'Marketing Stack'!K$6:K$40)) -> #REF! | R86: =IF('Absorption Schedule'!#REF!<90%,SUMIF('Marketing Stack - Lease-Up'!$B$6:$B$40,$E86,'Marketing Stack - Lease-Up'!L$6:L$40),SUMIF('Marketing Stack'!$B$6:$B$40,$E86,'Marketing Stack'!L$6:L$40)) -> #REF! | S86: =IF('Absorption Schedule'!#REF!<90%,SUMIF('Marketing Stack - Lease-Up'!$B$6:$B$40,$E86,'Marketing Stack - Lease-Up'!M$6:M$40),SUMIF('Marketing Stack'!$B$6:$B$40,$E86,'Marketing Stack'!M$6:M$40)) -> #REF! | T86: =IF('Absorption Schedule'!#REF!<90%,SUMIF('Marketing Stack - Lease-Up'!$B$6:$B$40,$E86,'Marketing Stack - Lease-Up'!N$6:N$40),SUMIF('Marketing Stack'!$B$6:$B$40,$E86,'Marketing Stack'!N$6:N$40)) -> #REF! | ... V86: =IF('Absorption Schedule'!#REF!<90%,SUMIF('Marketing Stack - Lease-Up'!$B$6:$B$40,$E86,'Marketing Stack - Lease-Up'!P$6:P$40),SUMIF('Marketing Stack'!$B$6:$B$40,$E86,'Marketing Stack'!P$6:P$40)) -> #REF! | W86: =IF('Absorption Schedule'!#REF!<90%,SUMIF('Marketing Stack - Lease-Up'!$B$6:$B$40,$E86,'Marketing Stack - Lease-Up'!E$6:E$40),SUMIF('Marketing Stack'!$B$6:$B$40,$E86,'Marketing Stack'!E$6:E$40)) -> #REF! | X86: =IF('Absorption Schedule'!#REF!<90%,SUMIF('Marketing Stack - Lease-Up'!$B$6:$B$40,$E86,'Marketing Stack - Lease-Up'!F$6:F$40),SUMIF('Marketing Stack'!$B$6:$B$40,$E86,'Marketing Stack'!F$6:F$40)) -> #REF! | Y86: =IF('Absorption Schedule'!#REF!<90%,SUMIF('Marketing Stack - Lease-Up'!$B$6:$B$40,$E86,'Marketing Stack - Lease-Up'!G$6:G$40),SUMIF('Marketing Stack'!$B$6:$B$40,$E86,'Marketing Stack'!G$6:G$40)) -> #REF! | Z86: =IF('Absorption Schedule'!#REF!<90%,SUMIF('Marketing Stack - Lease-Up'!$B$6:$B$40,$E86,'Marketing Stack - Lease-Up'!H$6:H$40),SUMIF('Marketing Stack'!$B$6:$B$40,$E86,'Marketing Stack'!H$6:H$40)) -> #REF! | AA86: =IF('Absorption Schedule'!#REF!<90%,SUMIF('Marketing Stack - Lease-Up'!$B$6:$B$40,$E86,'Marketing Stack - Lease-Up'!I$6:I$40),SUMIF('Marketing Stack'!$B$6:$B$40,$E86,'Marketing Stack'!I$6:I$40)) -> #REF! | AB86: =IF('Absorption Schedule'!#REF!<90%,SUMIF('Marketing Stack - Lease-Up'!$B$6:$B$40,$E86,'Marketing Stack - Lease-Up'!J$6:J$40),SUMIF('Marketing Stack'!$B$6:$B$40,$E86,'Marketing Stack'!J$6:J$40)) -> #REF! | AC86: =IF('Absorption Schedule'!#REF!<90%,SUMIF('Marketing Stack - Lease-Up'!$B$6:$B$40,$E86,'Marketing Stack - Lease-Up'!K$6:K$40),SUMIF('Marketing Stack'!$B$6:$B$40,$E86,'Marketing Stack'!K$6:K$40)) -> #REF! | AD86: =IF('Absorption Schedule'!#REF!<90%,SUMIF('Marketing Stack - Lease-Up'!$B$6:$B$40,$E86,'Marketing Stack - Lease-Up'!L$6:L$40),SUMIF('Marketing Stack'!$B$6:$B$40,$E86,'Marketing Stack'!L$6:L$40)) -> #REF! | ... AH86: =IF('Absorption Schedule'!#REF!<90%,SUMIF('Marketing Stack - Lease-Up'!$B$6:$B$40,$E86,'Marketing Stack - Lease-Up'!P$6:P$40),SUMIF('Marketing Stack'!$B$6:$B$40,$E86,'Marketing Stack'!P$6:P$40)) -> #REF!
E87: Resident Retention | K87: =SUMIF('Marketing Stack - Lease-Up'!$B$6:$B$40,$E87,'Marketing Stack - Lease-Up'!E$6:E$40) -> 2000 | L87: =SUMIF('Marketing Stack - Lease-Up'!$B$6:$B$40,$E87,'Marketing Stack - Lease-Up'!F$6:F$40) -> 2000 | M87: =IF('Absorption Schedule'!#REF!<90%,SUMIF('Marketing Stack - Lease-Up'!$B$6:$B$40,$E87,'Marketing Stack - Lease-Up'!G$6:G$40),SUMIF('Marketing Stack'!$B$6:$B$40,$E87,'Marketing Stack'!G$6:G$40)) -> #REF! | N87: =IF('Absorption Schedule'!#REF!<90%,SUMIF('Marketing Stack - Lease-Up'!$B$6:$B$40,$E87,'Marketing Stack - Lease-Up'!H$6:H$40),SUMIF('Marketing Stack'!$B$6:$B$40,$E87,'Marketing Stack'!H$6:H$40)) -> #REF! | O87: =IF('Absorption Schedule'!#REF!<90%,SUMIF('Marketing Stack - Lease-Up'!$B$6:$B$40,$E87,'Marketing Stack - Lease-Up'!I$6:I$40),SUMIF('Marketing Stack'!$B$6:$B$40,$E87,'Marketing Stack'!I$6:I$40)) -> #REF! | P87: =IF('Absorption Schedule'!#REF!<90%,SUMIF('Marketing Stack - Lease-Up'!$B$6:$B$40,$E87,'Marketing Stack - Lease-Up'!J$6:J$40),SUMIF('Marketing Stack'!$B$6:$B$40,$E87,'Marketing Stack'!J$6:J$40)) -> #REF! | Q87: =IF('Absorption Schedule'!#REF!<90%,SUMIF('Marketing Stack - Lease-Up'!$B$6:$B$40,$E87,'Marketing Stack - Lease-Up'!K$6:K$40),SUMIF('Marketing Stack'!$B$6:$B$40,$E87,'Marketing Stack'!K$6:K$40)) -> #REF! | R87: =IF('Absorption Schedule'!#REF!<90%,SUMIF('Marketing Stack - Lease-Up'!$B$6:$B$40,$E87,'Marketing Stack - Lease-Up'!L$6:L$40),SUMIF('Marketing Stack'!$B$6:$B$40,$E87,'Marketing Stack'!L$6:L$40)) -> #REF! | S87: =IF('Absorption Schedule'!#REF!<90%,SUMIF('Marketing Stack - Lease-Up'!$B$6:$B$40,$E87,'Marketing Stack - Lease-Up'!M$6:M$40),SUMIF('Marketing Stack'!$B$6:$B$40,$E87,'Marketing Stack'!M$6:M$40)) -> #REF! | T87: =IF('Absorption Schedule'!#REF!<90%,SUMIF('Marketing Stack - Lease-Up'!$B$6:$B$40,$E87,'Marketing Stack - Lease-Up'!N$6:N$40),SUMIF('Marketing Stack'!$B$6:$B$40,$E87,'Marketing Stack'!N$6:N$40)) -> #REF! | ... V87: =IF('Absorption Schedule'!#REF!<90%,SUMIF('Marketing Stack - Lease-Up'!$B$6:$B$40,$E87,'Marketing Stack - Lease-Up'!P$6:P$40),SUMIF('Marketing Stack'!$B$6:$B$40,$E87,'Marketing Stack'!P$6:P$40)) -> #REF! | W87: =IF('Absorption Schedule'!#REF!<90%,SUMIF('Marketing Stack - Lease-Up'!$B$6:$B$40,$E87,'Marketing Stack - Lease-Up'!E$6:E$40),SUMIF('Marketing Stack'!$B$6:$B$40,$E87,'Marketing Stack'!E$6:E$40)) -> #REF! | X87: =IF('Absorption Schedule'!#REF!<90%,SUMIF('Marketing Stack - Lease-Up'!$B$6:$B$40,$E87,'Marketing Stack - Lease-Up'!F$6:F$40),SUMIF('Marketing Stack'!$B$6:$B$40,$E87,'Marketing Stack'!F$6:F$40)) -> #REF! | Y87: =IF('Absorption Schedule'!#REF!<90%,SUMIF('Marketing Stack - Lease-Up'!$B$6:$B$40,$E87,'Marketing Stack - Lease-Up'!G$6:G$40),SUMIF('Marketing Stack'!$B$6:$B$40,$E87,'Marketing Stack'!G$6:G$40)) -> #REF! | Z87: =IF('Absorption Schedule'!#REF!<90%,SUMIF('Marketing Stack - Lease-Up'!$B$6:$B$40,$E87,'Marketing Stack - Lease-Up'!H$6:H$40),SUMIF('Marketing Stack'!$B$6:$B$40,$E87,'Marketing Stack'!H$6:H$40)) -> #REF! | AA87: =IF('Absorption Schedule'!#REF!<90%,SUMIF('Marketing Stack - Lease-Up'!$B$6:$B$40,$E87,'Marketing Stack - Lease-Up'!I$6:I$40),SUMIF('Marketing Stack'!$B$6:$B$40,$E87,'Marketing Stack'!I$6:I$40)) -> #REF! | AB87: =IF('Absorption Schedule'!#REF!<90%,SUMIF('Marketing Stack - Lease-Up'!$B$6:$B$40,$E87,'Marketing Stack - Lease-Up'!J$6:J$40),SUMIF('Marketing Stack'!$B$6:$B$40,$E87,'Marketing Stack'!J$6:J$40)) -> #REF! | AC87: =IF('Absorption Schedule'!#REF!<90%,SUMIF('Marketing Stack - Lease-Up'!$B$6:$B$40,$E87,'Marketing Stack - Lease-Up'!K$6:K$40),SUMIF('Marketing Stack'!$B$6:$B$40,$E87,'Marketing Stack'!K$6:K$40)) -> #REF! | AD87: =IF('Absorption Schedule'!#REF!<90%,SUMIF('Marketing Stack - Lease-Up'!$B$6:$B$40,$E87,'Marketing Stack - Lease-Up'!L$6:L$40),SUMIF('Marketing Stack'!$B$6:$B$40,$E87,'Marketing Stack'!L$6:L$40)) -> #REF! | ... AH87: =IF('Absorption Schedule'!#REF!<90%,SUMIF('Marketing Stack - Lease-Up'!$B$6:$B$40,$E87,'Marketing Stack - Lease-Up'!P$6:P$40),SUMIF('Marketing Stack'!$B$6:$B$40,$E87,'Marketing Stack'!P$6:P$40)) -> #REF!
E88: Total Marketing | H88: =SUM(H83:H87) -> 0 | I88: =SUM(I83:I87) -> 0 | J88: =SUM(J83:J87) -> 0 | K88: =SUM(K83:K87) -> 12725 | L88: =SUM(L83:L87) -> 11350 | M88: =SUM(M83:M87) -> #REF! | N88: =SUM(N83:N87) -> #REF! | O88: =SUM(O83:O87) -> #REF! | ... AH88: =SUM(AH83:AH87) -> #REF!
